Workbook

Sheet README
B2: ATELIER NORTH PTE. LTD. | D2: SGD · synthetic data
B3: Synthetic FP&A portfolio model · model guide and conventions
C5: SYNTHETIC DATA | D5: All companies, transactions and financial data in this workbook are fictional and created solely to demonstrate financial-modelling and FP&A capabilities.
D6: Atelier North Pte. Ltd. does not exist. No client, employer, customer or confidential information appears in this file. The methodology, structure and controls reflect the approach used on real engagements; the numbers do not.
B8: MODEL AT A GLANCE
C9: Purpose | D9: A management decision tool for an owner-managed fashion retailer under short-term cash pressure.
C10: Key questions | D10: Will we run out of cash this quarter? Which channels make money? Is the flagship store viable? What should we do?
C11: Business | D11: Atelier North Pte. Ltd. - independent Singapore fashion / apparel retailer, owner-managed, books kept in Xero.
C12: Channels | D12: Flagship store · E-commerce · Events / pop-ups · Consignment partners
C13: Reporting currency | D13: Singapore Dollars (SGD). All lines are stated net of GST; GST is settled quarterly as a single payment.
C14: Historical period | D14: Six months ended 31 July 2026 (Feb-26 to Jul-26) - channel P&L and break-even base.
C15: Forecast period | D15: 13 weeks, Monday 3 August 2026 to Sunday 1 November 2026.
C16: Source data | D16: Xero trial balance and tracking categories, AP ageing and purchase-order commitments, POS and e-commerce reports.
B18: WORKBOOK NAVIGATION
C19: Dashboard | D19: One-page executive summary: eight KPI cards, four headline conclusions and four charts. Start here.
C20: Management Insights | D20: Seven findings, each with its commercial consequence and a recommended action.
C21: 13W Cash Flow | D21: Rolling 13-week forecast. Receipts by channel, outflows by cost line, closing cash against the minimum buffer.
C22: Channel Profitability | D22: Six-month management P&L by channel: contribution margin, then direct channel profit, then shared overhead.
C23: Store Break-Even | D23: Flagship store viability: break-even sales, margin of safety, two sensitivity grids and a driver ranking.
C24: Scenarios | D24: Continue / improve / exit, each with a full 13-week cash rebuild and the thresholds that decide between them.
C25: Assumptions | D25: Every hardcoded input in the model, in sixteen labelled sections. The only sheet you need to edit.
C26: Controls | D26: Thirty reconciliation and integrity checks. MODEL STATUS must read PASS before the pack is issued.
B28: CELL CONVENTIONS
C29: Hardcoded input | D29: Pale yellow fill with navy-blue text. These are the only cells intended to be edited.
C30: Formula | D30: Standard black text - calculated on the same sheet.
C31: Cross-sheet link | D31: Muted green text - pulls a value from another sheet in this workbook.
C32: Key output | D32: Bold navy on a light panel - a headline figure that feeds the Dashboard.
B34: METHODOLOGY AND LIMITATIONS
C35: Cash, not accruals | D35: Receipts run through channel-specific settlement lags; costs run through their actual payment dates. Payment timing is derived from the week dates, so rolling the forecast forward is a one-cell change.
C36: Contribution first | D36: Channels are judged on contribution margin and then on direct channel profit. Shared overhead is held back from the primary view; a fully-absorbed memo view is shown separately.
C37: Break-even | D37: Break-even sales = fixed store costs / contribution margin %, measured after the costs that genuinely move with store sales.
C38: Scenarios | D38: Each scenario rebuilds the weekly cash path from the same drivers. With neutral levers Scenario 1 reproduces the base case exactly - this is tested on the Controls tab.
C39: Limitations | D39: Thirteen weeks only: a liquidity tool, not a budget. No balance sheet or deferred tax. GST is a single quarterly settlement. Exit costs are illustrative estimates.
D41: Prepared as a portfolio work sample. Data synthetic; methodology as used in practice.

Sheet Dashboard
B2: ATELIER NORTH PTE. LTD. | P2: SGD · synthetic data
B3: Management dashboard · 13 weeks from 3 August 2026
B5: CASH POSITION AND RUNWAY
B6: OPENING CASH · WEEK 1 | F6: ENDING CASH · WEEK 13 | J6: LOWEST CASH POINT | N6: CASH RUNWAY
B7: ='13W Cash Flow'!$D$45 -> 205000 | F7: ='13W Cash Flow'!$D$46 -> 139650.22 | J7: ='13W Cash Flow'!$D$51 -> 114528.43 | N7: ='13W Cash Flow'!$D$56 -> 27.780548
B8: Bank balance at 3 August 2026 | F8: ="Net movement "&TEXT('13W Cash Flow'!$D$47,"""S$""#,##0;(""S$""#,##0)")&" over the quarter" -> Net movement (S$65,350) over the quarter | J8: ="Week "&'13W Cash Flow'!$D$52&" · minimum buffer "&TEXT('13W Cash Flow'!$D$41,"""S$""#,##0") -> Week 9 · minimum buffer S$120,000 | N8: To nil cash at the average weekly burn
B10: TRADING AND STORE VIABILITY
B11: NET REVENUE · 13 WEEKS | F11: GROSS MARGIN | J11: STORE PROFIT / (LOSS) PER MONTH | N11: STORE BREAK-EVEN GAP
B12: ='13W Cash Flow'!$Q$77 -> 747630.46 | F12: ='Channel Profitability'!$H$11 -> 0.59786244 | J12: ='Store Break-Even'!$D$28 -> -1104.72 | N12: ='Store Break-Even'!$D$35 -> -2108.2443
B13: Forecast across all four channels | F13: Six months ended 31 July 2026 | J13: After directly attributable fixed costs | N13: ="Break-even "&TEXT('Store Break-Even'!$D$32,"""S$""#,##0")&" per month" -> Break-even S$84,828 per month
B15: WHAT THIS MEANS
B16: ="Cash bottoms out at "&TEXT('13W Cash Flow'!$D$51,"""S$""#,##0")&" in Week "&'13W Cash Flow'!$D$52&IF('13W Cash Flow'!$D$54<0,", which is "&TEXT(-'13W Cash Flow'!$D$54,"""S$""#,##0")&" below the minimum buffer in "&'13W Cash Flow'!$D$55&IF('13W Cash Flow'!$D$55=1," week"," weeks"),", leaving "&TEXT('13W Cash Flow'!$D$54,"""S$""#,##0")&" of headroom")&", before recovering to "&TEXT('13W Cash Flow'!$D$46,"""S$""#,##0")&" by Week 13." -> Cash bottoms out at S$114,528 in Week 9, which is S$5,472 below the minimum buffer in 1 week, before recovering to S$139,650 by Week 13.
B17: ="Inventory and supplier payments take "&TEXT('13W Cash Flow'!$Q$21/'13W Cash Flow'!$Q$36,"0.0%")&" of 13-week outflows "&"("&TEXT('13W Cash Flow'!$Q$21,"""S$""#,##0")&") - the AW26 buy, not trading, is what drains the cash." -> Inventory and supplier payments take 52.5% of 13-week outflows (S$409,023) - the AW26 buy, not trading, is what drains the cash.
B18: ="The flagship store trades "&TEXT(ABS('Store Break-Even'!$D$36),"0.0%")&IF('Store Break-Even'!$D$36<0," below"," above")&" break-even, but earns the highest contribution margin of any channel at "&TEXT('Channel Profitability'!$D$23,"0.0%")&"; e-commerce delivers the largest direct channel profit at "&TEXT('Channel Profitability'!$E$34/6,"""S$""#,##0")&" per month." -> The flagship store trades 2.5% below break-even, but earns the highest contribution margin of any channel at 52.4%; e-commerce delivers the largest direct channel profit at S$28,478 per month.
B19: ="Store improvement ends Week 13 with "&TEXT(Scenarios!$E$63,"""S$""#,##0")&" of cash against "&TEXT(Scenarios!$D$63,"""S$""#,##0")&" as-is and "&TEXT(Scenarios!$F$63,"""S$""#,##0")&" on exit; closure needs "&TEXT(Scenarios!$F$72,"0.0%")&" of store demand to migrate online just to beat standing still." -> Store improvement ends Week 13 with S$163,302 of cash against S$139,650 as-is and S$110,579 on exit; closure needs 3.6% of store demand to migrate online just to beat standing still.
B55: All figures synthetic. Every KPI and chart on this page links directly to the calculation sheets - no dashboard number is keyed independently.
B101: CHART DATA - links to the model; nothing here is keyed independently
B102: Week | C102: Closing cash | D102: Minimum buffer
B103: ="W"&'13W Cash Flow'!D$6 -> W1 | C103: ='13W Cash Flow'!D$40 -> 229516.49 | D103: ='13W Cash Flow'!D$41 -> 120000
B104: ="W"&'13W Cash Flow'!E$6 -> W2 | C104: ='13W Cash Flow'!E$40 -> 210506.61 | D104: ='13W Cash Flow'!E$41 -> 120000
B105: ="W"&'13W Cash Flow'!F$6 -> W3 | C105: ='13W Cash Flow'!F$40 -> 237278.14 | D105: ='13W Cash Flow'!F$41 -> 120000
B106: ="W"&'13W Cash Flow'!G$6 -> W4 | C106: ='13W Cash Flow'!G$40 -> 265003.42 | D106: ='13W Cash Flow'!G$41 -> 120000
B107: ="W"&'13W Cash Flow'!H$6 -> W5 | C107: ='13W Cash Flow'!H$40 -> 173817.29 | D107: ='13W Cash Flow'!H$41 -> 120000
B108: ="W"&'13W Cash Flow'!I$6 -> W6 | C108: ='13W Cash Flow'!I$40 -> 196072.2 | D108: ='13W Cash Flow'!I$41 -> 120000
B109: ="W"&'13W Cash Flow'!J$6 -> W7 | C109: ='13W Cash Flow'!J$40 -> 232293.09 | D109: ='13W Cash Flow'!J$41 -> 120000
B110: ="W"&'13W Cash Flow'!K$6 -> W8 | C110: ='13W Cash Flow'!K$40 -> 180344.9 | D110: ='13W Cash Flow'!K$41 -> 120000
B111: ="W"&'13W Cash Flow'!L$6 -> W9 | C111: ='13W Cash Flow'!L$40 -> 114528.43 | D111: ='13W Cash Flow'!L$41 -> 120000
B112: ="W"&'13W Cash Flow'!M$6 -> W10 | C112: ='13W Cash Flow'!M$40 -> 134028.5 | D112: ='13W Cash Flow'!M$41 -> 120000
B113: ="W"&'13W Cash Flow'!N$6 -> W11 | C113: ='13W Cash Flow'!N$40 -> 129334.06 | D113: ='13W Cash Flow'!N$41 -> 120000
B114: ="W"&'13W Cash Flow'!O$6 -> W12 | C114: ='13W Cash Flow'!O$40 -> 160084.21 | D114: ='13W Cash Flow'!O$41 -> 120000
B115: ="W"&'13W Cash Flow'!P$6 -> W13 | C115: ='13W Cash Flow'!P$40 -> 139650.22 | D115: ='13W Cash Flow'!P$41 -> 120000
B117: Channel | C117: Contribution profit / month | D117: Direct channel profit / month
B118: ='Channel Profitability'!$D$5 -> Physical Store | C118: ='Channel Profitability'!$D$58 -> 43345.28 | D118: ='Channel Profitability'!$D$60 -> -1104.72
B119: ='Channel Profitability'!$E$5 -> E-commerce | C119: ='Channel Profitability'!$E$58 -> 34777.6 | D119: ='Channel Profitability'!$E$60 -> 28477.6
B120: ='Channel Profitability'!$F$5 -> Events / Pop-ups | C120: ='Channel Profitability'!$F$58 -> 12833.1 | D120: ='Channel Profitability'!$F$60 -> 12833.1
B121: ='Channel Profitability'!$G$5 -> Consignment | C121: ='Channel Profitability'!$G$58 -> 9690 | D121: ='Channel Profitability'!$G$60 -> 9690
B123: Flagship store | C123: SGD per month
B124: Current net sales | C124: ='Store Break-Even'!$D$34 -> 82720
B125: Break-even sales | C125: ='Store Break-Even'!$D$32 -> 84828.244
B127: Scenario | C127: Ending cash - Week 13 | D127: Lowest projected cash
B128: =Scenarios!$D$6 -> 1. Current Operations | C128: =Scenarios!$D$63 -> 139650.22 | D128: =Scenarios!$D$64 -> 114528.43
B129: =Scenarios!$E$6 -> 2. Store Improvement | C129: =Scenarios!$E$63 -> 163301.64 | D129: =Scenarios!$E$64 -> 130288.23
B130: =Scenarios!$F$6 -> 3. Store Exit / Channel Shift | C130: =Scenarios!$F$63 -> 110579.35 | D130: =Scenarios!$F$64 -> 79427.177

Sheet Management Insights
B2: ATELIER NORTH PTE. LTD. | D2: SGD · synthetic data
B3: Management summary · findings, consequences and recommended actions | D3: Back to Dashboard
B5: Finding | C5: Why it matters | D5: Recommended action
B6: 1. Cash headroom disappears in Week 9
B7: ="Cash falls from "&TEXT('13W Cash Flow'!$D$45,"""S$""#,##0")&" to "&TEXT('13W Cash Flow'!$D$51,"""S$""#,##0")&" in Week "&'13W Cash Flow'!$D$52&", a shortfall of "&TEXT(-'13W Cash Flow'!$D$54,"""S$""#,##0")&" against the "&TEXT('13W Cash Flow'!$D$41,"""S$""#,##0")&" buffer, before recovering to "&TEXT('13W Cash Flow'!$D$46,"""S$""#,##0")&" by Week 13." -> Cash falls from S$205,000 to S$114,528 in Week 9, a shortfall of S$5,472 against the S$120,000 buffer, before recovering to S$139,650 by Week 13. | C7: The business is not close to running out of cash, but it breaches its own liquidity policy in the week when the AW26 buy, month-end payroll, rent and quarterly GST all land together. One slow trading week or one supplier pulling terms forward turns a policy breach into a funding problem. | D7: Treat Weeks 8-11 as a managed cash window: move to weekly forecast reviews and agree a standby facility of roughly S$75,000 now, while the bank is looking at a profitable trading record.
B9: 2. Inventory timing, not trading, drains the cash
B10: ="Inventory and supplier payments absorb "&TEXT('13W Cash Flow'!$Q$21,"""S$""#,##0")&" of the "&TEXT('13W Cash Flow'!$Q$36,"""S$""#,##0")&" of 13-week outflows ("&TEXT('13W Cash Flow'!$Q$21/'13W Cash Flow'!$Q$36,"0.0%")&"), of which "&TEXT(Assumptions!$C$120,"""S$""#,##0")&" is the scheduled AW26 buy." -> Inventory and supplier payments absorb S$409,023 of the S$779,039 of 13-week outflows (52.5%), of which S$235,000 is the scheduled AW26 buy. | C10: This is a working-capital timing problem wearing the costume of a profitability problem. Cutting operating cost would do far less for cash than moving one payment date, and would damage trading. | D10: Split the Week 8 tranche 60/40 across Weeks 8 and 12, or move the balance to 45-day terms. Re-phasing about S$33,000 keeps every week above the buffer without touching stock intake.
B12: 3. The store trades marginally below break-even
B13: ="Store net sales of "&TEXT('Store Break-Even'!$D$34,"""S$""#,##0")&" per month sit "&TEXT(ABS('Store Break-Even'!$D$36),"0.0%")&" below a break-even of "&TEXT('Store Break-Even'!$D$32,"""S$""#,##0")&", a monthly result of "&TEXT('Store Break-Even'!$D$28,"""S$""#,##0;(""S$""#,##0)")&"." -> Store net sales of S$82,720 per month sit 2.5% below a break-even of S$84,828, a monthly result of (S$1,105). | C13: ="The store is a rounding error away from covering its own costs. The driver ranking shows sales and gross margin move store profit roughly "&TEXT(MIN('Store Break-Even'!$G$66,'Store Break-Even'!$G$67)/MAX('Store Break-Even'!$G$68,'Store Break-Even'!$G$69),"0.0")&" to "&TEXT(MAX('Store Break-Even'!$G$66,'Store Break-Even'!$G$67)/MIN('Store Break-Even'!$G$68,'Store Break-Even'!$G$69),"0.0")&" times as hard as a proportionate move in rent or payroll, so this is a trading question, not a cost-cutting question." -> The store is a rounding error away from covering its own costs. The driver ranking shows sales and gross margin move store profit roughly 2.0 to 2.6 times as hard as a proportionate move in rent or payroll, so this is a trading question, not a cost-cutting question. | D13: ="Set a time-boxed trading threshold rather than debating closure: the store must reach "&TEXT('Store Break-Even'!$D$32,"""S$""#,##0")&" of monthly net sales within two quarters. Track it monthly and decide on evidence at the lease break." -> Set a time-boxed trading threshold rather than debating closure: the store must reach S$84,828 of monthly net sales within two quarters. Track it monthly and decide on evidence at the lease break.
B15: 4. Best margin per sale, worst fixed-cost recovery
B16: ="The store returns the highest contribution margin of any channel at "&TEXT('Channel Profitability'!$D$23,"0.0%")&" against e-commerce at "&TEXT('Channel Profitability'!$E$23,"0.0%")&", yet after direct fixed costs e-commerce earns "&TEXT('Channel Profitability'!$E$34/6,"""S$""#,##0")&" a month and the store "&TEXT('Channel Profitability'!$D$34/6,"""S$""#,##0;(""S$""#,##0)")&"." -> The store returns the highest contribution margin of any channel at 52.4% against e-commerce at 41.6%, yet after direct fixed costs e-commerce earns S$28,478 a month and the store (S$1,105). | C16: Judging channels on gross margin alone would keep the store and starve e-commerce. The store's problem is the rent and base payroll it must clear before the first sale counts. | D16: Judge channels on direct channel profit, not gross margin, and keep shared overhead unallocated in the management pack. Fund e-commerce while marginal contribution exceeds marginal media cost.
B18: 5. Consignment: lowest realised margin, slowest cash
B19: ="Consignment turns a "&TEXT('Channel Profitability'!$G$11,"0.0%")&" product gross margin into a "&TEXT('Channel Profitability'!$G$23,"0.0%")&" contribution margin after a "&TEXT(Assumptions!$C$42,"0.0%")&" partner commission, and the cash arrives "&Assumptions!$C$70&" weeks after the sale." -> Consignment turns a 60.0% product gross margin into a 28.5% contribution margin after a 30.0% partner commission, and the cash arrives 4 weeks after the sale. | C19: Consignment is a distribution channel and an interest-free loan to the partner at the same time. It earns real contribution and needs no fixed cost, so it should not be cut - but it is the worst channel to grow while cash is tight. | D19: Hold consignment at its current scale through the AW26 window. At contract review push for fortnightly remittance or a commission step-down above an agreed monthly volume.
B21: 6. Events are the best margin but cannot be relied on
B22: ="Events return the highest gross margin in the business at "&TEXT('Channel Profitability'!$F$11,"0.0%")&" and a "&TEXT('Channel Profitability'!$F$23,"0.0%")&" contribution margin with no fixed cost, on "&TEXT('Channel Profitability'!$F$8/6,"""S$""#,##0")&" of net revenue per month - but nil in two of the six historical months." -> Events return the highest gross margin in the business at 64.0% and a 44.1% contribution margin with no fixed cost, on S$29,100 of net revenue per month - but nil in two of the six historical months. | C22: Events flatter the average and hide the variance. They cannot replace recurring store or online revenue, and building a fixed-cost base on them would turn a tight quarter into a bad one. | D22: Contract four to six pop-ups per quarter a quarter ahead so the forecast carries real dates. Model them conservatively and treat any upside as cash buffer, not budget.
B24: 7. Improve the store; keep exit as the fallback
B25: ="Monthly run-rate operating profit is "&TEXT(Scenarios!$D$50,"""S$""#,##0")&" as-is, "&TEXT(Scenarios!$E$50,"""S$""#,##0")&" under improvement and "&TEXT(Scenarios!$F$50,"""S$""#,##0")&" on exit; Week 13 cash is "&TEXT(Scenarios!$D$63,"""S$""#,##0")&" / "&TEXT(Scenarios!$E$63,"""S$""#,##0")&" / "&TEXT(Scenarios!$F$63,"""S$""#,##0")&"." -> Monthly run-rate operating profit is S$20,196 as-is, S$27,343 under improvement and S$27,088 on exit; Week 13 cash is S$139,650 / S$163,302 / S$110,579. | C25: ="Exit removes a fixed-cost base the store is not covering, but it consumes cash at the worst possible moment: the exit case spends "&TEXT(Scenarios!$F$67,"0")&" of the 13 weeks below the minimum cash buffer and ends the quarter at "&TEXT(Scenarios!$F$63,"""S$""#,##0")&" against "&TEXT(Scenarios!$E$63,"""S$""#,##0")&" under improvement. It also permanently removes about a quarter of group revenue and needs "&TEXT(Scenarios!$F$73,"0.0%")&" online migration merely to match the improvement case - against the "&TEXT(Scenarios!$F$12,"0.0%")&" assumed." -> Exit removes a fixed-cost base the store is not covering, but it consumes cash at the worst possible moment: the exit case spends 6 of the 13 weeks below the minimum cash buffer and ends the quarter at S$110,579 against S$163,302 under improvement. It also permanently removes about a quarter of group revenue and needs 25.8% online migration merely to match the improvement case - against the 25.0% assumed. | D25: Adopt the improvement case for two quarters with its sales and margin targets written into store objectives. Review at the lease break and, if the threshold is missed, execute the exit then - having first run a controlled migration test to replace the 25% assumption with evidence.
B27: Every figure quoted above is a live link to the model - change an assumption and these sentences change with it.

Sheet 13W Cash Flow
B2: ATELIER NORTH PTE. LTD. | R2: SGD · synthetic data
B3: Rolling 13-week cash-flow forecast · week commencing Monday 3 August 2026 | R3: Back to Dashboard
B5: SGD | C5: Timing driver | D5: Week 1 | E5: Week 2 | F5: Week 3 | G5: Week 4 | H5: Week 5 | I5: Week 6 | J5: Week 7 | K5: Week 8 | L5: Week 9 | M5: Week 10 | N5: Week 11 | O5: Week 12 | P5: Week 13 | Q5: 13-Week Total | R5: Weekly Average
B6: Week number | D6: 1 | E6: =D6+1 -> 2 | F6: =E6+1 -> 3 | G6: =F6+1 -> 4 | H6: =G6+1 -> 5 | I6: =H6+1 -> 6 | J6: =I6+1 -> 7 | K6: =J6+1 -> 8 | L6: =K6+1 -> 9 | ... P6: =O6+1 -> 13
B7: Week commencing | D7: =Assumptions!$C$8 -> 46237 | E7: =D7+7 -> 46244 | F7: =E7+7 -> 46251 | G7: =F7+7 -> 46258 | H7: =G7+7 -> 46265 | I7: =H7+7 -> 46272 | J7: =I7+7 -> 46279 | K7: =J7+7 -> 46286 | L7: =K7+7 -> 46293 | ... P7: =O7+7 -> 46321
B8: Week ending | D8: =D7+6 -> 46243 | E8: =E7+6 -> 46250 | F8: =F7+6 -> 46257 | G8: =G7+6 -> 46264 | H8: =H7+6 -> 46271 | I8: =I7+6 -> 46278 | J8: =J7+6 -> 46285 | K8: =K7+6 -> 46292 | ... P8: =P7+6 -> 46327
B10: OPENING CASH | C10: prior week close | D10: =Assumptions!$C$13 -> 205000 | E10: =D40 -> 229516.49 | F10: =E40 -> 210506.61 | G10: =F40 -> 237278.14 | H10: =G40 -> 265003.42 | I10: =H40 -> 173817.29 | J10: =I40 -> 196072.2 | K10: =J40 -> 232293.09 | L10: =K40 -> 180344.9 | ... P10: =O40 -> 160084.21
B12: CASH RECEIPTS
B13: Physical store receipts | C13: 92% same week | D13: =D73*Assumptions!$C$67+IF(D$6=1,Assumptions!$C$72,INDEX($D$73:$P$73,1,D$6-1)*(1-Assumptions!$C$67)) -> 18197.668 | E13: =E73*Assumptions!$C$67+IF(E$6=1,Assumptions!$C$72,INDEX($D$73:$P$73,1,E$6-1)*(1-Assumptions!$C$67)) -> 20410.107 | F13: =F73*Assumptions!$C$67+IF(F$6=1,Assumptions!$C$72,INDEX($D$73:$P$73,1,F$6-1)*(1-Assumptions!$C$67)) -> 17799.69 | G13: =G73*Assumptions!$C$67+IF(G$6=1,Assumptions!$C$72,INDEX($D$73:$P$73,1,G$6-1)*(1-Assumptions!$C$67)) -> 17204.331 | H13: =H73*Assumptions!$C$67+IF(H$6=1,Assumptions!$C$72,INDEX($D$73:$P$73,1,H$6-1)*(1-Assumptions!$C$67)) -> 17700.463 | I13: =I73*Assumptions!$C$67+IF(I$6=1,Assumptions!$C$72,INDEX($D$73:$P$73,1,I$6-1)*(1-Assumptions!$C$67)) -> 18448.478 | J13: =J73*Assumptions!$C$67+IF(J$6=1,Assumptions!$C$72,INDEX($D$73:$P$73,1,J$6-1)*(1-Assumptions!$C$67)) -> 19036.203 | K13: =K73*Assumptions!$C$67+IF(K$6=1,Assumptions!$C$72,INDEX($D$73:$P$73,1,K$6-1)*(1-Assumptions!$C$67)) -> 19433.109 | ... P13: =P73*Assumptions!$C$67+IF(P$6=1,Assumptions!$C$72,INDEX($D$73:$P$73,1,P$6-1)*(1-Assumptions!$C$67)) -> 21692.418 | Q13: =SUM(D13:P13) -> 249372.28 | R13: =AVERAGE(D13:P13) -> 19182.483
B14: E-commerce receipts | C14: 85% same week | D14: =D74*Assumptions!$C$68+IF(D$6=1,Assumptions!$C$73,INDEX($D$74:$P$74,1,D$6-1)*(1-Assumptions!$C$68)) -> 21016.22 | E14: =E74*Assumptions!$C$68+IF(E$6=1,Assumptions!$C$73,INDEX($D$74:$P$74,1,E$6-1)*(1-Assumptions!$C$68)) -> 22379.28 | F14: =F74*Assumptions!$C$68+IF(F$6=1,Assumptions!$C$73,INDEX($D$74:$P$74,1,F$6-1)*(1-Assumptions!$C$68)) -> 20988.66 | G14: =G74*Assumptions!$C$68+IF(G$6=1,Assumptions!$C$73,INDEX($D$74:$P$74,1,G$6-1)*(1-Assumptions!$C$68)) -> 20514.34 | H14: =H74*Assumptions!$C$68+IF(H$6=1,Assumptions!$C$73,INDEX($D$74:$P$74,1,H$6-1)*(1-Assumptions!$C$68)) -> 21215.04 | I14: =I74*Assumptions!$C$68+IF(I$6=1,Assumptions!$C$73,INDEX($D$74:$P$74,1,I$6-1)*(1-Assumptions!$C$68)) -> 21894.18 | J14: =J74*Assumptions!$C$68+IF(J$6=1,Assumptions!$C$73,INDEX($D$74:$P$74,1,J$6-1)*(1-Assumptions!$C$68)) -> 22357.72 | K14: =K74*Assumptions!$C$68+IF(K$6=1,Assumptions!$C$73,INDEX($D$74:$P$74,1,K$6-1)*(1-Assumptions!$C$68)) -> 22788.92 | ... P14: =P74*Assumptions!$C$68+IF(P$6=1,Assumptions!$C$73,INDEX($D$74:$P$74,1,P$6-1)*(1-Assumptions!$C$68)) -> 25710.3 | Q14: =SUM(D14:P14) -> 293437.6 | R14: =AVERAGE(D14:P14) -> 22572.123
B15: Events / pop-up receipts | C15: banked at event | D15: =D75*Assumptions!$C$69+IF(D$6=1,0,INDEX($D$75:$P$75,1,D$6-1)*(1-Assumptions!$C$69)) -> 0 | E15: =E75*Assumptions!$C$69+IF(E$6=1,0,INDEX($D$75:$P$75,1,E$6-1)*(1-Assumptions!$C$69)) -> 23280 | F15: =F75*Assumptions!$C$69+IF(F$6=1,0,INDEX($D$75:$P$75,1,F$6-1)*(1-Assumptions!$C$69)) -> 0 | G15: =G75*Assumptions!$C$69+IF(G$6=1,0,INDEX($D$75:$P$75,1,G$6-1)*(1-Assumptions!$C$69)) -> 0 | H15: =H75*Assumptions!$C$69+IF(H$6=1,0,INDEX($D$75:$P$75,1,H$6-1)*(1-Assumptions!$C$69)) -> 0 | I15: =I75*Assumptions!$C$69+IF(I$6=1,0,INDEX($D$75:$P$75,1,I$6-1)*(1-Assumptions!$C$69)) -> 0 | J15: =J75*Assumptions!$C$69+IF(J$6=1,0,INDEX($D$75:$P$75,1,J$6-1)*(1-Assumptions!$C$69)) -> 18624 | K15: =K75*Assumptions!$C$69+IF(K$6=1,0,INDEX($D$75:$P$75,1,K$6-1)*(1-Assumptions!$C$69)) -> 0 | ... P15: =P75*Assumptions!$C$69+IF(P$6=1,0,INDEX($D$75:$P$75,1,P$6-1)*(1-Assumptions!$C$69)) -> 25608 | Q15: =SUM(D15:P15) -> 100104 | R15: =AVERAGE(D15:P15) -> 7700.3077
B16: Consignment receipts (net of partner commission) | C16: 4-week lag | D16: =IF(D$6<=Assumptions!$C$70,Assumptions!$C$74/Assumptions!$C$70,INDEX($D$76:$P$76,1,D$6-Assumptions!$C$70)*(1-Assumptions!$C$42)) -> 5495 | E16: =IF(E$6<=Assumptions!$C$70,Assumptions!$C$74/Assumptions!$C$70,INDEX($D$76:$P$76,1,E$6-Assumptions!$C$70)*(1-Assumptions!$C$42)) -> 5495 | F16: =IF(F$6<=Assumptions!$C$70,Assumptions!$C$74/Assumptions!$C$70,INDEX($D$76:$P$76,1,F$6-Assumptions!$C$70)*(1-Assumptions!$C$42)) -> 5495 | G16: =IF(G$6<=Assumptions!$C$70,Assumptions!$C$74/Assumptions!$C$70,INDEX($D$76:$P$76,1,G$6-Assumptions!$C$70)*(1-Assumptions!$C$42)) -> 5495 | H16: =IF(H$6<=Assumptions!$C$70,Assumptions!$C$74/Assumptions!$C$70,INDEX($D$76:$P$76,1,H$6-Assumptions!$C$70)*(1-Assumptions!$C$42)) -> 5275.2 | I16: =IF(I$6<=Assumptions!$C$70,Assumptions!$C$74/Assumptions!$C$70,INDEX($D$76:$P$76,1,I$6-Assumptions!$C$70)*(1-Assumptions!$C$42)) -> 5495 | J16: =IF(J$6<=Assumptions!$C$70,Assumptions!$C$74/Assumptions!$C$70,INDEX($D$76:$P$76,1,J$6-Assumptions!$C$70)*(1-Assumptions!$C$42)) -> 5220.25 | K16: =IF(K$6<=Assumptions!$C$70,Assumptions!$C$74/Assumptions!$C$70,INDEX($D$76:$P$76,1,K$6-Assumptions!$C$70)*(1-Assumptions!$C$42)) -> 5165.3 | ... P16: =IF(P$6<=Assumptions!$C$70,Assumptions!$C$74/Assumptions!$C$70,INDEX($D$76:$P$76,1,P$6-Assumptions!$C$70)*(1-Assumptions!$C$42)) -> 5549.95 | Q16: =SUM(D16:P16) -> 70775.6 | R16: =AVERAGE(D16:P16) -> 5444.2769
B17: Other / one-off receipts | C17: one-off schedule | D17: =IF(D$6=Assumptions!$C$125,Assumptions!$C$124,0) -> 0 | E17: =IF(E$6=Assumptions!$C$125,Assumptions!$C$124,0) -> 0 | F17: =IF(F$6=Assumptions!$C$125,Assumptions!$C$124,0) -> 0 | G17: =IF(G$6=Assumptions!$C$125,Assumptions!$C$124,0) -> 0 | H17: =IF(H$6=Assumptions!$C$125,Assumptions!$C$124,0) -> 0 | I17: =IF(I$6=Assumptions!$C$125,Assumptions!$C$124,0) -> 0 | J17: =IF(J$6=Assumptions!$C$125,Assumptions!$C$124,0) -> 0 | K17: =IF(K$6=Assumptions!$C$125,Assumptions!$C$124,0) -> 0 | ... P17: =IF(P$6=Assumptions!$C$125,Assumptions!$C$124,0) -> 0 | Q17: =SUM(D17:P17) -> 0 | R17: =AVERAGE(D17:P17) -> 0
B18: Total cash receipts | D18: =SUM(D13:D17) -> 44708.888 | E18: =SUM(E13:E17) -> 71564.387 | F18: =SUM(F13:F17) -> 44283.35 | G18: =SUM(G13:G17) -> 43213.671 | H18: =SUM(H13:H17) -> 44190.703 | I18: =SUM(I13:I17) -> 45837.658 | J18: =SUM(J13:J17) -> 65238.173 | K18: =SUM(K13:K17) -> 47387.329 | ... P18: =SUM(P13:P17) -> 78560.668 | Q18: =SUM(D18:P18) -> 713689.48 | R18: =AVERAGE(D18:P18) -> 54899.191
B20: CASH OUTFLOWS
B21: Inventory and supplier payments | C21: replenish + AW26 buy | D21: =D89 -> 11016.171 | E21: =E89 -> 70954.325 | F21: =F89 -> 10808.488 | G21: =G89 -> 10647.29 | H21: =H89 -> 57041.454 | I21: =I89 -> 11432.082 | J21: =J89 -> 15596.687 | K21: =K89 -> 93919.214 | ... P21: =P89 -> 18688.146 | Q21: =SUM(D21:P21) -> 409023.13 | R21: =AVERAGE(D21:P21) -> 31463.318
B22: Store payroll | C22: month end | D22: =Assumptions!$C$47*D70 -> 0 | E22: =Assumptions!$C$47*E70 -> 0 | F22: =Assumptions!$C$47*F70 -> 0 | G22: =Assumptions!$C$47*G70 -> 0 | H22: =Assumptions!$C$47*H70 -> 18500 | I22: =Assumptions!$C$47*I70 -> 0 | J22: =Assumptions!$C$47*J70 -> 0 | K22: =Assumptions!$C$47*K70 -> 0 | ... P22: =Assumptions!$C$47*P70 -> 18500 | Q22: =SUM(D22:P22) -> 55500 | R22: =AVERAGE(D22:P22) -> 4269.2308
B23: Corporate and admin payroll | C23: month end | D23: =Assumptions!$C$92*D70 -> 0 | E23: =Assumptions!$C$92*E70 -> 0 | F23: =Assumptions!$C$92*F70 -> 0 | G23: =Assumptions!$C$92*G70 -> 0 | H23: =Assumptions!$C$92*H70 -> 26200 | I23: =Assumptions!$C$92*I70 -> 0 | J23: =Assumptions!$C$92*J70 -> 0 | K23: =Assumptions!$C$92*K70 -> 0 | ... P23: =Assumptions!$C$92*P70 -> 26200 | Q23: =SUM(D23:P23) -> 78600 | R23: =AVERAGE(D23:P23) -> 6046.1538
B24: Rent | C24: 1st of month | D24: =Assumptions!$C$46*D65 -> 0 | E24: =Assumptions!$C$46*E65 -> 0 | F24: =Assumptions!$C$46*F65 -> 0 | G24: =Assumptions!$C$46*G65 -> 0 | H24: =Assumptions!$C$46*H65 -> 22000 | I24: =Assumptions!$C$46*I65 -> 0 | J24: =Assumptions!$C$46*J65 -> 0 | K24: =Assumptions!$C$46*K65 -> 0 | ... P24: =Assumptions!$C$46*P65 -> 22000 | Q24: =SUM(D24:P24) -> 66000 | R24: =AVERAGE(D24:P24) -> 5076.9231
B25: Digital and brand marketing | C25: % of e-comm + monthly | D25: =D74*Assumptions!$C$40+Assumptions!$C$62*D67 -> 1882.188 | E25: =E74*Assumptions!$C$40+Assumptions!$C$62*E67 -> 6537.42 | F25: =F74*Assumptions!$C$40+Assumptions!$C$62*F67 -> 1862.784 | G25: =G74*Assumptions!$C$40+Assumptions!$C$62*G67 -> 1843.38 | H25: =H74*Assumptions!$C$40+Assumptions!$C$62*H67 -> 1920.996 | I25: =I74*Assumptions!$C$40+Assumptions!$C$62*I67 -> 6479.208 | J25: =J74*Assumptions!$C$40+Assumptions!$C$62*J67 -> 2018.016 | K25: =K74*Assumptions!$C$40+Assumptions!$C$62*K67 -> 2056.824 | ... P25: =P74*Assumptions!$C$40+Assumptions!$C$62*P67 -> 2328.48 | Q25: =SUM(D25:P25) -> 39967.056 | R25: =AVERAGE(D25:P25) -> 3074.3889
B26: Shipping, fulfilment and handling | C26: % of sales | D26: =D74*Assumptions!$C$39+D76*Assumptions!$C$43 -> 1472.398 | E26: =E74*Assumptions!$C$39+E76*Assumptions!$C$43 -> 1589.22 | F26: =F74*Assumptions!$C$39+F76*Assumptions!$C$43 -> 1457.2065 | G26: =G74*Assumptions!$C$39+G76*Assumptions!$C$43 -> 1442.015 | H26: =H74*Assumptions!$C$39+H76*Assumptions!$C$43 -> 1501.6035 | I26: =I74*Assumptions!$C$39+I76*Assumptions!$C$43 -> 1547.178 | J26: =J74*Assumptions!$C$39+J76*Assumptions!$C$43 -> 1577.561 | K26: =K74*Assumptions!$C$39+K76*Assumptions!$C$43 -> 1606.7665 | ... P26: =P74*Assumptions!$C$39+P76*Assumptions!$C$43 -> 1813.56 | Q26: =SUM(D26:P26) -> 20672.929 | R26: =AVERAGE(D26:P26) -> 1590.2253
B27: Merchant and payment fees | C27: % of sales | D27: =D73*Assumptions!$C$34+D74*Assumptions!$C$35+D75*Assumptions!$C$36 -> 932.785 | E27: =E73*Assumptions!$C$34+E74*Assumptions!$C$35+E75*Assumptions!$C$36 -> 1469.7761 | F27: =F73*Assumptions!$C$34+F74*Assumptions!$C$35+F75*Assumptions!$C$36 -> 916.22832 | G27: =G73*Assumptions!$C$34+G74*Assumptions!$C$35+G75*Assumptions!$C$36 -> 903.1064 | H27: =H73*Assumptions!$C$34+H74*Assumptions!$C$35+H75*Assumptions!$C$36 -> 938.42028 | I27: =I73*Assumptions!$C$34+I74*Assumptions!$C$35+I75*Assumptions!$C$36 -> 970.91652 | J27: =J73*Assumptions!$C$34+J74*Assumptions!$C$35+J75*Assumptions!$C$36 -> 1347.5816 | K27: =K73*Assumptions!$C$34+K74*Assumptions!$C$35+K75*Assumptions!$C$36 -> 1013.0999 | ... P27: =P73*Assumptions!$C$34+P74*Assumptions!$C$35+P75*Assumptions!$C$36 -> 1628.4026 | Q27: =SUM(D27:P27) -> 14922.916 | R27: =AVERAGE(D27:P27) -> 1147.9166
B28: Event costs | C28: % of event sales | D28: =D75*Assumptions!$C$41 -> 0 | E28: =E75*Assumptions!$C$41 -> 4190.4 | F28: =F75*Assumptions!$C$41 -> 0 | G28: =G75*Assumptions!$C$41 -> 0 | H28: =H75*Assumptions!$C$41 -> 0 | I28: =I75*Assumptions!$C$41 -> 0 | J28: =J75*Assumptions!$C$41 -> 3352.32 | K28: =K75*Assumptions!$C$41 -> 0 | ... P28: =P75*Assumptions!$C$41 -> 4609.44 | Q28: =SUM(D28:P28) -> 18018.72 | R28: =AVERAGE(D28:P28) -> 1386.0554
B29: Store variable labour | C29: % of store sales | D29: =D73*Assumptions!$C$37 -> 543.837 | E29: =E73*Assumptions!$C$37 -> 618.2568 | F29: =F73*Assumptions!$C$37 -> 526.6632 | G29: =G73*Assumptions!$C$37 -> 515.214 | H29: =H73*Assumptions!$C$37 -> 532.3878 | I29: =I73*Assumptions!$C$37 -> 555.2862 | J29: =J73*Assumptions!$C$37 -> 572.46 | K29: =K73*Assumptions!$C$37 -> 583.9092 | ... P29: =P73*Assumptions!$C$37 -> 652.6044 | Q29: =SUM(D29:P29) -> 7487.7768 | R29: =AVERAGE(D29:P29) -> 575.98283
B30: Utilities and service charge | C30: 15th | D30: =Assumptions!$C$48*D68 -> 0 | E30: =Assumptions!$C$48*E68 -> 2600 | F30: =Assumptions!$C$48*F68 -> 0 | G30: =Assumptions!$C$48*G68 -> 0 | H30: =Assumptions!$C$48*H68 -> 0 | I30: =Assumptions!$C$48*I68 -> 0 | J30: =Assumptions!$C$48*J68 -> 2600 | K30: =Assumptions!$C$48*K68 -> 0 | ... P30: =Assumptions!$C$48*P68 -> 0 | Q30: =SUM(D30:P30) -> 7800 | R30: =AVERAGE(D30:P30) -> 600
B31: Software and subscriptions | C31: 10th | D31: =Assumptions!$C$93*D67 -> 0 | E31: =Assumptions!$C$93*E67 -> 2450 | F31: =Assumptions!$C$93*F67 -> 0 | G31: =Assumptions!$C$93*G67 -> 0 | H31: =Assumptions!$C$93*H67 -> 0 | I31: =Assumptions!$C$93*I67 -> 2450 | J31: =Assumptions!$C$93*J67 -> 0 | K31: =Assumptions!$C$93*K67 -> 0 | ... P31: =Assumptions!$C$93*P67 -> 0 | Q31: =SUM(D31:P31) -> 7350 | R31: =AVERAGE(D31:P31) -> 565.38462
B32: Professional fees | C32: 20th | D32: =Assumptions!$C$60*D69 -> 0 | E32: =Assumptions!$C$60*E69 -> 0 | F32: =Assumptions!$C$60*F69 -> 1800 | G32: =Assumptions!$C$60*G69 -> 0 | H32: =Assumptions!$C$60*H69 -> 0 | I32: =Assumptions!$C$60*I69 -> 0 | J32: =Assumptions!$C$60*J69 -> 1800 | K32: =Assumptions!$C$60*K69 -> 0 | ... P32: =Assumptions!$C$60*P69 -> 0 | Q32: =SUM(D32:P32) -> 5400 | R32: =AVERAGE(D32:P32) -> 415.38462
B33: GST settlement | C33: quarterly | D33: =IF(D$6=Assumptions!$C$89,Assumptions!$C$88,0) -> 0 | E33: =IF(E$6=Assumptions!$C$89,Assumptions!$C$88,0) -> 0 | F33: =IF(F$6=Assumptions!$C$89,Assumptions!$C$88,0) -> 0 | G33: =IF(G$6=Assumptions!$C$89,Assumptions!$C$88,0) -> 0 | H33: =IF(H$6=Assumptions!$C$89,Assumptions!$C$88,0) -> 0 | I33: =IF(I$6=Assumptions!$C$89,Assumptions!$C$88,0) -> 0 | J33: =IF(J$6=Assumptions!$C$89,Assumptions!$C$88,0) -> 0 | K33: =IF(K$6=Assumptions!$C$89,Assumptions!$C$88,0) -> 0 | ... P33: =IF(P$6=Assumptions!$C$89,Assumptions!$C$88,0) -> 0 | Q33: =SUM(D33:P33) -> 26500 | R33: =AVERAGE(D33:P33) -> 2038.4615
B34: Term loan repayment | C34: 5th | D34: =Assumptions!$C$87*D66 -> 4200 | E34: =Assumptions!$C$87*E66 -> 0 | F34: =Assumptions!$C$87*F66 -> 0 | G34: =Assumptions!$C$87*G66 -> 0 | H34: =Assumptions!$C$87*H66 -> 4200 | I34: =Assumptions!$C$87*I66 -> 0 | J34: =Assumptions!$C$87*J66 -> 0 | K34: =Assumptions!$C$87*K66 -> 0 | ... P34: =Assumptions!$C$87*P66 -> 0 | Q34: =SUM(D34:P34) -> 12600 | R34: =AVERAGE(D34:P34) -> 969.23077
B35: Other operating expenses | C35: monthly + variable | D35: =Assumptions!$C$94*D65+D73*Assumptions!$C$38 -> 145.0232 | E35: =Assumptions!$C$94*E65+E73*Assumptions!$C$38 -> 164.86848 | F35: =Assumptions!$C$94*F65+F73*Assumptions!$C$38 -> 140.44352 | G35: =Assumptions!$C$94*G65+G73*Assumptions!$C$38 -> 137.3904 | H35: =Assumptions!$C$94*H65+H73*Assumptions!$C$38 -> 2541.9701 | I35: =Assumptions!$C$94*I65+I73*Assumptions!$C$38 -> 148.07632 | J35: =Assumptions!$C$94*J65+J73*Assumptions!$C$38 -> 152.656 | K35: =Assumptions!$C$94*K65+K73*Assumptions!$C$38 -> 155.70912 | ... P35: =Assumptions!$C$94*P65+P73*Assumptions!$C$38 -> 2574.0278 | Q35: =SUM(D35:P35) -> 9196.7405 | R35: =AVERAGE(D35:P35) -> 707.44158
B36: Total cash outflows | D36: =SUM(D21:D35) -> 20192.402 | E36: =SUM(E21:E35) -> 90574.267 | F36: =SUM(F21:F35) -> 17511.814 | G36: =SUM(G21:G35) -> 15488.395 | H36: =SUM(H21:H35) -> 135376.83 | I36: =SUM(I21:I35) -> 23582.747 | J36: =SUM(J21:J35) -> 29017.282 | K36: =SUM(K21:K35) -> 99335.523 | ... P36: =SUM(P21:P35) -> 98994.661 | Q36: =SUM(D36:P36) -> 779039.27 | R36: =AVERAGE(D36:P36) -> 59926.097
B38: CASH SUMMARY
B39: Net weekly cash movement | D39: =D18-D36 -> 24516.486 | E39: =E18-E36 -> -19009.879 | F39: =F18-F36 -> 26771.536 | G39: =G18-G36 -> 27725.276 | H39: =H18-H36 -> -91186.128 | I39: =I18-I36 -> 22254.91 | J39: =J18-J36 -> 36220.891 | K39: =K18-K36 -> -51948.194 | ... P39: =P18-P36 -> -20433.993 | Q39: =SUM(D39:P39) -> -65349.783 | R39: =AVERAGE(D39:P39) -> -5026.9064
B40: CLOSING CASH | D40: =D10+D39 -> 229516.49 | E40: =E10+E39 -> 210506.61 | F40: =F10+F39 -> 237278.14 | G40: =G10+G39 -> 265003.42 | H40: =H10+H39 -> 173817.29 | I40: =I10+I39 -> 196072.2 | J40: =J10+J39 -> 232293.09 | K40: =K10+K39 -> 180344.9 | ... P40: =P10+P39 -> 139650.22
B41: Minimum cash threshold | D41: =Assumptions!$C$14 -> 120000 | E41: =Assumptions!$C$14 -> 120000 | F41: =Assumptions!$C$14 -> 120000 | G41: =Assumptions!$C$14 -> 120000 | H41: =Assumptions!$C$14 -> 120000 | I41: =Assumptions!$C$14 -> 120000 | J41: =Assumptions!$C$14 -> 120000 | K41: =Assumptions!$C$14 -> 120000 | ... P41: =Assumptions!$C$14 -> 120000
B42: Headroom / (shortfall) vs threshold | D42: =D40-D41 -> 109516.49 | E42: =E40-E41 -> 90506.607 | F42: =F40-F41 -> 117278.14 | G42: =G40-G41 -> 145003.42 | H42: =H40-H41 -> 53817.29 | I42: =I40-I41 -> 76072.2 | J42: =J40-J41 -> 112293.09 | K42: =K40-K41 -> 60344.898 | ... P42: =P40-P41 -> 19650.217
B44: KEY OUTPUTS - these cells feed the Dashboard
B45: Opening cash - Week 1 | D45: =D10 -> 205000 | F45: Per the Assumptions tab.
B46: Closing cash - Week 13 | D46: =P40 -> 139650.22
B47: Net cash movement over 13 weeks | D47: =P40-D10 -> -65349.783
B48: Average weekly net cash movement | D48: =R39 -> -5026.9064 | F48: Negative = weekly cash burn.
B49: Total cash receipts | D49: =Q18 -> 713689.48
B50: Total cash outflows | D50: =Q36 -> 779039.27
B51: Lowest projected cash balance | D51: =MIN(D40:P40) -> 114528.43
B52: Week of lowest cash | D52: =MATCH(MIN(D40:P40),D40:P40,0) -> 9
B53: Week commencing of lowest cash | D53: =INDEX(D7:P7,1,D52) -> 46293
B54: Headroom / (shortfall) at the lowest point | D54: =MIN(D42:P42) -> -5471.5654
B55: Weeks below the minimum cash threshold | D55: =COUNTIF(D42:P42,"<0") -> 1
B56: Cash runway to nil cash at the average weekly burn | D56: =IF(D48<0,-P40/D48,"n/a - cash generative") -> 27.780548 | F56: Closing cash divided by the average weekly burn.
B57: Cash runway to the minimum threshold at the average weekly burn | D57: =IF(D48<0,-(P40-D41)/D48,"n/a") -> 3.9090078
B58: Average weekly cash burn (positive number) | D58: =MAX(0,-D48) -> 5026.9064
B60: Roll-forward: Opening cash + Total receipts - Total outflows = Closing cash, and next week's opening cash equals this week's closing cash. Both identities are tested on the Controls tab.
B63: SUPPORTING CALCULATIONS - drivers, cash conversion and payment timing
B64: Payment timing flags (1 = the payment date falls inside that week; driven by the week dates, not by hardcoded week numbers)
B65: Rent and monthly sundry costs (day 1) | C65: DATE / AND test | D65: =IF(OR(AND(MIN(DATE(YEAR(D$7),MONTH(D$7),Assumptions!$C$79),EOMONTH(D$7,0))>=D$7,MIN(DATE(YEAR(D$7),MONTH(D$7),Assumptions!$C$79),EOMONTH(D$7,0))<=D$8),AND(MIN(DATE(YEAR(D$8),MONTH(D$8),Assumptions!$C$79),EOMONTH(D$8,0))>=D$7,MIN(DATE(YEAR(D$8),MONTH(D$8),Assumptions!$C$79),EOMONTH(D$8,0))<=D$8)),1,0) -> 0 | E65: =IF(OR(AND(MIN(DATE(YEAR(E$7),MONTH(E$7),Assumptions!$C$79),EOMONTH(E$7,0))>=E$7,MIN(DATE(YEAR(E$7),MONTH(E$7),Assumptions!$C$79),EOMONTH(E$7,0))<=E$8),AND(MIN(DATE(YEAR(E$8),MONTH(E$8),Assumptions!$C$79),EOMONTH(E$8,0))>=E$7,MIN(DATE(YEAR(E$8),MONTH(E$8),Assumptions!$C$79),EOMONTH(E$8,0))<=E$8)),1,0) -> 0 | F65: =IF(OR(AND(MIN(DATE(YEAR(F$7),MONTH(F$7),Assumptions!$C$79),EOMONTH(F$7,0))>=F$7,MIN(DATE(YEAR(F$7),MONTH(F$7),Assumptions!$C$79),EOMONTH(F$7,0))<=F$8),AND(MIN(DATE(YEAR(F$8),MONTH(F$8),Assumptions!$C$79),EOMONTH(F$8,0))>=F$7,MIN(DATE(YEAR(F$8),MONTH(F$8),Assumptions!$C$79),EOMONTH(F$8,0))<=F$8)),1,0) -> 0 | G65: =IF(OR(AND(MIN(DATE(YEAR(G$7),MONTH(G$7),Assumptions!$C$79),EOMONTH(G$7,0))>=G$7,MIN(DATE(YEAR(G$7),MONTH(G$7),Assumptions!$C$79),EOMONTH(G$7,0))<=G$8),AND(MIN(DATE(YEAR(G$8),MONTH(G$8),Assumptions!$C$79),EOMONTH(G$8,0))>=G$7,MIN(DATE(YEAR(G$8),MONTH(G$8),Assumptions!$C$79),EOMONTH(G$8,0))<=G$8)),1,0) -> 0 | H65: =IF(OR(AND(MIN(DATE(YEAR(H$7),MONTH(H$7),Assumptions!$C$79),EOMONTH(H$7,0))>=H$7,MIN(DATE(YEAR(H$7),MONTH(H$7),Assumptions!$C$79),EOMONTH(H$7,0))<=H$8),AND(MIN(DATE(YEAR(H$8),MONTH(H$8),Assumptions!$C$79),EOMONTH(H$8,0))>=H$7,MIN(DATE(YEAR(H$8),MONTH(H$8),Assumptions!$C$79),EOMONTH(H$8,0))<=H$8)),1,0) -> 1 | I65: =IF(OR(AND(MIN(DATE(YEAR(I$7),MONTH(I$7),Assumptions!$C$79),EOMONTH(I$7,0))>=I$7,MIN(DATE(YEAR(I$7),MONTH(I$7),Assumptions!$C$79),EOMONTH(I$7,0))<=I$8),AND(MIN(DATE(YEAR(I$8),MONTH(I$8),Assumptions!$C$79),EOMONTH(I$8,0))>=I$7,MIN(DATE(YEAR(I$8),MONTH(I$8),Assumptions!$C$79),EOMONTH(I$8,0))<=I$8)),1,0) -> 0 | J65: =IF(OR(AND(MIN(DATE(YEAR(J$7),MONTH(J$7),Assumptions!$C$79),EOMONTH(J$7,0))>=J$7,MIN(DATE(YEAR(J$7),MONTH(J$7),Assumptions!$C$79),EOMONTH(J$7,0))<=J$8),AND(MIN(DATE(YEAR(J$8),MONTH(J$8),Assumptions!$C$79),EOMONTH(J$8,0))>=J$7,MIN(DATE(YEAR(J$8),MONTH(J$8),Assumptions!$C$79),EOMONTH(J$8,0))<=J$8)),1,0) -> 0 | K65: =IF(OR(AND(MIN(DATE(YEAR(K$7),MONTH(K$7),Assumptions!$C$79),EOMONTH(K$7,0))>=K$7,MIN(DATE(YEAR(K$7),MONTH(K$7),Assumptions!$C$79),EOMONTH(K$7,0))<=K$8),AND(MIN(DATE(YEAR(K$8),MONTH(K$8),Assumptions!$C$79),EOMONTH(K$8,0))>=K$7,MIN(DATE(YEAR(K$8),MONTH(K$8),Assumptions!$C$79),EOMONTH(K$8,0))<=K$8)),1,0) -> 0 | ... P65: =IF(OR(AND(MIN(DATE(YEAR(P$7),MONTH(P$7),Assumptions!$C$79),EOMONTH(P$7,0))>=P$7,MIN(DATE(YEAR(P$7),MONTH(P$7),Assumptions!$C$79),EOMONTH(P$7,0))<=P$8),AND(MIN(DATE(YEAR(P$8),MONTH(P$8),Assumptions!$C$79),EOMONTH(P$8,0))>=P$7,MIN(DATE(YEAR(P$8),MONTH(P$8),Assumptions!$C$79),EOMONTH(P$8,0))<=P$8)),1,0) -> 1
B66: Term loan instalment (day 5) | D66: =IF(OR(AND(MIN(DATE(YEAR(D$7),MONTH(D$7),Assumptions!$C$80),EOMONTH(D$7,0))>=D$7,MIN(DATE(YEAR(D$7),MONTH(D$7),Assumptions!$C$80),EOMONTH(D$7,0))<=D$8),AND(MIN(DATE(YEAR(D$8),MONTH(D$8),Assumptions!$C$80),EOMONTH(D$8,0))>=D$7,MIN(DATE(YEAR(D$8),MONTH(D$8),Assumptions!$C$80),EOMONTH(D$8,0))<=D$8)),1,0) -> 1 | E66: =IF(OR(AND(MIN(DATE(YEAR(E$7),MONTH(E$7),Assumptions!$C$80),EOMONTH(E$7,0))>=E$7,MIN(DATE(YEAR(E$7),MONTH(E$7),Assumptions!$C$80),EOMONTH(E$7,0))<=E$8),AND(MIN(DATE(YEAR(E$8),MONTH(E$8),Assumptions!$C$80),EOMONTH(E$8,0))>=E$7,MIN(DATE(YEAR(E$8),MONTH(E$8),Assumptions!$C$80),EOMONTH(E$8,0))<=E$8)),1,0) -> 0 | F66: =IF(OR(AND(MIN(DATE(YEAR(F$7),MONTH(F$7),Assumptions!$C$80),EOMONTH(F$7,0))>=F$7,MIN(DATE(YEAR(F$7),MONTH(F$7),Assumptions!$C$80),EOMONTH(F$7,0))<=F$8),AND(MIN(DATE(YEAR(F$8),MONTH(F$8),Assumptions!$C$80),EOMONTH(F$8,0))>=F$7,MIN(DATE(YEAR(F$8),MONTH(F$8),Assumptions!$C$80),EOMONTH(F$8,0))<=F$8)),1,0) -> 0 | G66: =IF(OR(AND(MIN(DATE(YEAR(G$7),MONTH(G$7),Assumptions!$C$80),EOMONTH(G$7,0))>=G$7,MIN(DATE(YEAR(G$7),MONTH(G$7),Assumptions!$C$80),EOMONTH(G$7,0))<=G$8),AND(MIN(DATE(YEAR(G$8),MONTH(G$8),Assumptions!$C$80),EOMONTH(G$8,0))>=G$7,MIN(DATE(YEAR(G$8),MONTH(G$8),Assumptions!$C$80),EOMONTH(G$8,0))<=G$8)),1,0) -> 0 | H66: =IF(OR(AND(MIN(DATE(YEAR(H$7),MONTH(H$7),Assumptions!$C$80),EOMONTH(H$7,0))>=H$7,MIN(DATE(YEAR(H$7),MONTH(H$7),Assumptions!$C$80),EOMONTH(H$7,0))<=H$8),AND(MIN(DATE(YEAR(H$8),MONTH(H$8),Assumptions!$C$80),EOMONTH(H$8,0))>=H$7,MIN(DATE(YEAR(H$8),MONTH(H$8),Assumptions!$C$80),EOMONTH(H$8,0))<=H$8)),1,0) -> 1 | I66: =IF(OR(AND(MIN(DATE(YEAR(I$7),MONTH(I$7),Assumptions!$C$80),EOMONTH(I$7,0))>=I$7,MIN(DATE(YEAR(I$7),MONTH(I$7),Assumptions!$C$80),EOMONTH(I$7,0))<=I$8),AND(MIN(DATE(YEAR(I$8),MONTH(I$8),Assumptions!$C$80),EOMONTH(I$8,0))>=I$7,MIN(DATE(YEAR(I$8),MONTH(I$8),Assumptions!$C$80),EOMONTH(I$8,0))<=I$8)),1,0) -> 0 | J66: =IF(OR(AND(MIN(DATE(YEAR(J$7),MONTH(J$7),Assumptions!$C$80),EOMONTH(J$7,0))>=J$7,MIN(DATE(YEAR(J$7),MONTH(J$7),Assumptions!$C$80),EOMONTH(J$7,0))<=J$8),AND(MIN(DATE(YEAR(J$8),MONTH(J$8),Assumptions!$C$80),EOMONTH(J$8,0))>=J$7,MIN(DATE(YEAR(J$8),MONTH(J$8),Assumptions!$C$80),EOMONTH(J$8,0))<=J$8)),1,0) -> 0 | K66: =IF(OR(AND(MIN(DATE(YEAR(K$7),MONTH(K$7),Assumptions!$C$80),EOMONTH(K$7,0))>=K$7,MIN(DATE(YEAR(K$7),MONTH(K$7),Assumptions!$C$80),EOMONTH(K$7,0))<=K$8),AND(MIN(DATE(YEAR(K$8),MONTH(K$8),Assumptions!$C$80),EOMONTH(K$8,0))>=K$7,MIN(DATE(YEAR(K$8),MONTH(K$8),Assumptions!$C$80),EOMONTH(K$8,0))<=K$8)),1,0) -> 0 | ... P66: =IF(OR(AND(MIN(DATE(YEAR(P$7),MONTH(P$7),Assumptions!$C$80),EOMONTH(P$7,0))>=P$7,MIN(DATE(YEAR(P$7),MONTH(P$7),Assumptions!$C$80),EOMONTH(P$7,0))<=P$8),AND(MIN(DATE(YEAR(P$8),MONTH(P$8),Assumptions!$C$80),EOMONTH(P$8,0))>=P$7,MIN(DATE(YEAR(P$8),MONTH(P$8),Assumptions!$C$80),EOMONTH(P$8,0))<=P$8)),1,0) -> 0
B67: Software and brand marketing (day 10) | D67: =IF(OR(AND(MIN(DATE(YEAR(D$7),MONTH(D$7),Assumptions!$C$81),EOMONTH(D$7,0))>=D$7,MIN(DATE(YEAR(D$7),MONTH(D$7),Assumptions!$C$81),EOMONTH(D$7,0))<=D$8),AND(MIN(DATE(YEAR(D$8),MONTH(D$8),Assumptions!$C$81),EOMONTH(D$8,0))>=D$7,MIN(DATE(YEAR(D$8),MONTH(D$8),Assumptions!$C$81),EOMONTH(D$8,0))<=D$8)),1,0) -> 0 | E67: =IF(OR(AND(MIN(DATE(YEAR(E$7),MONTH(E$7),Assumptions!$C$81),EOMONTH(E$7,0))>=E$7,MIN(DATE(YEAR(E$7),MONTH(E$7),Assumptions!$C$81),EOMONTH(E$7,0))<=E$8),AND(MIN(DATE(YEAR(E$8),MONTH(E$8),Assumptions!$C$81),EOMONTH(E$8,0))>=E$7,MIN(DATE(YEAR(E$8),MONTH(E$8),Assumptions!$C$81),EOMONTH(E$8,0))<=E$8)),1,0) -> 1 | F67: =IF(OR(AND(MIN(DATE(YEAR(F$7),MONTH(F$7),Assumptions!$C$81),EOMONTH(F$7,0))>=F$7,MIN(DATE(YEAR(F$7),MONTH(F$7),Assumptions!$C$81),EOMONTH(F$7,0))<=F$8),AND(MIN(DATE(YEAR(F$8),MONTH(F$8),Assumptions!$C$81),EOMONTH(F$8,0))>=F$7,MIN(DATE(YEAR(F$8),MONTH(F$8),Assumptions!$C$81),EOMONTH(F$8,0))<=F$8)),1,0) -> 0 | G67: =IF(OR(AND(MIN(DATE(YEAR(G$7),MONTH(G$7),Assumptions!$C$81),EOMONTH(G$7,0))>=G$7,MIN(DATE(YEAR(G$7),MONTH(G$7),Assumptions!$C$81),EOMONTH(G$7,0))<=G$8),AND(MIN(DATE(YEAR(G$8),MONTH(G$8),Assumptions!$C$81),EOMONTH(G$8,0))>=G$7,MIN(DATE(YEAR(G$8),MONTH(G$8),Assumptions!$C$81),EOMONTH(G$8,0))<=G$8)),1,0) -> 0 | H67: =IF(OR(AND(MIN(DATE(YEAR(H$7),MONTH(H$7),Assumptions!$C$81),EOMONTH(H$7,0))>=H$7,MIN(DATE(YEAR(H$7),MONTH(H$7),Assumptions!$C$81),EOMONTH(H$7,0))<=H$8),AND(MIN(DATE(YEAR(H$8),MONTH(H$8),Assumptions!$C$81),EOMONTH(H$8,0))>=H$7,MIN(DATE(YEAR(H$8),MONTH(H$8),Assumptions!$C$81),EOMONTH(H$8,0))<=H$8)),1,0) -> 0 | I67: =IF(OR(AND(MIN(DATE(YEAR(I$7),MONTH(I$7),Assumptions!$C$81),EOMONTH(I$7,0))>=I$7,MIN(DATE(YEAR(I$7),MONTH(I$7),Assumptions!$C$81),EOMONTH(I$7,0))<=I$8),AND(MIN(DATE(YEAR(I$8),MONTH(I$8),Assumptions!$C$81),EOMONTH(I$8,0))>=I$7,MIN(DATE(YEAR(I$8),MONTH(I$8),Assumptions!$C$81),EOMONTH(I$8,0))<=I$8)),1,0) -> 1 | J67: =IF(OR(AND(MIN(DATE(YEAR(J$7),MONTH(J$7),Assumptions!$C$81),EOMONTH(J$7,0))>=J$7,MIN(DATE(YEAR(J$7),MONTH(J$7),Assumptions!$C$81),EOMONTH(J$7,0))<=J$8),AND(MIN(DATE(YEAR(J$8),MONTH(J$8),Assumptions!$C$81),EOMONTH(J$8,0))>=J$7,MIN(DATE(YEAR(J$8),MONTH(J$8),Assumptions!$C$81),EOMONTH(J$8,0))<=J$8)),1,0) -> 0 | K67: =IF(OR(AND(MIN(DATE(YEAR(K$7),MONTH(K$7),Assumptions!$C$81),EOMONTH(K$7,0))>=K$7,MIN(DATE(YEAR(K$7),MONTH(K$7),Assumptions!$C$81),EOMONTH(K$7,0))<=K$8),AND(MIN(DATE(YEAR(K$8),MONTH(K$8),Assumptions!$C$81),EOMONTH(K$8,0))>=K$7,MIN(DATE(YEAR(K$8),MONTH(K$8),Assumptions!$C$81),EOMONTH(K$8,0))<=K$8)),1,0) -> 0 | ... P67: =IF(OR(AND(MIN(DATE(YEAR(P$7),MONTH(P$7),Assumptions!$C$81),EOMONTH(P$7,0))>=P$7,MIN(DATE(YEAR(P$7),MONTH(P$7),Assumptions!$C$81),EOMONTH(P$7,0))<=P$8),AND(MIN(DATE(YEAR(P$8),MONTH(P$8),Assumptions!$C$81),EOMONTH(P$8,0))>=P$7,MIN(DATE(YEAR(P$8),MONTH(P$8),Assumptions!$C$81),EOMONTH(P$8,0))<=P$8)),1,0) -> 0
B68: Utilities and service charge (day 15) | D68: =IF(OR(AND(MIN(DATE(YEAR(D$7),MONTH(D$7),Assumptions!$C$82),EOMONTH(D$7,0))>=D$7,MIN(DATE(YEAR(D$7),MONTH(D$7),Assumptions!$C$82),EOMONTH(D$7,0))<=D$8),AND(MIN(DATE(YEAR(D$8),MONTH(D$8),Assumptions!$C$82),EOMONTH(D$8,0))>=D$7,MIN(DATE(YEAR(D$8),MONTH(D$8),Assumptions!$C$82),EOMONTH(D$8,0))<=D$8)),1,0) -> 0 | E68: =IF(OR(AND(MIN(DATE(YEAR(E$7),MONTH(E$7),Assumptions!$C$82),EOMONTH(E$7,0))>=E$7,MIN(DATE(YEAR(E$7),MONTH(E$7),Assumptions!$C$82),EOMONTH(E$7,0))<=E$8),AND(MIN(DATE(YEAR(E$8),MONTH(E$8),Assumptions!$C$82),EOMONTH(E$8,0))>=E$7,MIN(DATE(YEAR(E$8),MONTH(E$8),Assumptions!$C$82),EOMONTH(E$8,0))<=E$8)),1,0) -> 1 | F68: =IF(OR(AND(MIN(DATE(YEAR(F$7),MONTH(F$7),Assumptions!$C$82),EOMONTH(F$7,0))>=F$7,MIN(DATE(YEAR(F$7),MONTH(F$7),Assumptions!$C$82),EOMONTH(F$7,0))<=F$8),AND(MIN(DATE(YEAR(F$8),MONTH(F$8),Assumptions!$C$82),EOMONTH(F$8,0))>=F$7,MIN(DATE(YEAR(F$8),MONTH(F$8),Assumptions!$C$82),EOMONTH(F$8,0))<=F$8)),1,0) -> 0 | G68: =IF(OR(AND(MIN(DATE(YEAR(G$7),MONTH(G$7),Assumptions!$C$82),EOMONTH(G$7,0))>=G$7,MIN(DATE(YEAR(G$7),MONTH(G$7),Assumptions!$C$82),EOMONTH(G$7,0))<=G$8),AND(MIN(DATE(YEAR(G$8),MONTH(G$8),Assumptions!$C$82),EOMONTH(G$8,0))>=G$7,MIN(DATE(YEAR(G$8),MONTH(G$8),Assumptions!$C$82),EOMONTH(G$8,0))<=G$8)),1,0) -> 0 | H68: =IF(OR(AND(MIN(DATE(YEAR(H$7),MONTH(H$7),Assumptions!$C$82),EOMONTH(H$7,0))>=H$7,MIN(DATE(YEAR(H$7),MONTH(H$7),Assumptions!$C$82),EOMONTH(H$7,0))<=H$8),AND(MIN(DATE(YEAR(H$8),MONTH(H$8),Assumptions!$C$82),EOMONTH(H$8,0))>=H$7,MIN(DATE(YEAR(H$8),MONTH(H$8),Assumptions!$C$82),EOMONTH(H$8,0))<=H$8)),1,0) -> 0 | I68: =IF(OR(AND(MIN(DATE(YEAR(I$7),MONTH(I$7),Assumptions!$C$82),EOMONTH(I$7,0))>=I$7,MIN(DATE(YEAR(I$7),MONTH(I$7),Assumptions!$C$82),EOMONTH(I$7,0))<=I$8),AND(MIN(DATE(YEAR(I$8),MONTH(I$8),Assumptions!$C$82),EOMONTH(I$8,0))>=I$7,MIN(DATE(YEAR(I$8),MONTH(I$8),Assumptions!$C$82),EOMONTH(I$8,0))<=I$8)),1,0) -> 0 | J68: =IF(OR(AND(MIN(DATE(YEAR(J$7),MONTH(J$7),Assumptions!$C$82),EOMONTH(J$7,0))>=J$7,MIN(DATE(YEAR(J$7),MONTH(J$7),Assumptions!$C$82),EOMONTH(J$7,0))<=J$8),AND(MIN(DATE(YEAR(J$8),MONTH(J$8),Assumptions!$C$82),EOMONTH(J$8,0))>=J$7,MIN(DATE(YEAR(J$8),MONTH(J$8),Assumptions!$C$82),EOMONTH(J$8,0))<=J$8)),1,0) -> 1 | K68: =IF(OR(AND(MIN(DATE(YEAR(K$7),MONTH(K$7),Assumptions!$C$82),EOMONTH(K$7,0))>=K$7,MIN(DATE(YEAR(K$7),MONTH(K$7),Assumptions!$C$82),EOMONTH(K$7,0))<=K$8),AND(MIN(DATE(YEAR(K$8),MONTH(K$8),Assumptions!$C$82),EOMONTH(K$8,0))>=K$7,MIN(DATE(YEAR(K$8),MONTH(K$8),Assumptions!$C$82),EOMONTH(K$8,0))<=K$8)),1,0) -> 0 | ... P68: =IF(OR(AND(MIN(DATE(YEAR(P$7),MONTH(P$7),Assumptions!$C$82),EOMONTH(P$7,0))>=P$7,MIN(DATE(YEAR(P$7),MONTH(P$7),Assumptions!$C$82),EOMONTH(P$7,0))<=P$8),AND(MIN(DATE(YEAR(P$8),MONTH(P$8),Assumptions!$C$82),EOMONTH(P$8,0))>=P$7,MIN(DATE(YEAR(P$8),MONTH(P$8),Assumptions!$C$82),EOMONTH(P$8,0))<=P$8)),1,0) -> 0
B69: Professional fees (day 20) | D69: =IF(OR(AND(MIN(DATE(YEAR(D$7),MONTH(D$7),Assumptions!$C$83),EOMONTH(D$7,0))>=D$7,MIN(DATE(YEAR(D$7),MONTH(D$7),Assumptions!$C$83),EOMONTH(D$7,0))<=D$8),AND(MIN(DATE(YEAR(D$8),MONTH(D$8),Assumptions!$C$83),EOMONTH(D$8,0))>=D$7,MIN(DATE(YEAR(D$8),MONTH(D$8),Assumptions!$C$83),EOMONTH(D$8,0))<=D$8)),1,0) -> 0 | E69: =IF(OR(AND(MIN(DATE(YEAR(E$7),MONTH(E$7),Assumptions!$C$83),EOMONTH(E$7,0))>=E$7,MIN(DATE(YEAR(E$7),MONTH(E$7),Assumptions!$C$83),EOMONTH(E$7,0))<=E$8),AND(MIN(DATE(YEAR(E$8),MONTH(E$8),Assumptions!$C$83),EOMONTH(E$8,0))>=E$7,MIN(DATE(YEAR(E$8),MONTH(E$8),Assumptions!$C$83),EOMONTH(E$8,0))<=E$8)),1,0) -> 0 | F69: =IF(OR(AND(MIN(DATE(YEAR(F$7),MONTH(F$7),Assumptions!$C$83),EOMONTH(F$7,0))>=F$7,MIN(DATE(YEAR(F$7),MONTH(F$7),Assumptions!$C$83),EOMONTH(F$7,0))<=F$8),AND(MIN(DATE(YEAR(F$8),MONTH(F$8),Assumptions!$C$83),EOMONTH(F$8,0))>=F$7,MIN(DATE(YEAR(F$8),MONTH(F$8),Assumptions!$C$83),EOMONTH(F$8,0))<=F$8)),1,0) -> 1 | G69: =IF(OR(AND(MIN(DATE(YEAR(G$7),MONTH(G$7),Assumptions!$C$83),EOMONTH(G$7,0))>=G$7,MIN(DATE(YEAR(G$7),MONTH(G$7),Assumptions!$C$83),EOMONTH(G$7,0))<=G$8),AND(MIN(DATE(YEAR(G$8),MONTH(G$8),Assumptions!$C$83),EOMONTH(G$8,0))>=G$7,MIN(DATE(YEAR(G$8),MONTH(G$8),Assumptions!$C$83),EOMONTH(G$8,0))<=G$8)),1,0) -> 0 | H69: =IF(OR(AND(MIN(DATE(YEAR(H$7),MONTH(H$7),Assumptions!$C$83),EOMONTH(H$7,0))>=H$7,MIN(DATE(YEAR(H$7),MONTH(H$7),Assumptions!$C$83),EOMONTH(H$7,0))<=H$8),AND(MIN(DATE(YEAR(H$8),MONTH(H$8),Assumptions!$C$83),EOMONTH(H$8,0))>=H$7,MIN(DATE(YEAR(H$8),MONTH(H$8),Assumptions!$C$83),EOMONTH(H$8,0))<=H$8)),1,0) -> 0 | I69: =IF(OR(AND(MIN(DATE(YEAR(I$7),MONTH(I$7),Assumptions!$C$83),EOMONTH(I$7,0))>=I$7,MIN(DATE(YEAR(I$7),MONTH(I$7),Assumptions!$C$83),EOMONTH(I$7,0))<=I$8),AND(MIN(DATE(YEAR(I$8),MONTH(I$8),Assumptions!$C$83),EOMONTH(I$8,0))>=I$7,MIN(DATE(YEAR(I$8),MONTH(I$8),Assumptions!$C$83),EOMONTH(I$8,0))<=I$8)),1,0) -> 0 | J69: =IF(OR(AND(MIN(DATE(YEAR(J$7),MONTH(J$7),Assumptions!$C$83),EOMONTH(J$7,0))>=J$7,MIN(DATE(YEAR(J$7),MONTH(J$7),Assumptions!$C$83),EOMONTH(J$7,0))<=J$8),AND(MIN(DATE(YEAR(J$8),MONTH(J$8),Assumptions!$C$83),EOMONTH(J$8,0))>=J$7,MIN(DATE(YEAR(J$8),MONTH(J$8),Assumptions!$C$83),EOMONTH(J$8,0))<=J$8)),1,0) -> 1 | K69: =IF(OR(AND(MIN(DATE(YEAR(K$7),MONTH(K$7),Assumptions!$C$83),EOMONTH(K$7,0))>=K$7,MIN(DATE(YEAR(K$7),MONTH(K$7),Assumptions!$C$83),EOMONTH(K$7,0))<=K$8),AND(MIN(DATE(YEAR(K$8),MONTH(K$8),Assumptions!$C$83),EOMONTH(K$8,0))>=K$7,MIN(DATE(YEAR(K$8),MONTH(K$8),Assumptions!$C$83),EOMONTH(K$8,0))<=K$8)),1,0) -> 0 | ... P69: =IF(OR(AND(MIN(DATE(YEAR(P$7),MONTH(P$7),Assumptions!$C$83),EOMONTH(P$7,0))>=P$7,MIN(DATE(YEAR(P$7),MONTH(P$7),Assumptions!$C$83),EOMONTH(P$7,0))<=P$8),AND(MIN(DATE(YEAR(P$8),MONTH(P$8),Assumptions!$C$83),EOMONTH(P$8,0))>=P$7,MIN(DATE(YEAR(P$8),MONTH(P$8),Assumptions!$C$83),EOMONTH(P$8,0))<=P$8)),1,0) -> 0
B70: Payroll (last day of month) | C70: EOMONTH test | D70: =IF(EOMONTH(D$7,0)<=D$8,1,0) -> 0 | E70: =IF(EOMONTH(E$7,0)<=E$8,1,0) -> 0 | F70: =IF(EOMONTH(F$7,0)<=F$8,1,0) -> 0 | G70: =IF(EOMONTH(G$7,0)<=G$8,1,0) -> 0 | H70: =IF(EOMONTH(H$7,0)<=H$8,1,0) -> 1 | I70: =IF(EOMONTH(I$7,0)<=I$8,1,0) -> 0 | J70: =IF(EOMONTH(J$7,0)<=J$8,1,0) -> 0 | K70: =IF(EOMONTH(K$7,0)<=K$8,1,0) -> 0 | ... P70: =IF(EOMONTH(P$7,0)<=P$8,1,0) -> 1
B72: Net sales by channel (gross weekly run-rate x seasonality index, less discounts and returns)
B73: Physical store | C73: run-rate x index | D73: =Assumptions!$C$17*Assumptions!D$108*(1-Assumptions!$C$23) -> 18127.9 | E73: =Assumptions!$C$17*Assumptions!E$108*(1-Assumptions!$C$23) -> 20608.56 | F73: =Assumptions!$C$17*Assumptions!F$108*(1-Assumptions!$C$23) -> 17555.44 | G73: =Assumptions!$C$17*Assumptions!G$108*(1-Assumptions!$C$23) -> 17173.8 | H73: =Assumptions!$C$17*Assumptions!H$108*(1-Assumptions!$C$23) -> 17746.26 | I73: =Assumptions!$C$17*Assumptions!I$108*(1-Assumptions!$C$23) -> 18509.54 | J73: =Assumptions!$C$17*Assumptions!J$108*(1-Assumptions!$C$23) -> 19082 | K73: =Assumptions!$C$17*Assumptions!K$108*(1-Assumptions!$C$23) -> 19463.64 | ... P73: =Assumptions!$C$17*Assumptions!P$108*(1-Assumptions!$C$23) -> 21753.48 | Q73: =SUM(D73:P73) -> 249592.56 | R73: =AVERAGE(D73:P73) -> 19199.428
B74: E-commerce | C74: run-rate x index | D74: =Assumptions!$C$18*Assumptions!D$109*(1-Assumptions!$C$24) -> 20913.2 | E74: =Assumptions!$C$18*Assumptions!E$109*(1-Assumptions!$C$24) -> 22638 | F74: =Assumptions!$C$18*Assumptions!F$109*(1-Assumptions!$C$24) -> 20697.6 | G74: =Assumptions!$C$18*Assumptions!G$109*(1-Assumptions!$C$24) -> 20482 | H74: =Assumptions!$C$18*Assumptions!H$109*(1-Assumptions!$C$24) -> 21344.4 | I74: =Assumptions!$C$18*Assumptions!I$109*(1-Assumptions!$C$24) -> 21991.2 | J74: =Assumptions!$C$18*Assumptions!J$109*(1-Assumptions!$C$24) -> 22422.4 | K74: =Assumptions!$C$18*Assumptions!K$109*(1-Assumptions!$C$24) -> 22853.6 | ... P74: =Assumptions!$C$18*Assumptions!P$109*(1-Assumptions!$C$24) -> 25872 | Q74: =SUM(D74:P74) -> 294078.4 | R74: =AVERAGE(D74:P74) -> 22621.415
B75: Events / pop-ups | C75: event calendar | D75: =Assumptions!$C$19*Assumptions!D$110*(1-Assumptions!$C$25) -> 0 | E75: =Assumptions!$C$19*Assumptions!E$110*(1-Assumptions!$C$25) -> 23280 | F75: =Assumptions!$C$19*Assumptions!F$110*(1-Assumptions!$C$25) -> 0 | G75: =Assumptions!$C$19*Assumptions!G$110*(1-Assumptions!$C$25) -> 0 | H75: =Assumptions!$C$19*Assumptions!H$110*(1-Assumptions!$C$25) -> 0 | I75: =Assumptions!$C$19*Assumptions!I$110*(1-Assumptions!$C$25) -> 0 | J75: =Assumptions!$C$19*Assumptions!J$110*(1-Assumptions!$C$25) -> 18624 | K75: =Assumptions!$C$19*Assumptions!K$110*(1-Assumptions!$C$25) -> 0 | ... P75: =Assumptions!$C$19*Assumptions!P$110*(1-Assumptions!$C$25) -> 25608 | Q75: =SUM(D75:P75) -> 100104 | R75: =AVERAGE(D75:P75) -> 7700.3077
B76: Consignment | C76: run-rate x index | D76: =Assumptions!$C$20*Assumptions!D$111*(1-Assumptions!$C$26) -> 7536 | E76: =Assumptions!$C$20*Assumptions!E$111*(1-Assumptions!$C$26) -> 7850 | F76: =Assumptions!$C$20*Assumptions!F$111*(1-Assumptions!$C$26) -> 7457.5 | G76: =Assumptions!$C$20*Assumptions!G$111*(1-Assumptions!$C$26) -> 7379 | H76: =Assumptions!$C$20*Assumptions!H$111*(1-Assumptions!$C$26) -> 7614.5 | I76: =Assumptions!$C$20*Assumptions!I$111*(1-Assumptions!$C$26) -> 7850 | J76: =Assumptions!$C$20*Assumptions!J$111*(1-Assumptions!$C$26) -> 8007 | K76: =Assumptions!$C$20*Assumptions!K$111*(1-Assumptions!$C$26) -> 8085.5 | ... P76: =Assumptions!$C$20*Assumptions!P$111*(1-Assumptions!$C$26) -> 8792 | Q76: =SUM(D76:P76) -> 103855.5 | R76: =AVERAGE(D76:P76) -> 7988.8846
B77: Total net sales | D77: =SUM(D73:D76) -> 46577.1 | E77: =SUM(E73:E76) -> 74376.56 | F77: =SUM(F73:F76) -> 45710.54 | G77: =SUM(G73:G76) -> 45034.8 | H77: =SUM(H73:H76) -> 46705.16 | I77: =SUM(I73:I76) -> 48350.74 | J77: =SUM(J73:J76) -> 68135.4 | K77: =SUM(K73:K76) -> 50402.74 | ... P77: =SUM(P73:P76) -> 82025.48 | Q77: =SUM(D77:P77) -> 747630.46 | R77: =AVERAGE(D77:P77) -> 57510.035
B79: Cost of goods sold
B80: Physical store | D80: =D73*(1-Assumptions!$C$28) -> 7613.718 | E80: =E73*(1-Assumptions!$C$28) -> 8655.5952 | F80: =F73*(1-Assumptions!$C$28) -> 7373.2848 | G80: =G73*(1-Assumptions!$C$28) -> 7212.996 | H80: =H73*(1-Assumptions!$C$28) -> 7453.4292 | I80: =I73*(1-Assumptions!$C$28) -> 7774.0068 | J80: =J73*(1-Assumptions!$C$28) -> 8014.44 | K80: =K73*(1-Assumptions!$C$28) -> 8174.7288 | ... P80: =P73*(1-Assumptions!$C$28) -> 9136.4616 | Q80: =SUM(D80:P80) -> 104828.88 | R80: =AVERAGE(D80:P80) -> 8063.7596
B81: E-commerce | D81: =D74*(1-Assumptions!$C$29) -> 8365.28 | E81: =E74*(1-Assumptions!$C$29) -> 9055.2 | F81: =F74*(1-Assumptions!$C$29) -> 8279.04 | G81: =G74*(1-Assumptions!$C$29) -> 8192.8 | H81: =H74*(1-Assumptions!$C$29) -> 8537.76 | I81: =I74*(1-Assumptions!$C$29) -> 8796.48 | J81: =J74*(1-Assumptions!$C$29) -> 8968.96 | K81: =K74*(1-Assumptions!$C$29) -> 9141.44 | ... P81: =P74*(1-Assumptions!$C$29) -> 10348.8 | Q81: =SUM(D81:P81) -> 117631.36 | R81: =AVERAGE(D81:P81) -> 9048.5662
B82: Events / pop-ups | D82: =D75*(1-Assumptions!$C$30) -> 0 | E82: =E75*(1-Assumptions!$C$30) -> 8380.8 | F82: =F75*(1-Assumptions!$C$30) -> 0 | G82: =G75*(1-Assumptions!$C$30) -> 0 | H82: =H75*(1-Assumptions!$C$30) -> 0 | I82: =I75*(1-Assumptions!$C$30) -> 0 | J82: =J75*(1-Assumptions!$C$30) -> 6704.64 | K82: =K75*(1-Assumptions!$C$30) -> 0 | ... P82: =P75*(1-Assumptions!$C$30) -> 9218.88 | Q82: =SUM(D82:P82) -> 36037.44 | R82: =AVERAGE(D82:P82) -> 2772.1108
B83: Consignment | D83: =D76*(1-Assumptions!$C$31) -> 3014.4 | E83: =E76*(1-Assumptions!$C$31) -> 3140 | F83: =F76*(1-Assumptions!$C$31) -> 2983 | G83: =G76*(1-Assumptions!$C$31) -> 2951.6 | H83: =H76*(1-Assumptions!$C$31) -> 3045.8 | I83: =I76*(1-Assumptions!$C$31) -> 3140 | J83: =J76*(1-Assumptions!$C$31) -> 3202.8 | K83: =K76*(1-Assumptions!$C$31) -> 3234.2 | ... P83: =P76*(1-Assumptions!$C$31) -> 3516.8 | Q83: =SUM(D83:P83) -> 41542.2 | R83: =AVERAGE(D83:P83) -> 3195.5538
B84: Total cost of goods sold | D84: =SUM(D80:D83) -> 18993.398 | E84: =SUM(E80:E83) -> 29231.595 | F84: =SUM(F80:F83) -> 18635.325 | G84: =SUM(G80:G83) -> 18357.396 | H84: =SUM(H80:H83) -> 19036.989 | I84: =SUM(I80:I83) -> 19710.487 | J84: =SUM(J80:J83) -> 26890.84 | K84: =SUM(K80:K83) -> 20550.369 | ... P84: =SUM(P80:P83) -> 32220.942 | Q84: =SUM(D84:P84) -> 300039.88 | R84: =AVERAGE(D84:P84) -> 23079.99
B86: Inventory purchase build
B87: Ongoing replenishment purchases | C87: % of weekly COGS | D87: =D84*Assumptions!$C$76 -> 11016.171 | E87: =E84*Assumptions!$C$76 -> 16954.325 | F87: =F84*Assumptions!$C$76 -> 10808.488 | G87: =G84*Assumptions!$C$76 -> 10647.29 | H87: =H84*Assumptions!$C$76 -> 11041.454 | I87: =I84*Assumptions!$C$76 -> 11432.082 | J87: =J84*Assumptions!$C$76 -> 15596.687 | K87: =K84*Assumptions!$C$76 -> 11919.214 | ... P87: =P84*Assumptions!$C$76 -> 18688.146 | Q87: =SUM(D87:P87) -> 174023.13 | R87: =AVERAGE(D87:P87) -> 13386.394
B88: Scheduled AW26 buy payments | C88: purchase schedule | D88: =SUMIFS(Assumptions!$C$116:$C$119,Assumptions!$D$116:$D$119,D$6) -> 0 | E88: =SUMIFS(Assumptions!$C$116:$C$119,Assumptions!$D$116:$D$119,E$6) -> 54000 | F88: =SUMIFS(Assumptions!$C$116:$C$119,Assumptions!$D$116:$D$119,F$6) -> 0 | G88: =SUMIFS(Assumptions!$C$116:$C$119,Assumptions!$D$116:$D$119,G$6) -> 0 | H88: =SUMIFS(Assumptions!$C$116:$C$119,Assumptions!$D$116:$D$119,H$6) -> 46000 | I88: =SUMIFS(Assumptions!$C$116:$C$119,Assumptions!$D$116:$D$119,I$6) -> 0 | J88: =SUMIFS(Assumptions!$C$116:$C$119,Assumptions!$D$116:$D$119,J$6) -> 0 | K88: =SUMIFS(Assumptions!$C$116:$C$119,Assumptions!$D$116:$D$119,K$6) -> 82000 | ... P88: =SUMIFS(Assumptions!$C$116:$C$119,Assumptions!$D$116:$D$119,P$6) -> 0 | Q88: =SUM(D88:P88) -> 235000 | R88: =AVERAGE(D88:P88) -> 18076.923
B89: Total inventory and supplier payments | D89: =D87+D88 -> 11016.171 | E89: =E87+E88 -> 70954.325 | F89: =F87+F88 -> 10808.488 | G89: =G87+G88 -> 10647.29 | H89: =H87+H88 -> 57041.454 | I89: =I87+I88 -> 11432.082 | J89: =J87+J88 -> 15596.687 | K89: =K87+K88 -> 93919.214 | ... P89: =P87+P88 -> 18688.146 | Q89: =SUM(D89:P89) -> 409023.13 | R89: =AVERAGE(D89:P89) -> 31463.318
B91: PAYMENT DATE COVERAGE TEST - independent check that every configured payment date is captured exactly once (feeds Controls #9)
B92: Accrual month | C92: Month start | D92: Rent / sundry | E92: Term loan | F92: Software / brand | G92: Utilities | H92: Professional fees | I92: Payroll (month end)
B93: Payment day of month | D93: =Assumptions!$C$79 -> 1 | E93: =Assumptions!$C$80 -> 5 | F93: =Assumptions!$C$81 -> 10 | G93: =Assumptions!$C$82 -> 15 | H93: =Assumptions!$C$83 -> 20 | I93: =31 -> 31
B94: =TEXT(C94,"mmm yy") -> Aug 26 | C94: =DATE(YEAR($D$7),MONTH($D$7),1) -> 46235 | D94: =IF(AND(MIN(DATE(YEAR($C94),MONTH($C94),D$93),EOMONTH($C94,0))>=$D$7,MIN(DATE(YEAR($C94),MONTH($C94),D$93),EOMONTH($C94,0))<=$P$8),1,0) -> 0 | E94: =IF(AND(MIN(DATE(YEAR($C94),MONTH($C94),E$93),EOMONTH($C94,0))>=$D$7,MIN(DATE(YEAR($C94),MONTH($C94),E$93),EOMONTH($C94,0))<=$P$8),1,0) -> 1 | F94: =IF(AND(MIN(DATE(YEAR($C94),MONTH($C94),F$93),EOMONTH($C94,0))>=$D$7,MIN(DATE(YEAR($C94),MONTH($C94),F$93),EOMONTH($C94,0))<=$P$8),1,0) -> 1 | G94: =IF(AND(MIN(DATE(YEAR($C94),MONTH($C94),G$93),EOMONTH($C94,0))>=$D$7,MIN(DATE(YEAR($C94),MONTH($C94),G$93),EOMONTH($C94,0))<=$P$8),1,0) -> 1 | H94: =IF(AND(MIN(DATE(YEAR($C94),MONTH($C94),H$93),EOMONTH($C94,0))>=$D$7,MIN(DATE(YEAR($C94),MONTH($C94),H$93),EOMONTH($C94,0))<=$P$8),1,0) -> 1 | I94: =IF(AND(MIN(DATE(YEAR($C94),MONTH($C94),I$93),EOMONTH($C94,0))>=$D$7,MIN(DATE(YEAR($C94),MONTH($C94),I$93),EOMONTH($C94,0))<=$P$8),1,0) -> 1
B95: =TEXT(C95,"mmm yy") -> Sep 26 | C95: =EOMONTH(C94,0)+1 -> 46266 | D95: =IF(AND(MIN(DATE(YEAR($C95),MONTH($C95),D$93),EOMONTH($C95,0))>=$D$7,MIN(DATE(YEAR($C95),MONTH($C95),D$93),EOMONTH($C95,0))<=$P$8),1,0) -> 1 | E95: =IF(AND(MIN(DATE(YEAR($C95),MONTH($C95),E$93),EOMONTH($C95,0))>=$D$7,MIN(DATE(YEAR($C95),MONTH($C95),E$93),EOMONTH($C95,0))<=$P$8),1,0) -> 1 | F95: =IF(AND(MIN(DATE(YEAR($C95),MONTH($C95),F$93),EOMONTH($C95,0))>=$D$7,MIN(DATE(YEAR($C95),MONTH($C95),F$93),EOMONTH($C95,0))<=$P$8),1,0) -> 1 | G95: =IF(AND(MIN(DATE(YEAR($C95),MONTH($C95),G$93),EOMONTH($C95,0))>=$D$7,MIN(DATE(YEAR($C95),MONTH($C95),G$93),EOMONTH($C95,0))<=$P$8),1,0) -> 1 | H95: =IF(AND(MIN(DATE(YEAR($C95),MONTH($C95),H$93),EOMONTH($C95,0))>=$D$7,MIN(DATE(YEAR($C95),MONTH($C95),H$93),EOMONTH($C95,0))<=$P$8),1,0) -> 1 | I95: =IF(AND(MIN(DATE(YEAR($C95),MONTH($C95),I$93),EOMONTH($C95,0))>=$D$7,MIN(DATE(YEAR($C95),MONTH($C95),I$93),EOMONTH($C95,0))<=$P$8),1,0) -> 1
B96: =TEXT(C96,"mmm yy") -> Oct 26 | C96: =EOMONTH(C95,0)+1 -> 46296 | D96: =IF(AND(MIN(DATE(YEAR($C96),MONTH($C96),D$93),EOMONTH($C96,0))>=$D$7,MIN(DATE(YEAR($C96),MONTH($C96),D$93),EOMONTH($C96,0))<=$P$8),1,0) -> 1 | E96: =IF(AND(MIN(DATE(YEAR($C96),MONTH($C96),E$93),EOMONTH($C96,0))>=$D$7,MIN(DATE(YEAR($C96),MONTH($C96),E$93),EOMONTH($C96,0))<=$P$8),1,0) -> 1 | F96: =IF(AND(MIN(DATE(YEAR($C96),MONTH($C96),F$93),EOMONTH($C96,0))>=$D$7,MIN(DATE(YEAR($C96),MONTH($C96),F$93),EOMONTH($C96,0))<=$P$8),1,0) -> 1 | G96: =IF(AND(MIN(DATE(YEAR($C96),MONTH($C96),G$93),EOMONTH($C96,0))>=$D$7,MIN(DATE(YEAR($C96),MONTH($C96),G$93),EOMONTH($C96,0))<=$P$8),1,0) -> 1 | H96: =IF(AND(MIN(DATE(YEAR($C96),MONTH($C96),H$93),EOMONTH($C96,0))>=$D$7,MIN(DATE(YEAR($C96),MONTH($C96),H$93),EOMONTH($C96,0))<=$P$8),1,0) -> 1 | I96: =IF(AND(MIN(DATE(YEAR($C96),MONTH($C96),I$93),EOMONTH($C96,0))>=$D$7,MIN(DATE(YEAR($C96),MONTH($C96),I$93),EOMONTH($C96,0))<=$P$8),1,0) -> 1
B97: =TEXT(C97,"mmm yy") -> Nov 26 | C97: =EOMONTH(C96,0)+1 -> 46327 | D97: =IF(AND(MIN(DATE(YEAR($C97),MONTH($C97),D$93),EOMONTH($C97,0))>=$D$7,MIN(DATE(YEAR($C97),MONTH($C97),D$93),EOMONTH($C97,0))<=$P$8),1,0) -> 1 | E97: =IF(AND(MIN(DATE(YEAR($C97),MONTH($C97),E$93),EOMONTH($C97,0))>=$D$7,MIN(DATE(YEAR($C97),MONTH($C97),E$93),EOMONTH($C97,0))<=$P$8),1,0) -> 0 | F97: =IF(AND(MIN(DATE(YEAR($C97),MONTH($C97),F$93),EOMONTH($C97,0))>=$D$7,MIN(DATE(YEAR($C97),MONTH($C97),F$93),EOMONTH($C97,0))<=$P$8),1,0) -> 0 | G97: =IF(AND(MIN(DATE(YEAR($C97),MONTH($C97),G$93),EOMONTH($C97,0))>=$D$7,MIN(DATE(YEAR($C97),MONTH($C97),G$93),EOMONTH($C97,0))<=$P$8),1,0) -> 0 | H97: =IF(AND(MIN(DATE(YEAR($C97),MONTH($C97),H$93),EOMONTH($C97,0))>=$D$7,MIN(DATE(YEAR($C97),MONTH($C97),H$93),EOMONTH($C97,0))<=$P$8),1,0) -> 0 | I97: =IF(AND(MIN(DATE(YEAR($C97),MONTH($C97),I$93),EOMONTH($C97,0))>=$D$7,MIN(DATE(YEAR($C97),MONTH($C97),I$93),EOMONTH($C97,0))<=$P$8),1,0) -> 0
B98: =TEXT(C98,"mmm yy") -> Dec 26 | C98: =EOMONTH(C97,0)+1 -> 46357 | D98: =IF(AND(MIN(DATE(YEAR($C98),MONTH($C98),D$93),EOMONTH($C98,0))>=$D$7,MIN(DATE(YEAR($C98),MONTH($C98),D$93),EOMONTH($C98,0))<=$P$8),1,0) -> 0 | E98: =IF(AND(MIN(DATE(YEAR($C98),MONTH($C98),E$93),EOMONTH($C98,0))>=$D$7,MIN(DATE(YEAR($C98),MONTH($C98),E$93),EOMONTH($C98,0))<=$P$8),1,0) -> 0 | F98: =IF(AND(MIN(DATE(YEAR($C98),MONTH($C98),F$93),EOMONTH($C98,0))>=$D$7,MIN(DATE(YEAR($C98),MONTH($C98),F$93),EOMONTH($C98,0))<=$P$8),1,0) -> 0 | G98: =IF(AND(MIN(DATE(YEAR($C98),MONTH($C98),G$93),EOMONTH($C98,0))>=$D$7,MIN(DATE(YEAR($C98),MONTH($C98),G$93),EOMONTH($C98,0))<=$P$8),1,0) -> 0 | H98: =IF(AND(MIN(DATE(YEAR($C98),MONTH($C98),H$93),EOMONTH($C98,0))>=$D$7,MIN(DATE(YEAR($C98),MONTH($C98),H$93),EOMONTH($C98,0))<=$P$8),1,0) -> 0 | I98: =IF(AND(MIN(DATE(YEAR($C98),MONTH($C98),I$93),EOMONTH($C98,0))>=$D$7,MIN(DATE(YEAR($C98),MONTH($C98),I$93),EOMONTH($C98,0))<=$P$8),1,0) -> 0
B99: Payments falling inside the 13-week window | D99: =SUM(D94:D98) -> 3 | E99: =SUM(E94:E98) -> 3 | F99: =SUM(F94:F98) -> 3 | G99: =SUM(G94:G98) -> 3 | H99: =SUM(H94:H98) -> 3 | I99: =SUM(I94:I98) -> 3
B100: Payment flags actually raised by the forecast | D100: =SUM($D$65:$P$65) -> 3 | E100: =SUM($D$66:$P$66) -> 3 | F100: =SUM($D$67:$P$67) -> 3 | G100: =SUM($D$68:$P$68) -> 3 | H100: =SUM($D$69:$P$69) -> 3 | I100: =SUM($D$70:$P$70) -> 3
B101: Difference (must be nil - a non-zero value means a payment was lost or duplicated) | D101: =D100-D99 -> 0 | E101: =E100-E99 -> 0 | F101: =F100-F99 -> 0 | G101: =G100-G99 -> 0 | H101: =H100-H99 -> 0 | I101: =I100-I99 -> 0
B102: Payment dates are clamped to the month end, so a payment day of 29-31 settles on the last day of a shorter month rather than disappearing from the forecast.

Sheet Scenarios
B2: ATELIER NORTH PTE. LTD. | Q2: SGD · synthetic data
B3: Management scenarios · 13-week cash outcome and monthly run-rate P&L | Q3: Back to Dashboard
B4: ="Preferred scenario: "&INDEX($D$6:$F$6,MATCH(MAX($D$50:$F$50),$D$50:$F$50,0))&" · highest monthly run-rate operating profit at "&TEXT(MAX($D$50:$F$50),"""S$""#,##0")&", the strongest Week 13 cash position at "&TEXT(INDEX($D$63:$F$63,MATCH(MAX($D$50:$F$50),$D$50:$F$50,0)),"""S$""#,##0")&" and "&INDEX($D$67:$F$67,MATCH(MAX($D$50:$F$50),$D$50:$F$50,0))&IF(INDEX($D$67:$F$67,MATCH(MAX($D$50:$F$50),$D$50:$F$50,0))=1," week"," weeks")&" below the minimum cash buffer." -> Preferred scenario: 2. Store Improvement · highest monthly run-rate operating profit at S$27,343, the strongest Week 13 cash position at S$163,302 and 0 weeks below the minimum cash buffer.
B5: SCENARIO LEVERS - the only inputs on this sheet (amber cells)
B6: Lever | D6: 1. Current Operations | E6: 2. Store Improvement | F6: 3. Store Exit / Channel Shift | H6: Note
B7: Store net sales change | D7: 0 | E7: 0.06 | F7: 0 | H7: Improvement case: conversion, clienteling and appointment selling.
B8: Store gross margin change (percentage points) | D8: 0 | E8: 0.015 | F8: 0 | H8: Tighter markdown control and better buy discipline.
B9: Store base payroll change | D9: 0 | E9: -0.12 | F9: 0 | H9: Reduced opening hours on the two quietest trading days.
B10: Store other fixed cost change | D10: 0 | E10: -0.08 | F10: 0 | H10: Utilities, POS and sundry occupancy.
B11: E-commerce sales change (before migration) | D11: 0 | E11: 0.02 | F11: 0
B12: Share of lost store demand migrating to e-commerce | D12: 0 | E12: 0 | F12: 0.25 | H12: Deliberately NOT 100%: walk-in and tourist demand does not follow the brand online.
B13: Digital marketing spend factor | D13: 1 | E13: 1 | F13: 1.3 | H13: Exit case funds paid media to recapture migrating demand.
B14: Store closure effective at the end of week (0 = no closure) | D14: 0 | E14: 0 | F14: 4
B15: One-off exit costs | D15: 0 | E15: 0 | F15: 96000 | H15: Lease break S$33k, reinstatement S$45k, redundancy S$18k.
B16: Share of exit costs settled in the first instalment | D16: 0 | E16: 0 | F16: 0.5
B17: First exit-cost instalment - week | D17: 0 | E17: 0 | F17: 5
B18: Second exit-cost instalment - week | D18: 0 | E18: 0 | F18: 7
B19: Store inventory release - one-off cash inflow | D19: 0 | E19: 0 | F19: 42000 | H19: Clearance of store floor stock.
B20: Week of inventory release | D20: 0 | E20: 0 | F20: 6
B21: Inventory replenishment factor after closure (x base) | D21: 1 | E21: 1 | F21: 0.8 | H21: Smaller forward buy once the store is gone.
B23: MONTHLY RUN-RATE P&L - steady state once each scenario is fully in effect
B24: SGD per month | D24: 1. Current Operations | E24: 2. Store Improvement | F24: 3. Store Exit / Channel Shift | G24: S2 vs S1 | H24: S3 vs S1
B25: Store net sales | D25: ='Channel Profitability'!$D$55*(1+$D$7)*IF($D$14=0,1,0) -> 82720 | E25: ='Channel Profitability'!$D$55*(1+$E$7)*IF($E$14=0,1,0) -> 87683.2 | F25: ='Channel Profitability'!$D$55*(1+$F$7)*IF($F$14=0,1,0) -> 0 | G25: =E25-D25 -> 4963.2 | H25: =F25-D25 -> -82720
B26: E-commerce net sales | D26: ='Channel Profitability'!$E$55*(1+$D$11)+'Channel Profitability'!$D$55*(1-IF($D$14=0,1,0))*$D$12 -> 83600 | E26: ='Channel Profitability'!$E$55*(1+$E$11)+'Channel Profitability'!$D$55*(1-IF($E$14=0,1,0))*$E$12 -> 85272 | F26: ='Channel Profitability'!$E$55*(1+$F$11)+'Channel Profitability'!$D$55*(1-IF($F$14=0,1,0))*$F$12 -> 104280 | G26: =E26-D26 -> 1672 | H26: =F26-D26 -> 20680
B27: Events / pop-up net sales | D27: ='Channel Profitability'!$F$55 -> 29100 | E27: ='Channel Profitability'!$F$55 -> 29100 | F27: ='Channel Profitability'!$F$55 -> 29100 | G27: =E27-D27 -> 0 | H27: =F27-D27 -> 0
B28: Consignment net sales | D28: ='Channel Profitability'!$G$55 -> 34000 | E28: ='Channel Profitability'!$G$55 -> 34000 | F28: ='Channel Profitability'!$G$55 -> 34000 | G28: =E28-D28 -> 0 | H28: =F28-D28 -> 0
B29: NET REVENUE | D29: =SUM(D25:D28) -> 229420 | E29: =SUM(E25:E28) -> 236055.2 | F29: =SUM(F25:F28) -> 167380 | G29: =E29-D29 -> 6635.2 | H29: =F29-D29 -> -62040
B30: Gross profit | D30: =D25*(Assumptions!$C$28+$D$8)+D26*Assumptions!$C$29+D27*Assumptions!$C$30+D28*Assumptions!$C$31 -> 137161.6 | E30: =E25*(Assumptions!$C$28+$E$8)+E26*Assumptions!$C$29+E27*Assumptions!$C$30+E28*Assumptions!$C$31 -> 142358.7 | F30: =F25*(Assumptions!$C$28+$F$8)+F26*Assumptions!$C$29+F27*Assumptions!$C$30+F28*Assumptions!$C$31 -> 101592 | G30: =E30-D30 -> 5197.104 | H30: =F30-D30 -> -35569.6
B31: Gross margin % | D31: =IFERROR(D30/D29,0) -> 0.59786244 | E31: =IFERROR(E30/E29,0) -> 0.60307379 | F31: =IFERROR(F30/F29,0) -> 0.60695424 | G31: =E31-D31 -> 0.0052113538 | H31: =F31-D31 -> 0.0090918002
B33: Contribution margin % - physical store | D33: =Assumptions!$C$28+$D$8-Assumptions!$C$34-Assumptions!$C$37-Assumptions!$C$38 -> 0.524 | E33: =Assumptions!$C$28+$E$8-Assumptions!$C$34-Assumptions!$C$37-Assumptions!$C$38 -> 0.539 | F33: =Assumptions!$C$28+$F$8-Assumptions!$C$34-Assumptions!$C$37-Assumptions!$C$38 -> 0.524
B34: Contribution margin % - e-commerce | D34: =Assumptions!$C$29-Assumptions!$C$35-Assumptions!$C$39-Assumptions!$C$40*$D$13 -> 0.416 | E34: =Assumptions!$C$29-Assumptions!$C$35-Assumptions!$C$39-Assumptions!$C$40*$E$13 -> 0.416 | F34: =Assumptions!$C$29-Assumptions!$C$35-Assumptions!$C$39-Assumptions!$C$40*$F$13 -> 0.389
B35: Contribution margin % - events | D35: =Assumptions!$C$30-Assumptions!$C$36-Assumptions!$C$41 -> 0.441 | E35: =Assumptions!$C$30-Assumptions!$C$36-Assumptions!$C$41 -> 0.441 | F35: =Assumptions!$C$30-Assumptions!$C$36-Assumptions!$C$41 -> 0.441
B36: Contribution margin % - consignment | D36: =Assumptions!$C$31-Assumptions!$C$42-Assumptions!$C$43 -> 0.285 | E36: =Assumptions!$C$31-Assumptions!$C$42-Assumptions!$C$43 -> 0.285 | F36: =Assumptions!$C$31-Assumptions!$C$42-Assumptions!$C$43 -> 0.285
B38: Contribution profit - physical store | D38: =D25*D33 -> 43345.28 | E38: =E25*E33 -> 47261.245 | F38: =F25*F33 -> 0 | G38: =E38-D38 -> 3915.9648 | H38: =F38-D38 -> -43345.28
B39: Contribution profit - e-commerce | D39: =D26*D34 -> 34777.6 | E39: =E26*E34 -> 35473.152 | F39: =F26*F34 -> 40564.92 | G39: =E39-D39 -> 695.552 | H39: =F39-D39 -> 5787.32
B40: Contribution profit - events / pop-ups | D40: =D27*D35 -> 12833.1 | E40: =E27*E35 -> 12833.1 | F40: =F27*F35 -> 12833.1 | G40: =E40-D40 -> 0 | H40: =F40-D40 -> 0
B41: Contribution profit - consignment | D41: =D28*D36 -> 9690 | E41: =E28*E36 -> 9690 | F41: =F28*F36 -> 9690 | G41: =E41-D41 -> 0 | H41: =F41-D41 -> 0
B42: TOTAL CONTRIBUTION PROFIT | D42: =SUM(D38:D41) -> 100645.98 | E42: =SUM(E38:E41) -> 105257.5 | F42: =SUM(F38:F41) -> 63088.02 | G42: =E42-D42 -> 4611.5168 | H42: =F42-D42 -> -37557.96
B43: Contribution margin % | D43: =IFERROR(D42/D29,0) -> 0.4386975 | E43: =IFERROR(E42/E29,0) -> 0.44590205 | F43: =IFERROR(F42/F29,0) -> 0.37691492 | G43: =E43-D43 -> 0.0072045486 | H43: =F43-D43 -> -0.061782574
B45: Direct fixed costs - physical store | D45: =-IF($D$14=0,1,0)*(Assumptions!$C$46+Assumptions!$C$47*(1+$D$9)+(Assumptions!$C$48+Assumptions!$C$49+Assumptions!$C$50)*(1+$D$10)) -> -44450 | E45: =-IF($E$14=0,1,0)*(Assumptions!$C$46+Assumptions!$C$47*(1+$E$9)+(Assumptions!$C$48+Assumptions!$C$49+Assumptions!$C$50)*(1+$E$10)) -> -41914 | F45: =-IF($F$14=0,1,0)*(Assumptions!$C$46+Assumptions!$C$47*(1+$F$9)+(Assumptions!$C$48+Assumptions!$C$49+Assumptions!$C$50)*(1+$F$10)) -> 0 | G45: =E45-D45 -> 2536 | H45: =F45-D45 -> 44450
B46: Direct fixed costs - e-commerce | D46: =-Assumptions!$C$56 -> -6300 | E46: =-Assumptions!$C$56 -> -6300 | F46: =-Assumptions!$C$56 -> -6300 | G46: =E46-D46 -> 0 | H46: =F46-D46 -> 0
B47: Total direct fixed costs | D47: =D45+D46 -> -50750 | E47: =E45+E46 -> -48214 | F47: =F45+F46 -> -6300 | G47: =E47-D47 -> 2536 | H47: =F47-D47 -> 44450
B48: Direct channel profit | D48: =D42+D47 -> 49895.98 | E48: =E42+E47 -> 57043.497 | F48: =F42+F47 -> 56788.02 | G48: =E48-D48 -> 7147.5168 | H48: =F48-D48 -> 6892.04
B49: Shared overhead | D49: =-Assumptions!$C$64 -> -29700 | E49: =-Assumptions!$C$64 -> -29700 | F49: =-Assumptions!$C$64 -> -29700 | G49: =E49-D49 -> 0 | H49: =F49-D49 -> 0
B50: OPERATING PROFIT (monthly run-rate) | D50: =D48+D49 -> 20195.98 | E50: =E48+E49 -> 27343.497 | F50: =F48+F49 -> 27088.02 | G50: =E50-D50 -> 7147.5168 | H50: =F50-D50 -> 6892.04
B51: Operating margin % | D51: =IFERROR(D50/D29,0) -> 0.088030599 | E51: =IFERROR(E50/E29,0) -> 0.11583518 | F51: =IFERROR(F50/F29,0) -> 0.16183546 | G51: =E51-D51 -> 0.027804582 | H51: =F51-D51 -> 0.073804865
B53: Store break-even net sales per month | D53: =IFERROR(-D45/D33,0) -> 84828.244 | E53: =IFERROR(-E45/E33,0) -> 77762.523 | F53: =IFERROR(-F45/F33,0) -> 0
B54: Store net sales vs break-even | D54: =IFERROR(D25/D53-1,0) -> -0.024853093 | E54: =IFERROR(E25/E53-1,0) -> 0.12757658 | F54: =IFERROR(F25/F53-1,0) -> 0 | J54: Negative = the store is trading below its own break-even point.
B56: 13-WEEK CASH OUTCOME COMPARISON - linked to the weekly blocks below
B57: SGD unless stated | D57: 1. Current Operations | E57: 2. Store Improvement | F57: 3. Store Exit / Channel Shift | G57: S2 vs S1 | H57: S3 vs S1
B58: Net sales over 13 weeks | D58: =Q91 -> 747630.46 | E58: =Q124 -> 768487.58 | F58: =Q157 -> 615535.32 | G58: =E58-D58 -> 20857.122 | H58: =F58-D58 -> -132095.14
B59: Cash receipts | D59: =Q98 -> 713689.48 | E59: =Q131 -> 734364.57 | F59: =Q164 -> 624518.86 | G59: =E59-D59 -> 20675.089 | H59: =F59-D59 -> -89170.622
B60: Cash outflows | D60: =Q109 -> 779039.27 | E60: =Q142 -> 776062.93 | F60: =Q175 -> 718939.51 | G60: =E60-D60 -> -2976.3344 | H60: =F60-D60 -> -60099.757
B61: Net cash movement | D61: =Q110 -> -65349.783 | E61: =Q143 -> -41698.36 | F61: =Q176 -> -94420.649 | G61: =E61-D61 -> 23651.423 | H61: =F61-D61 -> -29070.866
B62: Opening cash | D62: =D111 -> 205000 | E62: =D144 -> 205000 | F62: =D177 -> 205000
B63: CLOSING CASH - WEEK 13 | D63: =P112 -> 139650.22 | E63: =P145 -> 163301.64 | F63: =P178 -> 110579.35 | G63: =E63-D63 -> 23651.423 | H63: =F63-D63 -> -29070.866
B64: Lowest projected cash balance | D64: =MIN(D112:P112) -> 114528.43 | E64: =MIN(D145:P145) -> 130288.23 | F64: =MIN(D178:P178) -> 79427.177 | G64: =E64-D64 -> 15759.792 | H64: =F64-D64 -> -35101.258
B65: Week of lowest cash | D65: =MATCH(MIN(D112:P112),D112:P112,0) -> 9 | E65: =MATCH(MIN(D145:P145),D145:P145,0) -> 9 | F65: =MATCH(MIN(D178:P178),D178:P178,0) -> 11
B66: Headroom / (shortfall) at the lowest point | D66: =MIN(D113:P113) -> -5471.5654 | E66: =MIN(D146:P146) -> 10288.226 | F66: =MIN(D179:P179) -> -40572.823 | G66: =E66-D66 -> 15759.792 | H66: =F66-D66 -> -35101.258
B67: Weeks below the minimum cash threshold | D67: =COUNTIF(D113:P113,"<0") -> 1 | E67: =COUNTIF(D146:P146,"<0") -> 0 | F67: =COUNTIF(D179:P179,"<0") -> 6
B68: Average weekly net cash movement | D68: =Q110/13 -> -5026.9064 | E68: =Q143/13 -> -3207.5662 | F68: =Q176/13 -> -7263.1268 | G68: =E68-D68 -> 1819.3403 | H68: =F68-D68 -> -2236.2204
B69: Cash runway at the average weekly burn | D69: =IF(D68<0,-P112/D68,"n/a - cash generative") -> 27.780548 | E69: =IF(E68<0,-P145/E68,"n/a - cash generative") -> 50.911386 | F69: =IF(F68<0,-P178/F68,"n/a - cash generative") -> 15.224758
B71: DECISION THRESHOLDS - what has to be true for each course of action to be right
B72: Migration required for Scenario 3 to match Scenario 1 | F72: =IFERROR(($D$50-($F$34*'Channel Profitability'!$E$55+$F$40+$F$41+$F$46+$F$49))/($F$34*'Channel Profitability'!$D$55),0) -> 0.035815686 | H72: Share of lost store demand that must move online.
B73: Migration required for Scenario 3 to match Scenario 2 | F73: =IFERROR(($E$50-($F$34*'Channel Profitability'!$E$55+$F$40+$F$41+$F$46+$F$49))/($F$34*'Channel Profitability'!$D$55),0) -> 0.25793947 | H73: Compare with the 25% migration assumed in the exit case.
B74: Store monthly net sales required to break even - current cost base | F74: =$D$53 -> 84828.244
B75: Store monthly net sales required to break even - improvement cost base | F75: =$E$53 -> 77762.523
B76: Net one-off cash cost of exit (exit costs less inventory release) | F76: =$F$15-$F$19 -> 54000
B77: Monthly operating profit uplift of Scenario 3 over Scenario 1 | F77: =$F$50-$D$50 -> 6892.04
B78: Payback period on the net exit cost (months) | F78: =IF(F77<=0,"no payback",IFERROR(F76/F77,"n/a")) -> 7.8351257
B80: =_xlfn._LONGTEXT("Trade-off: Scenario 2 protects revenue and delivers the strongest 13-week cash position, but it depends on management actually achieving the sales and margin uplift. Scenario 3 improves the fixed-cost base permanently, yet it consumes cash first: it spend","s ")&TEXT($F$67,"0")&" of the 13 weeks below the minimum cash buffer and ends the quarter at "&TEXT($F$63,"""S$""#,##0")&", against "&TEXT($E$63,"""S$""#,##0")&" under improvement. On monthly run-rate profit the two are only "&TEXT(ABS($E$50-$F$50),"""S$""#,##0")&" apart: exit needs "&TEXT($F$73,"0.0%")&" of store demand to move online just to match the improvement case, against the "&TEXT($F$12,"0.0%")&" assumed here - so the choice turns on cash timing, execution risk and reversibility rather than on run-rate profit." -> Trade-off: Scenario 2 protects revenue and delivers the strongest 13-week cash position, but it depends on management actually achieving the sales and margin uplift. Scenario 3 improves the fixed-cost base permanently, yet it consumes cash first: it spends 6 of the 13 weeks below the minimum cash buffer and ends the quarter at S$110,579, against S$163,302 under improvement. On monthly run-rate profit the two are only S$255 apart: exit needs 25.8% of store demand to move online just to match the improvement case, against the 25.0% assumed here - so the choice turns on cash timing, execution risk and reversibility rather than on run-rate profit.
B83: SCENARIO 1 - CURRENT OPERATIONS: 13-week cash flow (SGD)
B84: SGD | C84: Driver | D84: W1 | E84: W2 | F84: W3 | G84: W4 | H84: W5 | I84: W6 | J84: W7 | K84: W8 | L84: W9 | M84: W10 | N84: W11 | O84: W12 | P84: W13 | Q84: 13-Week Total
B85: Week number | D85: ='13W Cash Flow'!D$6 -> 1 | E85: ='13W Cash Flow'!E$6 -> 2 | F85: ='13W Cash Flow'!F$6 -> 3 | G85: ='13W Cash Flow'!G$6 -> 4 | H85: ='13W Cash Flow'!H$6 -> 5 | I85: ='13W Cash Flow'!I$6 -> 6 | J85: ='13W Cash Flow'!J$6 -> 7 | K85: ='13W Cash Flow'!K$6 -> 8 | ... P85: ='13W Cash Flow'!P$6 -> 13
B86: Store open factor (1 = trading, 0 = closed) | C86: closure week test | D86: =IF(OR($D$14=0,D$85<=$D$14),1,0) -> 1 | E86: =IF(OR($D$14=0,E$85<=$D$14),1,0) -> 1 | F86: =IF(OR($D$14=0,F$85<=$D$14),1,0) -> 1 | G86: =IF(OR($D$14=0,G$85<=$D$14),1,0) -> 1 | H86: =IF(OR($D$14=0,H$85<=$D$14),1,0) -> 1 | I86: =IF(OR($D$14=0,I$85<=$D$14),1,0) -> 1 | J86: =IF(OR($D$14=0,J$85<=$D$14),1,0) -> 1 | K86: =IF(OR($D$14=0,K$85<=$D$14),1,0) -> 1 | ... P86: =IF(OR($D$14=0,P$85<=$D$14),1,0) -> 1
B87: Store net sales | C87: base x lever | D87: ='13W Cash Flow'!D$73*(1+$D$7)*D86 -> 18127.9 | E87: ='13W Cash Flow'!E$73*(1+$D$7)*E86 -> 20608.56 | F87: ='13W Cash Flow'!F$73*(1+$D$7)*F86 -> 17555.44 | G87: ='13W Cash Flow'!G$73*(1+$D$7)*G86 -> 17173.8 | H87: ='13W Cash Flow'!H$73*(1+$D$7)*H86 -> 17746.26 | I87: ='13W Cash Flow'!I$73*(1+$D$7)*I86 -> 18509.54 | J87: ='13W Cash Flow'!J$73*(1+$D$7)*J86 -> 19082 | K87: ='13W Cash Flow'!K$73*(1+$D$7)*K86 -> 19463.64 | ... P87: ='13W Cash Flow'!P$73*(1+$D$7)*P86 -> 21753.48 | Q87: =SUM(D87:P87) -> 249592.56
B88: E-commerce net sales | C88: base + migration | D88: ='13W Cash Flow'!D$74*(1+$D$11)+'13W Cash Flow'!D$73*(1-D86)*$D$12 -> 20913.2 | E88: ='13W Cash Flow'!E$74*(1+$D$11)+'13W Cash Flow'!E$73*(1-E86)*$D$12 -> 22638 | F88: ='13W Cash Flow'!F$74*(1+$D$11)+'13W Cash Flow'!F$73*(1-F86)*$D$12 -> 20697.6 | G88: ='13W Cash Flow'!G$74*(1+$D$11)+'13W Cash Flow'!G$73*(1-G86)*$D$12 -> 20482 | H88: ='13W Cash Flow'!H$74*(1+$D$11)+'13W Cash Flow'!H$73*(1-H86)*$D$12 -> 21344.4 | I88: ='13W Cash Flow'!I$74*(1+$D$11)+'13W Cash Flow'!I$73*(1-I86)*$D$12 -> 21991.2 | J88: ='13W Cash Flow'!J$74*(1+$D$11)+'13W Cash Flow'!J$73*(1-J86)*$D$12 -> 22422.4 | K88: ='13W Cash Flow'!K$74*(1+$D$11)+'13W Cash Flow'!K$73*(1-K86)*$D$12 -> 22853.6 | ... P88: ='13W Cash Flow'!P$74*(1+$D$11)+'13W Cash Flow'!P$73*(1-P86)*$D$12 -> 25872 | Q88: =SUM(D88:P88) -> 294078.4
B89: Events / pop-up net sales | C89: unchanged | D89: ='13W Cash Flow'!D$75 -> 0 | E89: ='13W Cash Flow'!E$75 -> 23280 | F89: ='13W Cash Flow'!F$75 -> 0 | G89: ='13W Cash Flow'!G$75 -> 0 | H89: ='13W Cash Flow'!H$75 -> 0 | I89: ='13W Cash Flow'!I$75 -> 0 | J89: ='13W Cash Flow'!J$75 -> 18624 | K89: ='13W Cash Flow'!K$75 -> 0 | ... P89: ='13W Cash Flow'!P$75 -> 25608 | Q89: =SUM(D89:P89) -> 100104
B90: Consignment net sales | C90: unchanged | D90: ='13W Cash Flow'!D$76 -> 7536 | E90: ='13W Cash Flow'!E$76 -> 7850 | F90: ='13W Cash Flow'!F$76 -> 7457.5 | G90: ='13W Cash Flow'!G$76 -> 7379 | H90: ='13W Cash Flow'!H$76 -> 7614.5 | I90: ='13W Cash Flow'!I$76 -> 7850 | J90: ='13W Cash Flow'!J$76 -> 8007 | K90: ='13W Cash Flow'!K$76 -> 8085.5 | ... P90: ='13W Cash Flow'!P$76 -> 8792 | Q90: =SUM(D90:P90) -> 103855.5
B91: Total net sales | D91: =SUM(D87:D90) -> 46577.1 | E91: =SUM(E87:E90) -> 74376.56 | F91: =SUM(F87:F90) -> 45710.54 | G91: =SUM(G87:G90) -> 45034.8 | H91: =SUM(H87:H90) -> 46705.16 | I91: =SUM(I87:I90) -> 48350.74 | J91: =SUM(J87:J90) -> 68135.4 | K91: =SUM(K87:K90) -> 50402.74 | ... P91: =SUM(P87:P90) -> 82025.48 | Q91: =SUM(D91:P91) -> 747630.46
B92: Total cost of goods sold | D92: =D87*(1-Assumptions!$C$28-$D$8)+D88*(1-Assumptions!$C$29)+D89*(1-Assumptions!$C$30)+D90*(1-Assumptions!$C$31) -> 18993.398 | E92: =E87*(1-Assumptions!$C$28-$D$8)+E88*(1-Assumptions!$C$29)+E89*(1-Assumptions!$C$30)+E90*(1-Assumptions!$C$31) -> 29231.595 | F92: =F87*(1-Assumptions!$C$28-$D$8)+F88*(1-Assumptions!$C$29)+F89*(1-Assumptions!$C$30)+F90*(1-Assumptions!$C$31) -> 18635.325 | G92: =G87*(1-Assumptions!$C$28-$D$8)+G88*(1-Assumptions!$C$29)+G89*(1-Assumptions!$C$30)+G90*(1-Assumptions!$C$31) -> 18357.396 | H92: =H87*(1-Assumptions!$C$28-$D$8)+H88*(1-Assumptions!$C$29)+H89*(1-Assumptions!$C$30)+H90*(1-Assumptions!$C$31) -> 19036.989 | I92: =I87*(1-Assumptions!$C$28-$D$8)+I88*(1-Assumptions!$C$29)+I89*(1-Assumptions!$C$30)+I90*(1-Assumptions!$C$31) -> 19710.487 | J92: =J87*(1-Assumptions!$C$28-$D$8)+J88*(1-Assumptions!$C$29)+J89*(1-Assumptions!$C$30)+J90*(1-Assumptions!$C$31) -> 26890.84 | K92: =K87*(1-Assumptions!$C$28-$D$8)+K88*(1-Assumptions!$C$29)+K89*(1-Assumptions!$C$30)+K90*(1-Assumptions!$C$31) -> 20550.369 | ... P92: =P87*(1-Assumptions!$C$28-$D$8)+P88*(1-Assumptions!$C$29)+P89*(1-Assumptions!$C$30)+P90*(1-Assumptions!$C$31) -> 32220.942 | Q92: =SUM(D92:P92) -> 300039.88
B93: Store receipts | C93: 92% same week | D93: =D87*Assumptions!$C$67+IF(D85=1,Assumptions!$C$72,INDEX($D$87:$P$87,1,D85-1)*(1-Assumptions!$C$67)) -> 18197.668 | E93: =E87*Assumptions!$C$67+IF(E85=1,Assumptions!$C$72,INDEX($D$87:$P$87,1,E85-1)*(1-Assumptions!$C$67)) -> 20410.107 | F93: =F87*Assumptions!$C$67+IF(F85=1,Assumptions!$C$72,INDEX($D$87:$P$87,1,F85-1)*(1-Assumptions!$C$67)) -> 17799.69 | G93: =G87*Assumptions!$C$67+IF(G85=1,Assumptions!$C$72,INDEX($D$87:$P$87,1,G85-1)*(1-Assumptions!$C$67)) -> 17204.331 | H93: =H87*Assumptions!$C$67+IF(H85=1,Assumptions!$C$72,INDEX($D$87:$P$87,1,H85-1)*(1-Assumptions!$C$67)) -> 17700.463 | I93: =I87*Assumptions!$C$67+IF(I85=1,Assumptions!$C$72,INDEX($D$87:$P$87,1,I85-1)*(1-Assumptions!$C$67)) -> 18448.478 | J93: =J87*Assumptions!$C$67+IF(J85=1,Assumptions!$C$72,INDEX($D$87:$P$87,1,J85-1)*(1-Assumptions!$C$67)) -> 19036.203 | K93: =K87*Assumptions!$C$67+IF(K85=1,Assumptions!$C$72,INDEX($D$87:$P$87,1,K85-1)*(1-Assumptions!$C$67)) -> 19433.109 | ... P93: =P87*Assumptions!$C$67+IF(P85=1,Assumptions!$C$72,INDEX($D$87:$P$87,1,P85-1)*(1-Assumptions!$C$67)) -> 21692.418 | Q93: =SUM(D93:P93) -> 249372.28
B94: E-commerce receipts | C94: 85% same week | D94: =D88*Assumptions!$C$68+IF(D85=1,Assumptions!$C$73,INDEX($D$88:$P$88,1,D85-1)*(1-Assumptions!$C$68)) -> 21016.22 | E94: =E88*Assumptions!$C$68+IF(E85=1,Assumptions!$C$73,INDEX($D$88:$P$88,1,E85-1)*(1-Assumptions!$C$68)) -> 22379.28 | F94: =F88*Assumptions!$C$68+IF(F85=1,Assumptions!$C$73,INDEX($D$88:$P$88,1,F85-1)*(1-Assumptions!$C$68)) -> 20988.66 | G94: =G88*Assumptions!$C$68+IF(G85=1,Assumptions!$C$73,INDEX($D$88:$P$88,1,G85-1)*(1-Assumptions!$C$68)) -> 20514.34 | H94: =H88*Assumptions!$C$68+IF(H85=1,Assumptions!$C$73,INDEX($D$88:$P$88,1,H85-1)*(1-Assumptions!$C$68)) -> 21215.04 | I94: =I88*Assumptions!$C$68+IF(I85=1,Assumptions!$C$73,INDEX($D$88:$P$88,1,I85-1)*(1-Assumptions!$C$68)) -> 21894.18 | J94: =J88*Assumptions!$C$68+IF(J85=1,Assumptions!$C$73,INDEX($D$88:$P$88,1,J85-1)*(1-Assumptions!$C$68)) -> 22357.72 | K94: =K88*Assumptions!$C$68+IF(K85=1,Assumptions!$C$73,INDEX($D$88:$P$88,1,K85-1)*(1-Assumptions!$C$68)) -> 22788.92 | ... P94: =P88*Assumptions!$C$68+IF(P85=1,Assumptions!$C$73,INDEX($D$88:$P$88,1,P85-1)*(1-Assumptions!$C$68)) -> 25710.3 | Q94: =SUM(D94:P94) -> 293437.6
B95: Events / pop-up receipts | C95: banked at event | D95: =D89*Assumptions!$C$69+IF(D85=1,0,INDEX($D$89:$P$89,1,D85-1)*(1-Assumptions!$C$69)) -> 0 | E95: =E89*Assumptions!$C$69+IF(E85=1,0,INDEX($D$89:$P$89,1,E85-1)*(1-Assumptions!$C$69)) -> 23280 | F95: =F89*Assumptions!$C$69+IF(F85=1,0,INDEX($D$89:$P$89,1,F85-1)*(1-Assumptions!$C$69)) -> 0 | G95: =G89*Assumptions!$C$69+IF(G85=1,0,INDEX($D$89:$P$89,1,G85-1)*(1-Assumptions!$C$69)) -> 0 | H95: =H89*Assumptions!$C$69+IF(H85=1,0,INDEX($D$89:$P$89,1,H85-1)*(1-Assumptions!$C$69)) -> 0 | I95: =I89*Assumptions!$C$69+IF(I85=1,0,INDEX($D$89:$P$89,1,I85-1)*(1-Assumptions!$C$69)) -> 0 | J95: =J89*Assumptions!$C$69+IF(J85=1,0,INDEX($D$89:$P$89,1,J85-1)*(1-Assumptions!$C$69)) -> 18624 | K95: =K89*Assumptions!$C$69+IF(K85=1,0,INDEX($D$89:$P$89,1,K85-1)*(1-Assumptions!$C$69)) -> 0 | ... P95: =P89*Assumptions!$C$69+IF(P85=1,0,INDEX($D$89:$P$89,1,P85-1)*(1-Assumptions!$C$69)) -> 25608 | Q95: =SUM(D95:P95) -> 100104
B96: Consignment receipts (net of commission) | C96: 4-week lag | D96: =IF(D85<=Assumptions!$C$70,Assumptions!$C$74/Assumptions!$C$70,INDEX($D$90:$P$90,1,D85-Assumptions!$C$70)*(1-Assumptions!$C$42)) -> 5495 | E96: =IF(E85<=Assumptions!$C$70,Assumptions!$C$74/Assumptions!$C$70,INDEX($D$90:$P$90,1,E85-Assumptions!$C$70)*(1-Assumptions!$C$42)) -> 5495 | F96: =IF(F85<=Assumptions!$C$70,Assumptions!$C$74/Assumptions!$C$70,INDEX($D$90:$P$90,1,F85-Assumptions!$C$70)*(1-Assumptions!$C$42)) -> 5495 | G96: =IF(G85<=Assumptions!$C$70,Assumptions!$C$74/Assumptions!$C$70,INDEX($D$90:$P$90,1,G85-Assumptions!$C$70)*(1-Assumptions!$C$42)) -> 5495 | H96: =IF(H85<=Assumptions!$C$70,Assumptions!$C$74/Assumptions!$C$70,INDEX($D$90:$P$90,1,H85-Assumptions!$C$70)*(1-Assumptions!$C$42)) -> 5275.2 | I96: =IF(I85<=Assumptions!$C$70,Assumptions!$C$74/Assumptions!$C$70,INDEX($D$90:$P$90,1,I85-Assumptions!$C$70)*(1-Assumptions!$C$42)) -> 5495 | J96: =IF(J85<=Assumptions!$C$70,Assumptions!$C$74/Assumptions!$C$70,INDEX($D$90:$P$90,1,J85-Assumptions!$C$70)*(1-Assumptions!$C$42)) -> 5220.25 | K96: =IF(K85<=Assumptions!$C$70,Assumptions!$C$74/Assumptions!$C$70,INDEX($D$90:$P$90,1,K85-Assumptions!$C$70)*(1-Assumptions!$C$42)) -> 5165.3 | ... P96: =IF(P85<=Assumptions!$C$70,Assumptions!$C$74/Assumptions!$C$70,INDEX($D$90:$P$90,1,P85-Assumptions!$C$70)*(1-Assumptions!$C$42)) -> 5549.95 | Q96: =SUM(D96:P96) -> 70775.6
B97: One-off receipts (inventory release / other) | C97: one-off schedule | D97: =IF(D85=$D$20,$D$19,0)+IF(D85=Assumptions!$C$125,Assumptions!$C$124,0) -> 0 | E97: =IF(E85=$D$20,$D$19,0)+IF(E85=Assumptions!$C$125,Assumptions!$C$124,0) -> 0 | F97: =IF(F85=$D$20,$D$19,0)+IF(F85=Assumptions!$C$125,Assumptions!$C$124,0) -> 0 | G97: =IF(G85=$D$20,$D$19,0)+IF(G85=Assumptions!$C$125,Assumptions!$C$124,0) -> 0 | H97: =IF(H85=$D$20,$D$19,0)+IF(H85=Assumptions!$C$125,Assumptions!$C$124,0) -> 0 | I97: =IF(I85=$D$20,$D$19,0)+IF(I85=Assumptions!$C$125,Assumptions!$C$124,0) -> 0 | J97: =IF(J85=$D$20,$D$19,0)+IF(J85=Assumptions!$C$125,Assumptions!$C$124,0) -> 0 | K97: =IF(K85=$D$20,$D$19,0)+IF(K85=Assumptions!$C$125,Assumptions!$C$124,0) -> 0 | ... P97: =IF(P85=$D$20,$D$19,0)+IF(P85=Assumptions!$C$125,Assumptions!$C$124,0) -> 0 | Q97: =SUM(D97:P97) -> 0
B98: Total cash receipts | D98: =SUM(D93:D97) -> 44708.888 | E98: =SUM(E93:E97) -> 71564.387 | F98: =SUM(F93:F97) -> 44283.35 | G98: =SUM(G93:G97) -> 43213.671 | H98: =SUM(H93:H97) -> 44190.703 | I98: =SUM(I93:I97) -> 45837.658 | J98: =SUM(J93:J97) -> 65238.173 | K98: =SUM(K93:K97) -> 47387.329 | ... P98: =SUM(P93:P97) -> 78560.668 | Q98: =SUM(D98:P98) -> 713689.48
B99: Inventory and supplier payments | C99: replenish + AW26 | D99: =D92*Assumptions!$C$76*IF(D86=1,1,$D$21)+SUMIFS(Assumptions!$C$116:$C$119,Assumptions!$D$116:$D$119,D85) -> 11016.171 | E99: =E92*Assumptions!$C$76*IF(E86=1,1,$D$21)+SUMIFS(Assumptions!$C$116:$C$119,Assumptions!$D$116:$D$119,E85) -> 70954.325 | F99: =F92*Assumptions!$C$76*IF(F86=1,1,$D$21)+SUMIFS(Assumptions!$C$116:$C$119,Assumptions!$D$116:$D$119,F85) -> 10808.488 | G99: =G92*Assumptions!$C$76*IF(G86=1,1,$D$21)+SUMIFS(Assumptions!$C$116:$C$119,Assumptions!$D$116:$D$119,G85) -> 10647.29 | H99: =H92*Assumptions!$C$76*IF(H86=1,1,$D$21)+SUMIFS(Assumptions!$C$116:$C$119,Assumptions!$D$116:$D$119,H85) -> 57041.454 | I99: =I92*Assumptions!$C$76*IF(I86=1,1,$D$21)+SUMIFS(Assumptions!$C$116:$C$119,Assumptions!$D$116:$D$119,I85) -> 11432.082 | J99: =J92*Assumptions!$C$76*IF(J86=1,1,$D$21)+SUMIFS(Assumptions!$C$116:$C$119,Assumptions!$D$116:$D$119,J85) -> 15596.687 | K99: =K92*Assumptions!$C$76*IF(K86=1,1,$D$21)+SUMIFS(Assumptions!$C$116:$C$119,Assumptions!$D$116:$D$119,K85) -> 93919.214 | ... P99: =P92*Assumptions!$C$76*IF(P86=1,1,$D$21)+SUMIFS(Assumptions!$C$116:$C$119,Assumptions!$D$116:$D$119,P85) -> 18688.146 | Q99: =SUM(D99:P99) -> 409023.13
B100: Payroll - store and corporate | C100: month end | D100: =(Assumptions!$C$47*(1+$D$9)*D$183+Assumptions!$C$92)*'13W Cash Flow'!D$70 -> 0 | E100: =(Assumptions!$C$47*(1+$D$9)*E$183+Assumptions!$C$92)*'13W Cash Flow'!E$70 -> 0 | F100: =(Assumptions!$C$47*(1+$D$9)*F$183+Assumptions!$C$92)*'13W Cash Flow'!F$70 -> 0 | G100: =(Assumptions!$C$47*(1+$D$9)*G$183+Assumptions!$C$92)*'13W Cash Flow'!G$70 -> 0 | H100: =(Assumptions!$C$47*(1+$D$9)*H$183+Assumptions!$C$92)*'13W Cash Flow'!H$70 -> 44700 | I100: =(Assumptions!$C$47*(1+$D$9)*I$183+Assumptions!$C$92)*'13W Cash Flow'!I$70 -> 0 | J100: =(Assumptions!$C$47*(1+$D$9)*J$183+Assumptions!$C$92)*'13W Cash Flow'!J$70 -> 0 | K100: =(Assumptions!$C$47*(1+$D$9)*K$183+Assumptions!$C$92)*'13W Cash Flow'!K$70 -> 0 | ... P100: =(Assumptions!$C$47*(1+$D$9)*P$183+Assumptions!$C$92)*'13W Cash Flow'!P$70 -> 44700 | Q100: =SUM(D100:P100) -> 134100
B101: Rent and store occupancy | C101: 1st / 10th / 15th | D101: =D86*(Assumptions!$C$46*'13W Cash Flow'!D$65+(Assumptions!$C$48*'13W Cash Flow'!D$68+Assumptions!$C$49*'13W Cash Flow'!D$67+Assumptions!$C$50*'13W Cash Flow'!D$65)*(1+$D$10)) -> 0 | E101: =E86*(Assumptions!$C$46*'13W Cash Flow'!E$65+(Assumptions!$C$48*'13W Cash Flow'!E$68+Assumptions!$C$49*'13W Cash Flow'!E$67+Assumptions!$C$50*'13W Cash Flow'!E$65)*(1+$D$10)) -> 3050 | F101: =F86*(Assumptions!$C$46*'13W Cash Flow'!F$65+(Assumptions!$C$48*'13W Cash Flow'!F$68+Assumptions!$C$49*'13W Cash Flow'!F$67+Assumptions!$C$50*'13W Cash Flow'!F$65)*(1+$D$10)) -> 0 | G101: =G86*(Assumptions!$C$46*'13W Cash Flow'!G$65+(Assumptions!$C$48*'13W Cash Flow'!G$68+Assumptions!$C$49*'13W Cash Flow'!G$67+Assumptions!$C$50*'13W Cash Flow'!G$65)*(1+$D$10)) -> 0 | H101: =H86*(Assumptions!$C$46*'13W Cash Flow'!H$65+(Assumptions!$C$48*'13W Cash Flow'!H$68+Assumptions!$C$49*'13W Cash Flow'!H$67+Assumptions!$C$50*'13W Cash Flow'!H$65)*(1+$D$10)) -> 22900 | I101: =I86*(Assumptions!$C$46*'13W Cash Flow'!I$65+(Assumptions!$C$48*'13W Cash Flow'!I$68+Assumptions!$C$49*'13W Cash Flow'!I$67+Assumptions!$C$50*'13W Cash Flow'!I$65)*(1+$D$10)) -> 450 | J101: =J86*(Assumptions!$C$46*'13W Cash Flow'!J$65+(Assumptions!$C$48*'13W Cash Flow'!J$68+Assumptions!$C$49*'13W Cash Flow'!J$67+Assumptions!$C$50*'13W Cash Flow'!J$65)*(1+$D$10)) -> 2600 | K101: =K86*(Assumptions!$C$46*'13W Cash Flow'!K$65+(Assumptions!$C$48*'13W Cash Flow'!K$68+Assumptions!$C$49*'13W Cash Flow'!K$67+Assumptions!$C$50*'13W Cash Flow'!K$65)*(1+$D$10)) -> 0 | ... P101: =P86*(Assumptions!$C$46*'13W Cash Flow'!P$65+(Assumptions!$C$48*'13W Cash Flow'!P$68+Assumptions!$C$49*'13W Cash Flow'!P$67+Assumptions!$C$50*'13W Cash Flow'!P$65)*(1+$D$10)) -> 22900 | Q101: =SUM(D101:P101) -> 77850
B102: Marketing - digital and brand | C102: % of e-comm + monthly | D102: =D88*Assumptions!$C$40*$D$13+Assumptions!$C$62*'13W Cash Flow'!D$67 -> 1882.188 | E102: =E88*Assumptions!$C$40*$D$13+Assumptions!$C$62*'13W Cash Flow'!E$67 -> 6537.42 | F102: =F88*Assumptions!$C$40*$D$13+Assumptions!$C$62*'13W Cash Flow'!F$67 -> 1862.784 | G102: =G88*Assumptions!$C$40*$D$13+Assumptions!$C$62*'13W Cash Flow'!G$67 -> 1843.38 | H102: =H88*Assumptions!$C$40*$D$13+Assumptions!$C$62*'13W Cash Flow'!H$67 -> 1920.996 | I102: =I88*Assumptions!$C$40*$D$13+Assumptions!$C$62*'13W Cash Flow'!I$67 -> 6479.208 | J102: =J88*Assumptions!$C$40*$D$13+Assumptions!$C$62*'13W Cash Flow'!J$67 -> 2018.016 | K102: =K88*Assumptions!$C$40*$D$13+Assumptions!$C$62*'13W Cash Flow'!K$67 -> 2056.824 | ... P102: =P88*Assumptions!$C$40*$D$13+Assumptions!$C$62*'13W Cash Flow'!P$67 -> 2328.48 | Q102: =SUM(D102:P102) -> 39967.056
B103: Fulfilment, shipping and handling | C103: % of sales | D103: =D88*Assumptions!$C$39+D90*Assumptions!$C$43 -> 1472.398 | E103: =E88*Assumptions!$C$39+E90*Assumptions!$C$43 -> 1589.22 | F103: =F88*Assumptions!$C$39+F90*Assumptions!$C$43 -> 1457.2065 | G103: =G88*Assumptions!$C$39+G90*Assumptions!$C$43 -> 1442.015 | H103: =H88*Assumptions!$C$39+H90*Assumptions!$C$43 -> 1501.6035 | I103: =I88*Assumptions!$C$39+I90*Assumptions!$C$43 -> 1547.178 | J103: =J88*Assumptions!$C$39+J90*Assumptions!$C$43 -> 1577.561 | K103: =K88*Assumptions!$C$39+K90*Assumptions!$C$43 -> 1606.7665 | ... P103: =P88*Assumptions!$C$39+P90*Assumptions!$C$43 -> 1813.56 | Q103: =SUM(D103:P103) -> 20672.929
B104: Merchant and payment fees | C104: % of sales | D104: =D87*Assumptions!$C$34+D88*Assumptions!$C$35+D89*Assumptions!$C$36 -> 932.785 | E104: =E87*Assumptions!$C$34+E88*Assumptions!$C$35+E89*Assumptions!$C$36 -> 1469.7761 | F104: =F87*Assumptions!$C$34+F88*Assumptions!$C$35+F89*Assumptions!$C$36 -> 916.22832 | G104: =G87*Assumptions!$C$34+G88*Assumptions!$C$35+G89*Assumptions!$C$36 -> 903.1064 | H104: =H87*Assumptions!$C$34+H88*Assumptions!$C$35+H89*Assumptions!$C$36 -> 938.42028 | I104: =I87*Assumptions!$C$34+I88*Assumptions!$C$35+I89*Assumptions!$C$36 -> 970.91652 | J104: =J87*Assumptions!$C$34+J88*Assumptions!$C$35+J89*Assumptions!$C$36 -> 1347.5816 | K104: =K87*Assumptions!$C$34+K88*Assumptions!$C$35+K89*Assumptions!$C$36 -> 1013.0999 | ... P104: =P87*Assumptions!$C$34+P88*Assumptions!$C$35+P89*Assumptions!$C$36 -> 1628.4026 | Q104: =SUM(D104:P104) -> 14922.916
B105: Event costs and store variable costs | C105: % of sales | D105: =D89*Assumptions!$C$41+D87*(Assumptions!$C$37+Assumptions!$C$38) -> 688.8602 | E105: =E89*Assumptions!$C$41+E87*(Assumptions!$C$37+Assumptions!$C$38) -> 4973.5253 | F105: =F89*Assumptions!$C$41+F87*(Assumptions!$C$37+Assumptions!$C$38) -> 667.10672 | G105: =G89*Assumptions!$C$41+G87*(Assumptions!$C$37+Assumptions!$C$38) -> 652.6044 | H105: =H89*Assumptions!$C$41+H87*(Assumptions!$C$37+Assumptions!$C$38) -> 674.35788 | I105: =I89*Assumptions!$C$41+I87*(Assumptions!$C$37+Assumptions!$C$38) -> 703.36252 | J105: =J89*Assumptions!$C$41+J87*(Assumptions!$C$37+Assumptions!$C$38) -> 4077.436 | K105: =K89*Assumptions!$C$41+K87*(Assumptions!$C$37+Assumptions!$C$38) -> 739.61832 | ... P105: =P89*Assumptions!$C$41+P87*(Assumptions!$C$37+Assumptions!$C$38) -> 5436.0722 | Q105: =SUM(D105:P105) -> 27503.237
B106: Corporate fixed outflows (software, professional fees, admin) | C106: 10th / 20th / 1st | D106: =(Assumptions!$C$61+Assumptions!$C$54)*'13W Cash Flow'!D$67+Assumptions!$C$60*'13W Cash Flow'!D$69+Assumptions!$C$63*'13W Cash Flow'!D$65 -> 0 | E106: =(Assumptions!$C$61+Assumptions!$C$54)*'13W Cash Flow'!E$67+Assumptions!$C$60*'13W Cash Flow'!E$69+Assumptions!$C$63*'13W Cash Flow'!E$65 -> 2000 | F106: =(Assumptions!$C$61+Assumptions!$C$54)*'13W Cash Flow'!F$67+Assumptions!$C$60*'13W Cash Flow'!F$69+Assumptions!$C$63*'13W Cash Flow'!F$65 -> 1800 | G106: =(Assumptions!$C$61+Assumptions!$C$54)*'13W Cash Flow'!G$67+Assumptions!$C$60*'13W Cash Flow'!G$69+Assumptions!$C$63*'13W Cash Flow'!G$65 -> 0 | H106: =(Assumptions!$C$61+Assumptions!$C$54)*'13W Cash Flow'!H$67+Assumptions!$C$60*'13W Cash Flow'!H$69+Assumptions!$C$63*'13W Cash Flow'!H$65 -> 1500 | I106: =(Assumptions!$C$61+Assumptions!$C$54)*'13W Cash Flow'!I$67+Assumptions!$C$60*'13W Cash Flow'!I$69+Assumptions!$C$63*'13W Cash Flow'!I$65 -> 2000 | J106: =(Assumptions!$C$61+Assumptions!$C$54)*'13W Cash Flow'!J$67+Assumptions!$C$60*'13W Cash Flow'!J$69+Assumptions!$C$63*'13W Cash Flow'!J$65 -> 1800 | K106: =(Assumptions!$C$61+Assumptions!$C$54)*'13W Cash Flow'!K$67+Assumptions!$C$60*'13W Cash Flow'!K$69+Assumptions!$C$63*'13W Cash Flow'!K$65 -> 0 | ... P106: =(Assumptions!$C$61+Assumptions!$C$54)*'13W Cash Flow'!P$67+Assumptions!$C$60*'13W Cash Flow'!P$69+Assumptions!$C$63*'13W Cash Flow'!P$65 -> 1500 | Q106: =SUM(D106:P106) -> 15900
B107: GST settlement and debt service | C107: quarterly / 5th | D107: =IF(D85=Assumptions!$C$89,Assumptions!$C$88,0)+Assumptions!$C$87*'13W Cash Flow'!D$66 -> 4200 | E107: =IF(E85=Assumptions!$C$89,Assumptions!$C$88,0)+Assumptions!$C$87*'13W Cash Flow'!E$66 -> 0 | F107: =IF(F85=Assumptions!$C$89,Assumptions!$C$88,0)+Assumptions!$C$87*'13W Cash Flow'!F$66 -> 0 | G107: =IF(G85=Assumptions!$C$89,Assumptions!$C$88,0)+Assumptions!$C$87*'13W Cash Flow'!G$66 -> 0 | H107: =IF(H85=Assumptions!$C$89,Assumptions!$C$88,0)+Assumptions!$C$87*'13W Cash Flow'!H$66 -> 4200 | I107: =IF(I85=Assumptions!$C$89,Assumptions!$C$88,0)+Assumptions!$C$87*'13W Cash Flow'!I$66 -> 0 | J107: =IF(J85=Assumptions!$C$89,Assumptions!$C$88,0)+Assumptions!$C$87*'13W Cash Flow'!J$66 -> 0 | K107: =IF(K85=Assumptions!$C$89,Assumptions!$C$88,0)+Assumptions!$C$87*'13W Cash Flow'!K$66 -> 0 | ... P107: =IF(P85=Assumptions!$C$89,Assumptions!$C$88,0)+Assumptions!$C$87*'13W Cash Flow'!P$66 -> 0 | Q107: =SUM(D107:P107) -> 39100
B108: One-off exit costs | C108: exit schedule | D108: =IF(D85=$D$17,$D$15*$D$16,0)+IF(D85=$D$18,$D$15*(1-$D$16),0) -> 0 | E108: =IF(E85=$D$17,$D$15*$D$16,0)+IF(E85=$D$18,$D$15*(1-$D$16),0) -> 0 | F108: =IF(F85=$D$17,$D$15*$D$16,0)+IF(F85=$D$18,$D$15*(1-$D$16),0) -> 0 | G108: =IF(G85=$D$17,$D$15*$D$16,0)+IF(G85=$D$18,$D$15*(1-$D$16),0) -> 0 | H108: =IF(H85=$D$17,$D$15*$D$16,0)+IF(H85=$D$18,$D$15*(1-$D$16),0) -> 0 | I108: =IF(I85=$D$17,$D$15*$D$16,0)+IF(I85=$D$18,$D$15*(1-$D$16),0) -> 0 | J108: =IF(J85=$D$17,$D$15*$D$16,0)+IF(J85=$D$18,$D$15*(1-$D$16),0) -> 0 | K108: =IF(K85=$D$17,$D$15*$D$16,0)+IF(K85=$D$18,$D$15*(1-$D$16),0) -> 0 | ... P108: =IF(P85=$D$17,$D$15*$D$16,0)+IF(P85=$D$18,$D$15*(1-$D$16),0) -> 0 | Q108: =SUM(D108:P108) -> 0
B109: Total cash outflows | D109: =SUM(D99:D108) -> 20192.402 | E109: =SUM(E99:E108) -> 90574.267 | F109: =SUM(F99:F108) -> 17511.814 | G109: =SUM(G99:G108) -> 15488.395 | H109: =SUM(H99:H108) -> 135376.83 | I109: =SUM(I99:I108) -> 23582.747 | J109: =SUM(J99:J108) -> 29017.282 | K109: =SUM(K99:K108) -> 99335.523 | ... P109: =SUM(P99:P108) -> 98994.661 | Q109: =SUM(D109:P109) -> 779039.27
B110: Net cash movement | D110: =D98-D109 -> 24516.486 | E110: =E98-E109 -> -19009.879 | F110: =F98-F109 -> 26771.536 | G110: =G98-G109 -> 27725.276 | H110: =H98-H109 -> -91186.128 | I110: =I98-I109 -> 22254.91 | J110: =J98-J109 -> 36220.891 | K110: =K98-K109 -> -51948.194 | ... P110: =P98-P109 -> -20433.993 | Q110: =SUM(D110:P110) -> -65349.783
B111: Opening cash | C111: prior week close | D111: =Assumptions!$C$13 -> 205000 | E111: =D112 -> 229516.49 | F111: =E112 -> 210506.61 | G111: =F112 -> 237278.14 | H111: =G112 -> 265003.42 | I111: =H112 -> 173817.29 | J111: =I112 -> 196072.2 | K111: =J112 -> 232293.09 | L111: =K112 -> 180344.9 | ... P111: =O112 -> 160084.21
...

Sheet Channel Profitability
B2: ATELIER NORTH PTE. LTD. | I2: SGD · synthetic data
B3: Management P&L by channel · six months ended 31 July 2026 | I3: Back to Dashboard
B4: Months in period | C4: 6 | E4: Shared overhead is deliberately NOT allocated in the primary view - see the memo section below.
B5: SGD - six months | C5: Rate | D5: Physical Store | E5: E-commerce | F5: Events / Pop-ups | G5: Consignment | H5: Total Business | I5: % of total net revenue
B6: Gross sales | D6: =Assumptions!$J$99 -> 528000 | E6: =Assumptions!$J$100 -> 570000 | F6: =Assumptions!$J$101 -> 180000 | G6: =Assumptions!$J$102 -> 204000 | H6: =SUM(D6:G6) -> 1482000 | I6: =IFERROR(H6/$H$8,0) -> 1.076628
B7: Discounts and returns | D7: =-D6*Assumptions!$C$23 -> -31680 | E7: =-E6*Assumptions!$C$24 -> -68400 | F7: =-F6*Assumptions!$C$25 -> -5400 | G7: =-G6*Assumptions!$C$26 -> 0 | H7: =SUM(D7:G7) -> -105480 | I7: =IFERROR(H7/$H$8,0) -> -0.076628018
B8: Net revenue | D8: =D6+D7 -> 496320 | E8: =E6+E7 -> 501600 | F8: =F6+F7 -> 174600 | G8: =G6+G7 -> 204000 | H8: =SUM(D8:G8) -> 1376520 | I8: =IFERROR(H8/$H$8,0) -> 1
B9: Cost of goods sold | D9: =-D8*(1-Assumptions!$C$28) -> -208454.4 | E9: =-E8*(1-Assumptions!$C$29) -> -200640 | F9: =-F8*(1-Assumptions!$C$30) -> -62856 | G9: =-G8*(1-Assumptions!$C$31) -> -81600 | H9: =SUM(D9:G9) -> -553550.4 | I9: =IFERROR(H9/$H$8,0) -> -0.40213756
B10: Gross profit | D10: =D8+D9 -> 287865.6 | E10: =E8+E9 -> 300960 | F10: =F8+F9 -> 111744 | G10: =G8+G9 -> 122400 | H10: =SUM(D10:G10) -> 822969.6 | I10: =IFERROR(H10/$H$8,0) -> 0.59786244
B11: Gross margin % | D11: =IFERROR(D10/D8,0) -> 0.58 | E11: =IFERROR(E10/E8,0) -> 0.6 | F11: =IFERROR(F10/F8,0) -> 0.64 | G11: =IFERROR(G10/G8,0) -> 0.6 | H11: =IFERROR(H10/H8,0) -> 0.59786244
B13: VARIABLE CHANNEL COSTS (move directly with channel sales)
B14: Payment and merchant fees | D14: =-D8*Assumptions!$C$34 -> -8933.76 | E14: =-E8*Assumptions!$C$35 -> -14546.4 | F14: =-F8*Assumptions!$C$36 -> -3317.4 | H14: =SUM(D14:G14) -> -26797.56
B15: Fulfilment, shipping and handling | E15: =-E8*Assumptions!$C$39 -> -32604 | G15: =-G8*Assumptions!$C$43 -> -3060 | H15: =SUM(D15:G15) -> -35664
B16: Consignment partner commissions | C16: =Assumptions!$C$42 -> 0.3 | G16: =-G8*Assumptions!$C$42 -> -61200 | H16: =SUM(D16:G16) -> -61200
B17: Variable store labour | C17: =Assumptions!$C$37 -> 0.03 | D17: =-D8*Assumptions!$C$37 -> -14889.6 | H17: =SUM(D17:G17) -> -14889.6
B18: Channel marketing (digital performance media) | C18: =Assumptions!$C$40 -> 0.09 | E18: =-E8*Assumptions!$C$40 -> -45144 | H18: =SUM(D18:G18) -> -45144
B19: Event costs (space, fixtures, transport, crew) | C19: =Assumptions!$C$41 -> 0.18 | F19: =-F8*Assumptions!$C$41 -> -31428 | H19: =SUM(D19:G19) -> -31428
B20: Other direct operating costs | C20: =Assumptions!$C$38 -> 0.008 | D20: =-D8*Assumptions!$C$38 -> -3970.56 | H20: =SUM(D20:G20) -> -3970.56
B21: Total variable channel costs | D21: =SUM(D14:D20) -> -27793.92 | E21: =SUM(E14:E20) -> -92294.4 | F21: =SUM(F14:F20) -> -34745.4 | G21: =SUM(G14:G20) -> -64260 | H21: =SUM(D21:G21) -> -219093.72 | I21: =IFERROR(H21/$H$8,0) -> -0.15916494
B22: CONTRIBUTION PROFIT | D22: =D10+D21 -> 260071.68 | E22: =E10+E21 -> 208665.6 | F22: =F10+F21 -> 76998.6 | G22: =G10+G21 -> 58140 | H22: =SUM(D22:G22) -> 603875.88 | I22: =IFERROR(H22/$H$8,0) -> 0.4386975
B23: Contribution margin % | D23: =IFERROR(D22/D8,0) -> 0.524 | E23: =IFERROR(E22/E8,0) -> 0.416 | F23: =IFERROR(F22/F8,0) -> 0.441 | G23: =IFERROR(G22/G8,0) -> 0.285 | H23: =IFERROR(H22/H8,0) -> 0.4386975
B25: DIRECT FIXED COSTS (attributable to a single channel; avoided if that channel closes)
B26: Store rent | D26: =-Assumptions!$C$46*$C$4 -> -132000 | H26: =SUM(D26:G26) -> -132000
B27: Store base payroll | D27: =-Assumptions!$C$47*$C$4 -> -111000 | H27: =SUM(D27:G27) -> -111000
B28: Store utilities and service charge | D28: =-Assumptions!$C$48*$C$4 -> -15600 | H28: =SUM(D28:G28) -> -15600
B29: Store POS and store software | D29: =-Assumptions!$C$49*$C$4 -> -2700 | H29: =SUM(D29:G29) -> -2700
B30: Store insurance and other occupancy | D30: =-Assumptions!$C$50*$C$4 -> -5400 | H30: =SUM(D30:G30) -> -5400
B31: E-commerce platform, apps and subscriptions | E31: =-Assumptions!$C$54*$C$4 -> -6600 | H31: =SUM(D31:G31) -> -6600
B32: E-commerce and fulfilment payroll | E32: =-Assumptions!$C$55*$C$4 -> -31200 | H32: =SUM(D32:G32) -> -31200
B33: Total direct fixed costs | D33: =SUM(D26:D32) -> -266700 | E33: =SUM(E26:E32) -> -37800 | F33: =SUM(F26:F32) -> 0 | G33: =SUM(G26:G32) -> 0 | H33: =SUM(D33:G33) -> -304500 | I33: =IFERROR(H33/$H$8,0) -> -0.22121001
B34: DIRECT CHANNEL PROFIT / (LOSS) | D34: =D22+D33 -> -6628.32 | E34: =E22+E33 -> 170865.6 | F34: =F22+F33 -> 76998.6 | G34: =G22+G33 -> 58140 | H34: =SUM(D34:G34) -> 299375.88 | I34: =IFERROR(H34/$H$8,0) -> 0.21748749
B35: Direct channel margin % | D35: =IFERROR(D34/D8,0) -> -0.013354932 | E35: =IFERROR(E34/E8,0) -> 0.34064115 | F35: =IFERROR(F34/F8,0) -> 0.441 | G35: =IFERROR(G34/G8,0) -> 0.285 | H35: =IFERROR(H34/H8,0) -> 0.21748749
B37: SHARED OVERHEAD (not attributable to a single channel - shown in total only)
B38: Management and admin payroll | H38: =-Assumptions!$C$59*$C$4 -> -126000
B39: Professional fees | H39: =-Assumptions!$C$60*$C$4 -> -10800
B40: General software | H40: =-Assumptions!$C$61*$C$4 -> -5400
B41: Brand marketing (non-channel) | H41: =-Assumptions!$C$62*$C$4 -> -27000
B42: Corporate admin, insurance and bank charges | H42: =-Assumptions!$C$63*$C$4 -> -9000
B43: Total shared overhead | H43: =SUM(H38:H42) -> -178200 | I43: =IFERROR(H43/$H$8,0) -> -0.12945689
B45: OPERATING PROFIT (after shared overhead) | H45: =H34+H43 -> 121175.88 | I45: =IFERROR(H45/$H$8,0) -> 0.088030599
B46: Operating margin % | H46: =IFERROR(H45/H8,0) -> 0.088030599
B48: MEMO - fully-absorbed view (shared overhead allocated on share of net revenue)
B49: Allocation basis - share of total net revenue | D49: =IFERROR(D8/$H$8,0) -> 0.36056142 | E49: =IFERROR(E8/$H$8,0) -> 0.36439718 | F49: =IFERROR(F8/$H$8,0) -> 0.1268416 | G49: =IFERROR(G8/$H$8,0) -> 0.14819981 | H49: =SUM(D49:G49) -> 1
B50: Allocated shared overhead | D50: =$H$43*D49 -> -64252.044 | E50: =$H$43*E49 -> -64935.577 | F50: =$H$43*F49 -> -22603.173 | G50: =$H$43*G49 -> -26409.206 | H50: =SUM(D50:G50) -> -178200
B51: Fully-absorbed channel profit / (loss) | D51: =D34+D50 -> -70880.364 | E51: =E34+E50 -> 105930.02 | F51: =F34+F50 -> 54395.427 | G51: =G34+G50 -> 31730.794 | H51: =SUM(D51:G51) -> 121175.88
B52: Check: allocated overhead agrees to total shared overhead (must be nil) | H52: =H50-H43 -> 0
B54: MONTHLY AVERAGE (six-month basis - feeds the Store Break-Even tab)
B55: Net revenue per month | D55: =D8/$C$4 -> 82720 | E55: =E8/$C$4 -> 83600 | F55: =F8/$C$4 -> 29100 | G55: =G8/$C$4 -> 34000 | H55: =SUM(D55:G55) -> 229420
B56: Cost of goods sold per month | D56: =D9/$C$4 -> -34742.4 | E56: =E9/$C$4 -> -33440 | F56: =F9/$C$4 -> -10476 | G56: =G9/$C$4 -> -13600 | H56: =SUM(D56:G56) -> -92258.4
B57: Variable channel costs per month | D57: =D21/$C$4 -> -4632.32 | E57: =E21/$C$4 -> -15382.4 | F57: =F21/$C$4 -> -5790.9 | G57: =G21/$C$4 -> -10710 | H57: =SUM(D57:G57) -> -36515.62
B58: Contribution profit per month | D58: =D22/$C$4 -> 43345.28 | E58: =E22/$C$4 -> 34777.6 | F58: =F22/$C$4 -> 12833.1 | G58: =G22/$C$4 -> 9690 | H58: =SUM(D58:G58) -> 100645.98
B59: Direct fixed costs per month | D59: =D33/$C$4 -> -44450 | E59: =E33/$C$4 -> -6300 | F59: =F33/$C$4 -> 0 | G59: =G33/$C$4 -> 0 | H59: =SUM(D59:G59) -> -50750
B60: Direct channel profit / (loss) per month | D60: =D34/$C$4 -> -1104.72 | E60: =E34/$C$4 -> 28477.6 | F60: =F34/$C$4 -> 12833.1 | G60: =G34/$C$4 -> 9690 | H60: =SUM(D60:G60) -> 49895.98
B62: Reading note: contribution margin measures each channel before any fixed cost. Direct channel profit then charges only the fixed costs that would genuinely disappear if that channel closed. Shared overhead is held back because allocating it would make a decision look different without changing a single cash flow.

Sheet Store Break-Even
B2: ATELIER NORTH PTE. LTD. | I2: SGD · synthetic data
B3: Flagship store viability and break-even analysis · monthly basis | I3: Back to Dashboard
F4: STORE VIABILITY AT A GLANCE
B5: CURRENT STORE TRADING - SGD per month, six-month average to 31 July 2026 | F5: CURRENT NET SALES / MONTH | H5: BREAK-EVEN NET SALES / MONTH
B6: Store net sales | D6: ='Channel Profitability'!$D$55 -> 82720 | F6: =$D$34 -> 82720 | H6: =$D$32 -> 84828.244
B7: Cost of goods sold | D7: ='Channel Profitability'!$D$56 -> -34742.4 | F7: Six-month average | H7: Fixed costs / contribution margin
B8: Gross profit | D8: =D6+D7 -> 47977.6
B9: Gross margin % | D9: =IFERROR(D8/D6,0) -> 0.58 | F9: SALES GAP TO BREAK-EVEN | H9: MARGIN OF SAFETY
F10: =$D$35 -> -2108.2443 | H10: =$D$36 -> -0.025486512
B11: Variable operating costs (move with store sales) | F11: ="or "&TEXT($D$37,"0.0%")&" more sales per month" -> or 2.5% more sales per month | H11: Negative = trading below break-even
B12: Payment and merchant fees | D12: =-D6*Assumptions!$C$34 -> -1488.96
B13: Variable / casual store labour | D13: =-D6*Assumptions!$C$37 -> -2481.6 | F13: CONTRIBUTION MARGIN | H13: STORE PROFIT / (LOSS) PER MONTH
B14: Other direct operating costs | D14: =-D6*Assumptions!$C$38 -> -661.76 | F14: =$D$18 -> 0.524 | H14: =$D$28 -> -1104.72
B15: Total variable operating costs | D15: =SUM(D12:D14) -> -4632.32 | F15: Per S$1 of store net sales | H15: After directly attributable fixed costs
B16: Variable costs as % of net sales | D16: =IFERROR(-D15/D6,0) -> 0.056
B17: CONTRIBUTION PROFIT | D17: =D8+D15 -> 43345.28
B18: Contribution margin % | D18: =IFERROR(D17/D6,0) -> 0.524 | E18: Every S$1 of extra store sales contributes this much toward fixed costs.
B20: Fixed store costs (do not move with sales; avoided only on closure)
B21: Rent | D21: =-Assumptions!$C$46 -> -22000
B22: Base payroll | D22: =-Assumptions!$C$47 -> -18500
B23: Utilities and service charge | D23: =-Assumptions!$C$48 -> -2600
B24: POS and store software | D24: =-Assumptions!$C$49 -> -450
B25: Insurance and other occupancy | D25: =-Assumptions!$C$50 -> -900
B26: Total fixed store costs | D26: =SUM(D21:D25) -> -44450
B28: STORE PROFIT / (LOSS) - per month | D28: =D17+D26 -> -1104.72
B29: Store profit / (loss) - annualised | D29: =D28*12 -> -13256.64
B31: BREAK-EVEN ANALYSIS Break-even sales = fixed store costs / contribution margin %
B32: Break-even net sales - per month | D32: =IFERROR(-D26/D18,0) -> 84828.244
B33: Break-even net sales - per week | D33: =D32/Assumptions!$C$10 -> 19575.749
B34: Current net sales - per month | D34: =D6 -> 82720
B35: Sales above / (below) break-even | D35: =D34-D32 -> -2108.2443
B36: Margin of safety % | D36: =IFERROR(D35/D34,0) -> -0.025486512 | E36: Negative = trading below break-even.
B37: Sales uplift required to break even | D37: =IFERROR(D32/D34-1,0) -> 0.025486512
B38: Sales uplift required to break even - S$ per month | D38: =D32-D34 -> 2108.2443
B39: Alternatively: gross-margin uplift required to break even | D39: =IFERROR(-D26/D6-D18,0) -> 0.013354932 | E39: Percentage points of margin, holding sales flat.
B40: Alternatively: rent reduction required to break even | D40: =IF(D28<0,-D28,0) -> 1104.72 | E40: S$ per month, holding sales and margin flat.
B41: Rent reduction required - % of current rent | D41: =IFERROR(D40/-D21,0) -> 0.050214545
B43: MEMO - cross-check against the 13-week forecast run-rate
B44: Forecast store net sales - 13 weeks | D44: ='13W Cash Flow'!$Q$73 -> 249592.56
B45: Equivalent monthly run-rate | D45: =D44/13*Assumptions!$C$10 -> 83197.52
B46: Forecast run-rate vs break-even | D46: =IFERROR(D45/D32-1,0) -> -0.019223836 | E46: Forward-looking cross-check on the historic position above.
B48: SENSITIVITY 1 - monthly store profit / (loss) by sales change and gross margin
B49: Gross margin step (+/- percentage points) | C49: 0.03
B50: Gross margin scenario | C50: Gross margin % | D50: -0.2 | E50: -0.1 | F50: 0 | G50: 0.1 | H50: 0.2
B51: Downside | C51: =$D$9-$C$49 -> 0.55 | D51: =$D$6*(1+D$50)*($C51-$D$16)+$D$26 -> -11759.056 | E51: =$D$6*(1+E$50)*($C51-$D$16)+$D$26 -> -7672.688 | F51: =$D$6*(1+F$50)*($C51-$D$16)+$D$26 -> -3586.32 | G51: =$D$6*(1+G$50)*($C51-$D$16)+$D$26 -> 500.048 | H51: =$D$6*(1+H$50)*($C51-$D$16)+$D$26 -> 4586.416
B52: Base | C52: =$D$9 -> 0.58 | D52: =$D$6*(1+D$50)*($C52-$D$16)+$D$26 -> -9773.776 | E52: =$D$6*(1+E$50)*($C52-$D$16)+$D$26 -> -5439.248 | F52: =$D$6*(1+F$50)*($C52-$D$16)+$D$26 -> -1104.72 | G52: =$D$6*(1+G$50)*($C52-$D$16)+$D$26 -> 3229.808 | H52: =$D$6*(1+H$50)*($C52-$D$16)+$D$26 -> 7564.336
B53: Upside | C53: =$D$9+$C$49 -> 0.61 | D53: =$D$6*(1+D$50)*($C53-$D$16)+$D$26 -> -7788.496 | E53: =$D$6*(1+E$50)*($C53-$D$16)+$D$26 -> -3205.808 | F53: =$D$6*(1+F$50)*($C53-$D$16)+$D$26 -> 1376.88 | G53: =$D$6*(1+G$50)*($C53-$D$16)+$D$26 -> 5959.568 | H53: =$D$6*(1+H$50)*($C53-$D$16)+$D$26 -> 10542.256
B54: Positive = store covers its own fixed costs at that combination of sales and margin.
B56: SENSITIVITY 2 - break-even monthly sales by gross margin and rent
B57: Gross margin scenario | C57: Gross margin % | D57: -0.2 | E57: -0.15 | F57: -0.1 | G57: -0.05 | H57: 0
B58: Downside | C58: =$D$9-$C$49 -> 0.55 | D58: =IFERROR(-($D$26+$D$21*D$57)/($C58-$D$16),0) -> 81072.874 | E58: =IFERROR(-($D$26+$D$21*E$57)/($C58-$D$16),0) -> 83299.595 | F58: =IFERROR(-($D$26+$D$21*F$57)/($C58-$D$16),0) -> 85526.316 | G58: =IFERROR(-($D$26+$D$21*G$57)/($C58-$D$16),0) -> 87753.036 | H58: =IFERROR(-($D$26+$D$21*H$57)/($C58-$D$16),0) -> 89979.757
B59: Base | C59: =$D$9 -> 0.58 | D59: =IFERROR(-($D$26+$D$21*D$57)/($C59-$D$16),0) -> 76431.298 | E59: =IFERROR(-($D$26+$D$21*E$57)/($C59-$D$16),0) -> 78530.534 | F59: =IFERROR(-($D$26+$D$21*F$57)/($C59-$D$16),0) -> 80629.771 | G59: =IFERROR(-($D$26+$D$21*G$57)/($C59-$D$16),0) -> 82729.008 | H59: =IFERROR(-($D$26+$D$21*H$57)/($C59-$D$16),0) -> 84828.244
B60: Upside | C60: =$D$9+$C$49 -> 0.61 | D60: =IFERROR(-($D$26+$D$21*D$57)/($C60-$D$16),0) -> 72292.419 | E60: =IFERROR(-($D$26+$D$21*E$57)/($C60-$D$16),0) -> 74277.978 | F60: =IFERROR(-($D$26+$D$21*F$57)/($C60-$D$16),0) -> 76263.538 | G60: =IFERROR(-($D$26+$D$21*G$57)/($C60-$D$16),0) -> 78249.097 | H60: =IFERROR(-($D$26+$D$21*H$57)/($C60-$D$16),0) -> 80234.657
B61: Compare each cell with current monthly net sales. Rent columns show the break-even sales level if the lease were renegotiated by that percentage.
B63: DRIVER SENSITIVITY - what actually drives store viability
B64: Sensitivity step applied to each driver | C64: 0.1
B65: Driver | D65: Adverse move | E65: Base | F65: Favourable move | G65: Swing in monthly profit
B66: Store net sales | D66: =$D$6*(1-$C$64)*($D$9-$D$16)+$D$26 -> -5439.248 | E66: =$D$28 -> -1104.72 | F66: =$D$6*(1+$C$64)*($D$9-$D$16)+$D$26 -> 3229.808 | G66: =F66-D66 -> 8669.056
B67: Gross margin % | D67: =$D$6*($D$9*(1-$C$64)-$D$16)+$D$26 -> -5902.48 | E67: =$D$28 -> -1104.72 | F67: =$D$6*($D$9*(1+$C$64)-$D$16)+$D$26 -> 3693.04 | G67: =F67-D67 -> 9595.52
B68: Rent | D68: =$D$28+$D$21*$C$64 -> -3304.72 | E68: =$D$28 -> -1104.72 | F68: =$D$28-$D$21*$C$64 -> 1095.28 | G68: =F68-D68 -> 4400
B69: Base payroll | D69: =$D$28+$D$22*$C$64 -> -2954.72 | E69: =$D$28 -> -1104.72 | F69: =$D$28-$D$22*$C$64 -> 745.28 | G69: =F69-D69 -> 3700
B70: Variable cost % | D70: =$D$6*($D$9-$D$16*(1+$C$64))+$D$26 -> -1567.952 | E70: =$D$28 -> -1104.72 | F70: =$D$6*($D$9-$D$16*(1-$C$64))+$D$26 -> -641.488 | G70: =F70-D70 -> 926.464
B72: The widest swing identifies the dominant lever. Sales and gross margin move store profit far more than a proportionate change in rent or base payroll, so a trading recovery - not a cost cut alone - is what decides whether the store stays open.

Sheet Assumptions
B2: ATELIER NORTH PTE. LTD. | P2: SGD · synthetic data
B3: Central assumptions · every hardcoded input in the model lives on this sheet | P3: Back to Dashboard
B5: Legend | C5: input | D5: edit these | E5: Black = calculated on this sheet. Green = link to another sheet. Scenario levers are held on the Scenarios tab.
B7: 1. MODEL CONTROL
B8: Week 1 commencing (Monday) | C8: 46237 | D8: date | E8: Roll the forecast by changing this one date.
B9: Historical period ended | C9: 46234 | D9: date | E9: Six months of channel actuals to this date.
B10: Weeks per month conversion factor | C10: 4.3333333 | D10: wks/mth | E10: Used to convert weekly run-rates to monthly.
B12: 2. CASH
B13: Opening cash balance at Week 1 | C13: 205000 | D13: SGD | E13: Bank balance per the Xero bank reconciliation.
B14: Minimum operating cash threshold | C14: 120000 | D14: SGD | E14: ="Board-set buffer: c."&TEXT($C$14/$C$95,"0.0")&" months of total fixed-cost cover." -> Board-set buffer: c.1.5 months of total fixed-cost cover.
B16: 3. REVENUE - FORECAST WEEKLY RUN-RATES (gross of discounts)
B17: Physical store - gross sales per week | C17: 20300 | D17: SGD/wk
B18: E-commerce - gross sales per week | C18: 24500 | D18: SGD/wk | E18: Ahead of the 6-month average: e-commerce is growing.
B19: Events / pop-ups - gross sales per event week | C19: 24000 | D19: SGD/wk | E19: Applied only in weeks with a scheduled event.
B20: Consignment - gross sales per week (at partner retail) | C20: 7850 | D20: SGD/wk
B22: 4. DISCOUNTS, RETURNS AND GROSS MARGIN
B23: Store - discounts and returns | C23: 0.06 | D23: % of gross
B24: E-commerce - discounts and returns | C24: 0.12 | D24: % of gross | E24: Higher: size-driven online returns.
B25: Events - discounts and returns | C25: 0.03 | D25: % of gross
B26: Consignment - discounts and returns | C26: 0 | D26: % of gross | E26: Partner sells at full retail.
B28: Store - gross margin | C28: 0.58 | D28: % of net
B29: E-commerce - gross margin | C29: 0.6 | D29: % of net
B30: Events - gross margin | C30: 0.64 | D30: % of net | E30: Curated, full-price sell-through.
B31: Consignment - product gross margin (before commission) | C31: 0.6 | D31: % of net
B33: 5. VARIABLE CHANNEL COSTS (move with sales)
B34: Store - merchant / payment fees | C34: 0.018 | D34: % of net
B35: E-commerce - payment gateway and platform transaction fees | C35: 0.029 | D35: % of net
B36: Events - merchant / payment fees | C36: 0.019 | D36: % of net
B37: Store - variable / casual labour | C37: 0.03 | D37: % of net | E37: Weekend and peak-hour cover above base roster.
B38: Store - other direct costs (packaging, consumables) | C38: 0.008 | D38: % of net
B39: E-commerce - fulfilment and shipping, net of customer recovery | C39: 0.065 | D39: % of net
B40: E-commerce - digital marketing | C40: 0.09 | D40: % of net | E40: Performance media; scales with revenue.
B41: Events - event costs (space, fixtures, transport, crew) | C41: 0.18 | D41: % of net
B42: Consignment - partner commission | C42: 0.3 | D42: % of net | E42: Deducted by the partner before remittance.
B43: Consignment - handling and logistics | C43: 0.015 | D43: % of net
B45: 6. STORE DIRECT FIXED COSTS (monthly)
B46: Store rent | C46: 22000 | D46: SGD/mth | E46: Flagship lease; next break option at the end of Q1 2027.
B47: Store base payroll (manager + 2 full-time) | C47: 18500 | D47: SGD/mth
B48: Store utilities and service charge | C48: 2600 | D48: SGD/mth
B49: Store POS and store software | C49: 450 | D49: SGD/mth
B50: Store insurance and other occupancy | C50: 900 | D50: SGD/mth
B51: Total store direct fixed costs | C51: =SUM(C46:C50) -> 44450
B53: 7. E-COMMERCE DIRECT FIXED COSTS (monthly)
B54: E-commerce platform, apps and subscriptions | C54: 1100 | D54: SGD/mth
B55: E-commerce and fulfilment payroll | C55: 5200 | D55: SGD/mth
B56: Total e-commerce direct fixed costs | C56: =SUM(C54:C55) -> 6300
B58: 8. SHARED OVERHEAD (monthly - not allocated to channels)
B59: Management and admin payroll | C59: 21000 | D59: SGD/mth
B60: Professional fees (accounting, tax, advisory) | C60: 1800 | D60: SGD/mth
B61: General software (accounting, payroll, productivity) | C61: 900 | D61: SGD/mth
B62: Brand marketing (non-channel) | C62: 4500 | D62: SGD/mth
B63: Corporate admin, insurance and bank charges | C63: 1500 | D63: SGD/mth
B64: Total shared overhead | C64: =SUM(C59:C63) -> 29700
B66: 9. WORKING CAPITAL - CASH CONVERSION
B67: Store - % of sales collected in the week of sale | C67: 0.92 | D67: % | E67: Card settlement T+2; balance lands the following week.
B68: E-commerce - % of sales collected in the week of sale | C68: 0.85 | D68: % | E68: Gateway payout cycle.
B69: Events - % of sales collected in the week of sale | C69: 1 | D69: % | E69: Cash and terminal takings banked at the event.
B70: Consignment - collection lag | C70: 4 | D70: weeks | E70: Partners report and remit monthly in arrears.
B72: Store - receipts due in Week 1 from prior-week sales | C72: 1520 | D72: SGD
B73: E-commerce - receipts due in Week 1 from prior-week sales | C73: 3240 | D73: SGD
B74: Consignment receivable at Week 1 (net of commission) | C74: =Assumptions!$C$20*(1-Assumptions!$C$26)*Assumptions!$C$70*(1-Assumptions!$C$42) -> 21980 | D74: SGD | E74: Calculated: four weeks of consignment sales, released evenly over Weeks 1-4.
B76: Inventory replenishment funded weekly | C76: 0.58 | D76: % of weekly COGS | E76: Balance of stock intake comes from the scheduled AW26 buy below.
B78: 10. PAYMENT TIMING (day of month)
B79: Rent and monthly sundry costs paid on day | C79: 1 | D79: day
B80: Term loan instalment paid on day | C80: 5 | D80: day
B81: Software subscriptions and brand marketing paid on day | C81: 10 | D81: day
B82: Utilities and service charge paid on day | C82: 15 | D82: day
B83: Professional fees paid on day | C83: 20 | D83: day
B84: Payroll paid on the last day of the month | C84: month end | E84: Driven by EOMONTH() on the 13W Cash Flow tab - no hardcoded week numbers.
B86: 11. OTHER CASH ITEMS
B87: Term loan instalment (renovation facility) | C87: 4200 | D87: SGD/mth
B88: Quarterly GST settlement | C88: 26500 | D88: SGD | E88: Quarter ended 31 Aug 2026, payable by 30 Sep 2026.
B89: GST settlement falls in forecast week | C89: 9 | D89: week no.
B91: 12. DERIVED CASH GROUPINGS (calculated - keeps P&L and cash tied together)
B92: Corporate and admin payroll (cash row) | C92: =Assumptions!$C$59+Assumptions!$C$55 -> 26200 | D92: SGD/mth | E92: Management/admin payroll plus e-commerce payroll.
B93: Software and subscriptions (cash row) | C93: =Assumptions!$C$49+Assumptions!$C$54+Assumptions!$C$61 -> 2450 | D93: SGD/mth | E93: Store POS + e-commerce platform + general software.
B94: Other operating expenses - monthly (cash row) | C94: =Assumptions!$C$50+Assumptions!$C$63 -> 2400 | D94: SGD/mth | E94: Store insurance/occupancy + corporate admin.
B95: Total fixed cost base per month (all sheets) | C95: =Assumptions!$C$51+Assumptions!$C$56+Assumptions!$C$64 -> 80450 | D95: SGD/mth
B97: 13. HISTORICAL GROSS SALES BY CHANNEL - six months to 31 July 2026 (SGD)
B98: Channel | D98: Feb-26 | E98: Mar-26 | F98: Apr-26 | G98: May-26 | H98: Jun-26 | I98: Jul-26 | J98: 6-mth total | K98: Monthly avg
B99: Physical store | D99: 96500 | E99: 84200 | F99: 80900 | G99: 87600 | H99: 92400 | I99: 86400 | J99: =SUM(D99:I99) -> 528000 | K99: =J99/6 -> 88000
B100: E-commerce | D100: 84000 | E100: 88500 | F100: 91000 | G100: 96000 | H100: 104500 | I100: 106000 | J100: =SUM(D100:I100) -> 570000 | K100: =J100/6 -> 95000
B101: Events / pop-ups | D101: 41000 | E101: 0 | F101: 26500 | G101: 0 | H101: 58000 | I101: 54500 | J101: =SUM(D101:I101) -> 180000 | K101: =J101/6 -> 30000
B102: Consignment | D102: 36800 | E102: 31200 | F102: 29900 | G102: 33400 | H102: 36100 | I102: 36600 | J102: =SUM(D102:I102) -> 204000 | K102: =J102/6 -> 34000
B103: Total gross sales | D103: =SUM(D99:D102) -> 258300 | E103: =SUM(E99:E102) -> 203900 | F103: =SUM(F99:F102) -> 228300 | G103: =SUM(G99:G102) -> 217000 | H103: =SUM(H99:H102) -> 291000 | I103: =SUM(I99:I102) -> 283500 | J103: =SUM(J99:J102) -> 1482000 | K103: =SUM(K99:K102) -> 247000
B104: Months with no scheduled pop-up show nil event revenue - the channel is genuinely lumpy.
B106: 14. FORECAST WEEKLY DRIVERS - seasonality indices and event calendar (Weeks 1-13)
B107: Driver | C107: Avg / check | D107: W1 | E107: W2 | F107: W3 | G107: W4 | H107: W5 | I107: W6 | J107: W7 | K107: W8 | L107: W9 | M107: W10 | N107: W11 | O107: W12 | P107: W13
B108: Store demand index | C108: =AVERAGE(D108:P108) -> 1.0061538 | D108: 0.95 | E108: 1.08 | F108: 0.92 | G108: 0.9 | H108: 0.93 | I108: 0.97 | J108: 1 | K108: 1.02 | L108: 0.98 | M108: 1.03 | N108: 1.06 | O108: 1.1 | P108: 1.14
B109: E-commerce demand index | C109: =AVERAGE(D109:P109) -> 1.0492308 | D109: 0.97 | E109: 1.05 | F109: 0.96 | G109: 0.95 | H109: 0.99 | I109: 1.02 | J109: 1.04 | K109: 1.06 | L109: 1.05 | M109: 1.08 | N109: 1.12 | O109: 1.15 | P109: 1.2
B110: Event intensity (0 = no event; 1.0 = standard pop-up) | C110: =AVERAGE(D110:P110) -> 0.33076923 | D110: 0 | E110: 1 | F110: 0 | G110: 0 | H110: 0 | I110: 0 | J110: 0.8 | K110: 0 | L110: 0 | M110: 0 | N110: 1.4 | O110: 0 | P110: 1.1
B111: Consignment demand index | C111: =AVERAGE(D111:P111) -> 1.0176923 | D111: 0.96 | E111: 1 | F111: 0.95 | G111: 0.94 | H111: 0.97 | I111: 1 | J111: 1.02 | K111: 1.03 | L111: 1.01 | M111: 1.05 | N111: 1.08 | O111: 1.1 | P111: 1.12
B112: National Day trading in W2; AW26 launch builds through W10-W13; pop-ups scheduled in W2, W7, W11 and W13.
B114: 15. INVENTORY - SCHEDULED AW26 BUY PAYMENTS (in addition to weekly replenishment)
B115: Purchase commitment | C115: Amount (SGD) | D115: Due week
B116: AW26 core outerwear - 30% deposit on order | C116: 54000 | D116: 2
B117: AW26 knitwear and jersey - shipment balance | C117: 46000 | D117: 5
B118: AW26 main drop - shipment balance | C118: 82000 | D118: 8
B119: Holiday capsule and accessories - deposit | C119: 53000 | D119: 11
B120: Total scheduled AW26 buy payments | C120: =SUM(C116:C119) -> 235000
...

Sheet Controls
B2: ATELIER NORTH PTE. LTD. | H2: SGD · synthetic data
B3: Model controls · every check must pass before the pack is issued | H3: Back to Dashboard
B5: MODEL STATUS | D5: =IF(COUNTIF(H8:H42,"FAIL")=0,"PASS","REVIEW REQUIRED") -> PASS | E5: ="("&COUNTIF(H8:H42,"PASS")&" of "&COUNTA($C$8:$C$42)&" controls passing)" -> (35 of 35 controls passing)
B6: Tolerances: S$0.50 on value reconciliations (rounding only), 0.001 on count and flag checks.
B7: Category | C7: Control · what it proves | D7: Expected | E7: Actual | F7: Variance | G7: Tolerance | H7: Result
B8: CASH INTEGRITY | C8: 1. Cash roll-forward: opening cash + receipts - outflows = closing cash, every week | D8: 0 | E8: =SUMPRODUCT(ABS('13W Cash Flow'!D10:P10+'13W Cash Flow'!D18:P18-'13W Cash Flow'!D36:P36-'13W Cash Flow'!D40:P40)) -> 1.4551915e-10 | F8: =E8-D8 -> 1.4551915e-10 | G8: 0.5 | H8: =IF(ABS(F8)<=G8,"PASS","FAIL") -> PASS
C9: 2. Cash continuity: each week's opening cash equals the prior week's closing cash | D9: 0 | E9: =SUMPRODUCT(ABS('13W Cash Flow'!E10:P10-'13W Cash Flow'!D40:O40)) -> 0 | F9: =E9-D9 -> 0 | G9: 0.5 | H9: =IF(ABS(F9)<=G9,"PASS","FAIL") -> PASS
C10: 3. Week 1 opening cash agrees to the opening balance on Assumptions | D10: 0 | E10: ='13W Cash Flow'!$D$10-Assumptions!$C$13 -> 0 | F10: =E10-D10 -> 0 | G10: 0.5 | H10: =IF(ABS(F10)<=G10,"PASS","FAIL") -> PASS
C11: 4. Total cash receipts equals the sum of the individual receipt lines | D11: 0 | E11: ='13W Cash Flow'!$Q$18-SUM('13W Cash Flow'!$Q$13:$Q$17) -> 0 | F11: =E11-D11 -> 0 | G11: 0.5 | H11: =IF(ABS(F11)<=G11,"PASS","FAIL") -> PASS
C12: 5. Total cash outflows equals the sum of the individual outflow lines | D12: 0 | E12: ='13W Cash Flow'!$Q$36-SUM('13W Cash Flow'!$Q$21:$Q$35) -> 0 | F12: =E12-D12 -> 0 | G12: 0.5 | H12: =IF(ABS(F12)<=G12,"PASS","FAIL") -> PASS
C13: 6. Minimum cash threshold applied consistently across all 13 weeks | D13: 0 | E13: =SUMPRODUCT(ABS('13W Cash Flow'!D41:P41-Assumptions!$C$14)) -> 0 | F13: =E13-D13 -> 0 | G13: 0.5 | H13: =IF(ABS(F13)<=G13,"PASS","FAIL") -> PASS
C14: 7. Forecast net sales equals the sum of the four channel sales lines | D14: 0 | E14: ='13W Cash Flow'!$Q$77-SUM('13W Cash Flow'!$Q$73:$Q$76) -> 0 | F14: =E14-D14 -> 0 | G14: 0.5 | H14: =IF(ABS(F14)<=G14,"PASS","FAIL") -> PASS
C15: 8. Every scheduled AW26 purchase payment falls inside the 13-week window | D15: 0 | E15: ='13W Cash Flow'!$Q$88-Assumptions!$C$120 -> 0 | F15: =E15-D15 -> 0 | G15: 0.5 | H15: =IF(ABS(F15)<=G15,"PASS","FAIL") -> PASS
C16: 9. Payment completeness: every configured payment date is captured exactly once (see the coverage test on the 13W Cash Flow tab) | D16: 0 | E16: =SUMPRODUCT(ABS('13W Cash Flow'!$D$101:$I$101)) -> 0 | F16: =E16-D16 -> 0 | G16: 0.001 | H16: =IF(ABS(F16)<=G16,"PASS","FAIL") -> PASS
B17: CHANNEL P&L | C17: 10. Channel P&L: total net revenue equals the sum of the four channels | D17: 0 | E17: ='Channel Profitability'!$H$8-SUM('Channel Profitability'!$D$8:$G$8) -> 0 | F17: =E17-D17 -> 0 | G17: 0.5 | H17: =IF(ABS(F17)<=G17,"PASS","FAIL") -> PASS
C18: 11. Channel P&L: total cost of goods sold equals the sum of the four channels | D18: 0 | E18: ='Channel Profitability'!$H$9-SUM('Channel Profitability'!$D$9:$G$9) -> 0 | F18: =E18-D18 -> 0 | G18: 0.5 | H18: =IF(ABS(F18)<=G18,"PASS","FAIL") -> PASS
C19: 12. Channel P&L gross sales agree to the historical sales table on Assumptions | D19: 0 | E19: ='Channel Profitability'!$H$6-Assumptions!$J$103 -> 0 | F19: =E19-D19 -> 0 | G19: 0.5 | H19: =IF(ABS(F19)<=G19,"PASS","FAIL") -> PASS
C20: 13. Operating profit equals contribution less direct fixed costs less shared overhead | D20: 0 | E20: ='Channel Profitability'!$H$45-('Channel Profitability'!$H$22+'Channel Profitability'!$H$33+'Channel Profitability'!$H$43) -> 0 | F20: =E20-D20 -> 0 | G20: 0.5 | H20: =IF(ABS(F20)<=G20,"PASS","FAIL") -> PASS
C21: 14. Allocated shared overhead in the memo view sums back to total shared overhead | D21: 0 | E21: ='Channel Profitability'!$H$50-'Channel Profitability'!$H$43 -> 0 | F21: =E21-D21 -> 0 | G21: 0.5 | H21: =IF(ABS(F21)<=G21,"PASS","FAIL") -> PASS
C22: 15. Fully-absorbed channel profits sum back to total operating profit | D22: 0 | E22: =SUM('Channel Profitability'!$D$51:$G$51)-'Channel Profitability'!$H$45 -> 0 | F22: =E22-D22 -> 0 | G22: 0.5 | H22: =IF(ABS(F22)<=G22,"PASS","FAIL") -> PASS
B23: BREAK-EVEN | C23: 16. Store Break-Even contribution agrees to the Channel Profitability monthly average | D23: 0 | E23: ='Store Break-Even'!$D$17-'Channel Profitability'!$D$58 -> 0 | F23: =E23-D23 -> 0 | G23: 0.5 | H23: =IF(ABS(F23)<=G23,"PASS","FAIL") -> PASS
C24: 17. Break-even test: sales at the break-even level produce a nil store result | D24: 0 | E24: ='Store Break-Even'!$D$32*'Store Break-Even'!$D$18+'Store Break-Even'!$D$26 -> 0 | F24: =E24-D24 -> 0 | G24: 0.5 | H24: =IF(ABS(F24)<=G24,"PASS","FAIL") -> PASS
C25: 18. Store contribution margin is positive (break-even is mathematically meaningful) | D25: 1 | E25: =IF('Store Break-Even'!$D$18>0,1,0) -> 1 | F25: =E25-D25 -> 0 | G25: 0.001 | H25: =IF(ABS(F25)<=G25,"PASS","FAIL") -> PASS
B26: SCENARIO ENGINE | C26: 19. Scenario engine reproduces the base case: Scenario 1 receipts equal the 13W forecast | D26: 0 | E26: =Scenarios!$Q$98-'13W Cash Flow'!$Q$18 -> 0 | F26: =E26-D26 -> 0 | G26: 0.5 | H26: =IF(ABS(F26)<=G26,"PASS","FAIL") -> PASS
C27: 20. Scenario engine reproduces the base case: Scenario 1 outflows equal the 13W forecast | D27: 0 | E27: =Scenarios!$Q$109-'13W Cash Flow'!$Q$36 -> 0 | F27: =E27-D27 -> 0 | G27: 0.5 | H27: =IF(ABS(F27)<=G27,"PASS","FAIL") -> PASS
C28: 21. Scenario engine reproduces the base case: Scenario 1 Week 13 closing cash equals the 13W forecast | D28: 0 | E28: =Scenarios!$P$112-'13W Cash Flow'!$P$40 -> 0 | F28: =E28-D28 -> 0 | G28: 0.5 | H28: =IF(ABS(F28)<=G28,"PASS","FAIL") -> PASS
C29: 22. Scenario levers are complete - every lever is populated for all three scenarios | D29: 45 | E29: =COUNT(Scenarios!$D$7:$F$21) -> 45 | F29: =E29-D29 -> 0 | G29: 0.001 | H29: =IF(ABS(F29)<=G29,"PASS","FAIL") -> PASS
B30: DASHBOARD LINKS | C30: 23. Dashboard KPI links: opening cash card agrees to the 13W Cash Flow output | D30: 0 | E30: =Dashboard!$B$7-'13W Cash Flow'!$D$45 -> 0 | F30: =E30-D30 -> 0 | G30: 0.5 | H30: =IF(ABS(F30)<=G30,"PASS","FAIL") -> PASS
C31: 24. Dashboard KPI links: Week 13 closing cash card agrees to the 13W Cash Flow output | D31: 0 | E31: =Dashboard!$F$7-'13W Cash Flow'!$D$46 -> 0 | F31: =E31-D31 -> 0 | G31: 0.5 | H31: =IF(ABS(F31)<=G31,"PASS","FAIL") -> PASS
C32: 25. Dashboard KPI links: the store break-even gap card agrees to the Store Break-Even tab | D32: 0 | E32: =Dashboard!$N$12-'Store Break-Even'!$D$35 -> 0 | F32: =E32-D32 -> 0 | G32: 0.5 | H32: =IF(ABS(F32)<=G32,"PASS","FAIL") -> PASS
B33: ERROR SCAN | C33: 26. No formula errors on the 13W Cash Flow tab | D33: 0 | E33: =SUMPRODUCT(--ISERROR('13W Cash Flow'!$B$5:$R$102)) -> 0 | F33: =E33-D33 -> 0 | G33: 0.001 | H33: =IF(ABS(F33)<=G33,"PASS","FAIL") -> PASS
C34: 27. No formula errors on the Channel Profitability tab | D34: 0 | E34: =SUMPRODUCT(--ISERROR('Channel Profitability'!$B$5:$I$60)) -> 0 | F34: =E34-D34 -> 0 | G34: 0.001 | H34: =IF(ABS(F34)<=G34,"PASS","FAIL") -> PASS
C35: 28. No formula errors on the Store Break-Even tab | D35: 0 | E35: =SUMPRODUCT(--ISERROR('Store Break-Even'!$B$5:$I$70)) -> 0 | F35: =E35-D35 -> 0 | G35: 0.001 | H35: =IF(ABS(F35)<=G35,"PASS","FAIL") -> PASS
C36: 29. No formula errors on the Scenarios tab | D36: 0 | E36: =SUMPRODUCT(--ISERROR(Scenarios!$B$4:$Q$187)) -> 0 | F36: =E36-D36 -> 0 | G36: 0.001 | H36: =IF(ABS(F36)<=G36,"PASS","FAIL") -> PASS
C37: 30. No formula errors on the Dashboard, Management Insights, dashboard chart data or Assumptions | D37: 0 | E37: =SUMPRODUCT(--ISERROR(Dashboard!$B$5:$P$31))+SUMPRODUCT(--ISERROR('Management Insights'!$B$5:$D$27))+SUMPRODUCT(--ISERROR(Dashboard!$B$101:$D$130))+SUMPRODUCT(--ISERROR(Assumptions!$B$7:$P$125)) -> 0 | F37: =E37-D37 -> 0 | G37: 0.001 | H37: =IF(ABS(F37)<=G37,"PASS","FAIL") -> PASS
B38: SCENARIO & COMPLETENESS | C38: 31. Scenario cash roll-forward: opening + receipts - outflows = closing, every week, all three scenarios | D38: 0 | E38: =SUMPRODUCT(ABS(Scenarios!D111:P111+Scenarios!D98:P98-Scenarios!D109:P109-Scenarios!D112:P112))+SUMPRODUCT(ABS(Scenarios!D144:P144+Scenarios!D131:P131-Scenarios!D142:P142-Scenarios!D145:P145))+SUMPRODUCT(ABS(Scenarios!D177:P177+Scenarios!D164:P164-Scenarios!D175:P175-Scenarios!D178:P178)) -> 4.802132e-10 | F38: =E38-D38 -> 4.802132e-10 | G38: 0.5 | H38: =IF(ABS(F38)<=G38,"PASS","FAIL") -> PASS
C39: 32. Scenario cash continuity: each week opens on the prior week's close, all three scenarios | D39: 0 | E39: =SUMPRODUCT(ABS(Scenarios!E111:P111-Scenarios!D112:O112))+SUMPRODUCT(ABS(Scenarios!E144:P144-Scenarios!D145:O145))+SUMPRODUCT(ABS(Scenarios!E177:P177-Scenarios!D178:O178)) -> 0 | F39: =E39-D39 -> 0 | G39: 0.5 | H39: =IF(ABS(F39)<=G39,"PASS","FAIL") -> PASS
C40: 33. Store payroll survives closure: payroll paid is nil only if the store never traded, in every scenario | D40: 0 | E40: =IF(AND(SUM(Scenarios!$D$100:$P$100)-Assumptions!$C$92*SUM('13W Cash Flow'!$D$70:$P$70)<=0,SUM(Scenarios!$D$86:$P$86)>0),1,0)+IF(AND(SUM(Scenarios!$D$133:$P$133)-Assumptions!$C$92*SUM('13W Cash Flow'!$D$70:$P$70)<=0,SUM(Scenarios!$D$119:$P$119)>0),1,0)+IF(AND(SUM(Scenarios!$D$166:$P$166)-Assumptions!$C$92*SUM('13W Cash Flow'!$D$70:$P$70)<=0,SUM(Scenarios!$D$152:$P$152)>0),1,0) -> 0 | F40: =E40-D40 -> 0 | G40: 0.001 | H40: =IF(ABS(F40)<=G40,"PASS","FAIL") -> PASS
C41: 34. Receipts completeness: receipts tie to net sales less partner commission, adjusted for the debtor movement | D41: 0 | E41: ='13W Cash Flow'!$Q$77-'13W Cash Flow'!$Q$76*Assumptions!$C$42+(Assumptions!$C$72+Assumptions!$C$73+Assumptions!$C$74)-('13W Cash Flow'!$P$73*(1-Assumptions!$C$67)+'13W Cash Flow'!$P$74*(1-Assumptions!$C$68)+SUMPRODUCT(--('13W Cash Flow'!$D$6:$P$6>13-Assumptions!$C$70),'13W Cash Flow'!$D$76:$P$76)*(1-Assumptions!$C$42))-'13W Cash Flow'!$Q$18 -> 0 | F41: =E41-D41 -> 0 | G41: 0.5 | H41: =IF(ABS(F41)<=G41,"PASS","FAIL") -> PASS
C42: 35. Dashboard links: the remaining five KPI cards and the three scenario cash cards agree to source | D42: 0 | E42: =ABS(Dashboard!$J$7-'13W Cash Flow'!$D$51)+ABS(Dashboard!$B$12-'13W Cash Flow'!$Q$77)+ABS(Dashboard!$F$12-'Channel Profitability'!$H$11)+ABS(Dashboard!$J$12-'Store Break-Even'!$D$28)+ABS(Dashboard!$C$128-Scenarios!$D$63)+ABS(Dashboard!$C$129-Scenarios!$E$63)+ABS(Dashboard!$C$130-Scenarios!$F$63)+IF(AND(ISNUMBER(Dashboard!$N$7),ISNUMBER('13W Cash Flow'!$D$56)),ABS(Dashboard!$N$7-'13W Cash Flow'!$D$56),IF(Dashboard!$N$7='13W Cash Flow'!$D$56,0,1)) -> 0 | F42: =E42-D42 -> 0 | G42: 0.5 | H42: =IF(ABS(F42)<=G42,"PASS","FAIL") -> PASS
C44: Tolerances are set at S$0.50 for value reconciliations (rounding only) and 0.001 for count and flag checks. A variance outside tolerance is a modelling error, not a presentational one.
